Workbook

Sheet B1. B
B2: Boron
B3: (quantities are representative of quantified form listed below, unless otherwise specified)
B5: Byproduct Information
B6: Chemical Formula of Quantified Form: | C6: B2O3
B7: USGS Mineral Commodity Summary Page: | C7: Boron
B8: Demand Data Market Specificity: | C8: Byproduct
B9: Demand Data Resolution: | C9: Domestic
B13: Major End-Use Markets1
B14: Assigned End-Use Category | C14: End-Use | D14: Demand (kt) | E14: % of Demand | G14: The most recent Mineral Commodity Summary with quantified shares of consumption by end use is from 2024, which reports that the glass and ceramics industries account for 65% of total borates consumption, so we adopt this value. All other end uses are consolidated into "Miscellaneous Manufacturing".
B15: Glass Manufacturing | C15: Glass and ceramics | D15: – | E15: 0.65
B16: Miscellaneous Manufacturing | C16: Abrasives, cleaning products, insecticides, insulation, semiconductor production | D16: – | E16: 0.35
B17: (1) Source: USGS Mineral Commodity Summaries 2024, Boron
B21: Domestic Demand
B22: Calculation Schema: | C22: Trade Balance Estimate
B23: Description | C23: Units | D23: 2021 | E23: 2022 | F23: 2023 | G23: 2024 | H23: 2025
B24: Domestic Production1 | C24: kt | D24: =J41 -> 488 | E24: =K41 -> 532 | F24: =L41 -> 495 | G24: =M41 -> 504 | H24: =N41 -> 502
B25: Imports for Consumption2 | C25: kt | D25: =E55 -> 95.719809 | E25: =F55 -> 74.915214 | F25: =G55 -> 59.426397 | G25: =H55 -> 63.899414 | H25: =I55 -> 74.019796
B26: Domestic Exports3 | C26: kt | D26: =E62 -> 47.223602 | E26: =F62 -> 41.768599 | F26: =G62 -> 58.258883 | G26: =H62 -> 57.467468 | H26: =I62 -> 39.605678
B27: Consumption, apparent4 | C27: kt | D27: =D24+D25-D26 -> 536.49621 | E27: =E24+E25-E26 -> 565.14661 | F27: =F24+F25-F26 -> 496.16751 | G27: =G24+G25-G26 -> 510.43195 | H27: =H24+H25-H26 -> 536.41412
B28: (1) See "Domestic Production" section below
B29: (2) See "Imports and Exports" section below
B30: (3) See "Imports and Exports" section below
B31: (4) Production + Imports – Exports
B33: Demand Calculations
B34: Domestic Production
B35: To avoid disclosing proprietary information, USGS has withheld boron consumption estimates since 2006. Domestic boron production, however, is entirely attributable to two companies, chiefly U.S. Borax, a subsidiary of Rio Tinto responsible for 30% of global boron supply.1 As a publicly traded corporation, Rio Tinto publishes annual reports that disclose total production quantities for their mined metals and minerals. In the years for which both USGS and U.S. Borax production values are available (2000-2005), these values are quite similar (within 15%), supporting the assumption that U.S. Borax’s production of borates constitutes a vast majority of domestic production. Under this assumption, we adopt U.S. Borax production volumes as values for domestic boron production for 2021-2025.
B36: (1) Source: U.S. Borax
B38: Boron Production in the United States
B39: Description | C39: Units | D39: 2000 | E39: 2001 | F39: 2002 | G39: 2003 | H39: 2004 | I39: 2005 | J39: 2021 | K39: 2022 | L39: 2023 | M39: 2024 | N39: 2025
B40: Total Domestic Production1 | C40: kt | D40: 546 | E40: 536 | F40: 543 | G40: 605 | H40: 637 | I40: 612 | J40: – | K40: – | L40: – | M40: – | N40: –
B41: U.S. Borax Production2 | C41: kt | D41: 570 | E41: 549 | F41: 514 | G41: 541 | H41: 543 | I41: 540 | J41: 488 | K41: 532 | L41: 495 | M41: 504 | N41: 502
B42: (1) Source: USGS Mineral Commodity Summaries 2002-2007, Boron
B43: (2) Source: Annual Reports, Rio Tinto Corporation. Retrieved from the U.S. Securities and Exchange Commission's Electronic Data Gathering, Analysis, and Retrieval (EDGAR) system for RIO TINTO PLC (CIK 0000863064).
B45: Imports and Exports
B46: USITC tracks trade of boron products and minerals, rather than boron itself. We extract import/export quantities for key boron products and minerals from a combination of USITC statistics (for boron products) and USGS Mineral Commodity Summaries (for boron minerals). Note that these quantities are in units of gross weight of product, and are thus converted to kt of B2O3 when calculating the total.
B48: Imports for Consumption, Boron Products | K48: Assumed B2O3 content by boron product
B49: Product Name | C49: Units | D49: HTS Code | E49: 2021 | F49: 2022 | G49: 2023 | H49: 2024 | I49: 2025 | K49: Product Name | L49: Chemical Composition | M49: % B2O3
B50: Anhydrous Refined Borax1 | C50: kt gross weight | D50: 2840.11.0000 | E50: =_xlfn.XLOOKUP(_xlfn.CONCAT(_xlfn.TEXTSPLIT($D50,".")), 'S1. USITC Imports'!$B:$B,'S1. USITC Imports'!$J:$J)*_xlfn.XLOOKUP(_xlfn.CONCAT(_xlfn.TEXTSPLIT($D50,".")), 'S1. USITC Imports'!$B:$B,'S1. USITC Imports'!E:E) -> 6.01942 | F50: =_xlfn.XLOOKUP(_xlfn.CONCAT(_xlfn.TEXTSPLIT($D50,".")), 'S1. USITC Imports'!$B:$B,'S1. USITC Imports'!$J:$J)*_xlfn.XLOOKUP(_xlfn.CONCAT(_xlfn.TEXTSPLIT($D50,".")), 'S1. USITC Imports'!$B:$B,'S1. USITC Imports'!F:F) -> 5.375388 | G50: =_xlfn.XLOOKUP(_xlfn.CONCAT(_xlfn.TEXTSPLIT($D50,".")), 'S1. USITC Imports'!$B:$B,'S1. USITC Imports'!$J:$J)*_xlfn.XLOOKUP(_xlfn.CONCAT(_xlfn.TEXTSPLIT($D50,".")), 'S1. USITC Imports'!$B:$B,'S1. USITC Imports'!G:G) -> 3.15804 | H50: =_xlfn.XLOOKUP(_xlfn.CONCAT(_xlfn.TEXTSPLIT($D50,".")), 'S1. USITC Imports'!$B:$B,'S1. USITC Imports'!$J:$J)*_xlfn.XLOOKUP(_xlfn.CONCAT(_xlfn.TEXTSPLIT($D50,".")), 'S1. USITC Imports'!$B:$B,'S1. USITC Imports'!H:H) -> 2.955172 | I50: =_xlfn.XLOOKUP(_xlfn.CONCAT(_xlfn.TEXTSPLIT($D50,".")), 'S1. USITC Imports'!$B:$B,'S1. USITC Imports'!$J:$J)*_xlfn.XLOOKUP(_xlfn.CONCAT(_xlfn.TEXTSPLIT($D50,".")), 'S1. USITC Imports'!$B:$B,'S1. USITC Imports'!I:I) -> 4.371018 | K50: Anhydrous Refined Borax1 | L50: Na2B4O7 | M50: 0.35
B51: Non-Anhydrous Refined Borax1 | C51: kt gross weight | D51: 2840.19.0000 | E51: =_xlfn.XLOOKUP(_xlfn.CONCAT(_xlfn.TEXTSPLIT($D51,".")), 'S1. USITC Imports'!$B:$B,'S1. USITC Imports'!$J:$J)*_xlfn.XLOOKUP(_xlfn.CONCAT(_xlfn.TEXTSPLIT($D51,".")), 'S1. USITC Imports'!$B:$B,'S1. USITC Imports'!E:E) -> 225.92562 | F51: =_xlfn.XLOOKUP(_xlfn.CONCAT(_xlfn.TEXTSPLIT($D51,".")), 'S1. USITC Imports'!$B:$B,'S1. USITC Imports'!$J:$J)*_xlfn.XLOOKUP(_xlfn.CONCAT(_xlfn.TEXTSPLIT($D51,".")), 'S1. USITC Imports'!$B:$B,'S1. USITC Imports'!F:F) -> 162.30749 | G51: =_xlfn.XLOOKUP(_xlfn.CONCAT(_xlfn.TEXTSPLIT($D51,".")), 'S1. USITC Imports'!$B:$B,'S1. USITC Imports'!$J:$J)*_xlfn.XLOOKUP(_xlfn.CONCAT(_xlfn.TEXTSPLIT($D51,".")), 'S1. USITC Imports'!$B:$B,'S1. USITC Imports'!G:G) -> 152.40779 | H51: =_xlfn.XLOOKUP(_xlfn.CONCAT(_xlfn.TEXTSPLIT($D51,".")), 'S1. USITC Imports'!$B:$B,'S1. USITC Imports'!$J:$J)*_xlfn.XLOOKUP(_xlfn.CONCAT(_xlfn.TEXTSPLIT($D51,".")), 'S1. USITC Imports'!$B:$B,'S1. USITC Imports'!H:H) -> 147.19724 | I51: =_xlfn.XLOOKUP(_xlfn.CONCAT(_xlfn.TEXTSPLIT($D51,".")), 'S1. USITC Imports'!$B:$B,'S1. USITC Imports'!$J:$J)*_xlfn.XLOOKUP(_xlfn.CONCAT(_xlfn.TEXTSPLIT($D51,".")), 'S1. USITC Imports'!$B:$B,'S1. USITC Imports'!I:I) -> 143.31122 | K51: Non-Anhydrous Refined Borax1 | L51: Na2B4O7 · 10H2O | M51: 0.18
B52: Boric Acid1 | C52: kt gross weight | D52: 2810.00.0000 | E52: =_xlfn.XLOOKUP(_xlfn.CONCAT(_xlfn.TEXTSPLIT($D52,".")), 'S1. USITC Imports'!$B:$B,'S1. USITC Imports'!$J:$J)*_xlfn.XLOOKUP(_xlfn.CONCAT(_xlfn.TEXTSPLIT($D52,".")), 'S1. USITC Imports'!$B:$B,'S1. USITC Imports'!E:E) -> 54.19 | F52: =_xlfn.XLOOKUP(_xlfn.CONCAT(_xlfn.TEXTSPLIT($D52,".")), 'S1. USITC Imports'!$B:$B,'S1. USITC Imports'!$J:$J)*_xlfn.XLOOKUP(_xlfn.CONCAT(_xlfn.TEXTSPLIT($D52,".")), 'S1. USITC Imports'!$B:$B,'S1. USITC Imports'!F:F) -> 48.158 | G52: =_xlfn.XLOOKUP(_xlfn.CONCAT(_xlfn.TEXTSPLIT($D52,".")), 'S1. USITC Imports'!$B:$B,'S1. USITC Imports'!$J:$J)*_xlfn.XLOOKUP(_xlfn.CONCAT(_xlfn.TEXTSPLIT($D52,".")), 'S1. USITC Imports'!$B:$B,'S1. USITC Imports'!G:G) -> 37.978 | H52: =_xlfn.XLOOKUP(_xlfn.CONCAT(_xlfn.TEXTSPLIT($D52,".")), 'S1. USITC Imports'!$B:$B,'S1. USITC Imports'!$J:$J)*_xlfn.XLOOKUP(_xlfn.CONCAT(_xlfn.TEXTSPLIT($D52,".")), 'S1. USITC Imports'!$B:$B,'S1. USITC Imports'!H:H) -> 42.535 | I52: =_xlfn.XLOOKUP(_xlfn.CONCAT(_xlfn.TEXTSPLIT($D52,".")), 'S1. USITC Imports'!$B:$B,'S1. USITC Imports'!$J:$J)*_xlfn.XLOOKUP(_xlfn.CONCAT(_xlfn.TEXTSPLIT($D52,".")), 'S1. USITC Imports'!$B:$B,'S1. USITC Imports'!I:I) -> 52.382 | K52: Boric Acid2 | L52: H3BO3 | M52: 0.56
B53: Colemanite2 | C53: kt gross weight | D53: – | E53: 3 | F53: 1 | G53: 2 | H53: 1 | I53: 2 | K53: Colemanite2 | L53: Ca2B6O11·5H2O | M53: 0.51
B54: Ulexite2 | C54: kt gross weight | D54: – | E54: 49 | F54: 38 | G54: 20 | H54: 28 | I54: 38 | K54: Ulexite2 | L54: NaCaB5O9·8H2O | M54: 0.43
B55: Total3 | C55: kt | D55: – | E55: =SUMPRODUCT(E50:E54,$M50:$M54) -> 95.719809 | F55: =SUMPRODUCT(F50:F54,$M50:$M54) -> 74.915214 | G55: =SUMPRODUCT(G50:G54,$M50:$M54) -> 59.426397 | H55: =SUMPRODUCT(H50:H54,$M50:$M54) -> 63.899414 | I55: =SUMPRODUCT(I50:I54,$M50:$M54) -> 74.019796 | K55: (1) Calculated from molcular weight ratio between B2O3 and product composition.
B56: (1) Source: USITC DataWeb, Imports for Consumption | K56: (2) Extracted from Table 2 of USGS Minerals Yearbook 2023, Boron
B57: (2) Source: USGS Mineral Commodity Summaries 2026, Boron
B58: (3) Individual product quantities converted to kt of B2O3 content before aggregation
B60: Domestic Exports, Boron Products
B61: Product Name | C61: Units | D61: HTS Code | E61: 2021 | F61: 2022 | G61: 2023 | H61: 2024 | I61: 2025
B62: Anhydrous Refined Borax1 | C62: kt gross weight | D62: 2840.11.0000 | E62: =_xlfn.XLOOKUP(_xlfn.CONCAT(_xlfn.TEXTSPLIT($D62,".")), 'S2. USITC Exports'!$B:$B,'S2. USITC Exports'!$J:$J)*_xlfn.XLOOKUP(_xlfn.CONCAT(_xlfn.TEXTSPLIT($D62,".")), 'S2. USITC Exports'!$B:$B,'S2. USITC Exports'!E:E) -> 47.223602 | F62: =_xlfn.XLOOKUP(_xlfn.CONCAT(_xlfn.TEXTSPLIT($D62,".")), 'S2. USITC Exports'!$B:$B,'S2. USITC Exports'!$J:$J)*_xlfn.XLOOKUP(_xlfn.CONCAT(_xlfn.TEXTSPLIT($D62,".")), 'S2. USITC Exports'!$B:$B,'S2. USITC Exports'!F:F) -> 41.768599 | G62: =_xlfn.XLOOKUP(_xlfn.CONCAT(_xlfn.TEXTSPLIT($D62,".")), 'S2. USITC Exports'!$B:$B,'S2. USITC Exports'!$J:$J)*_xlfn.XLOOKUP(_xlfn.CONCAT(_xlfn.TEXTSPLIT($D62,".")), 'S2. USITC Exports'!$B:$B,'S2. USITC Exports'!G:G) -> 58.258883 | H62: =_xlfn.XLOOKUP(_xlfn.CONCAT(_xlfn.TEXTSPLIT($D62,".")), 'S2. USITC Exports'!$B:$B,'S2. USITC Exports'!$J:$J)*_xlfn.XLOOKUP(_xlfn.CONCAT(_xlfn.TEXTSPLIT($D62,".")), 'S2. USITC Exports'!$B:$B,'S2. USITC Exports'!H:H) -> 57.467468 | I62: =_xlfn.XLOOKUP(_xlfn.CONCAT(_xlfn.TEXTSPLIT($D62,".")), 'S2. USITC Exports'!$B:$B,'S2. USITC Exports'!$J:$J)*_xlfn.XLOOKUP(_xlfn.CONCAT(_xlfn.TEXTSPLIT($D62,".")), 'S2. USITC Exports'!$B:$B,'S2. USITC Exports'!I:I) -> 39.605678
B63: Non-Anhydrous Refined Borax1 | C63: kt gross weight | D63: 2840.19.0000 | E63: =_xlfn.XLOOKUP(_xlfn.CONCAT(_xlfn.TEXTSPLIT($D63,".")), 'S2. USITC Exports'!$B:$B,'S2. USITC Exports'!$J:$J)*_xlfn.XLOOKUP(_xlfn.CONCAT(_xlfn.TEXTSPLIT($D63,".")), 'S2. USITC Exports'!$B:$B,'S2. USITC Exports'!E:E) -> 559.53619 | F63: =_xlfn.XLOOKUP(_xlfn.CONCAT(_xlfn.TEXTSPLIT($D63,".")), 'S2. USITC Exports'!$B:$B,'S2. USITC Exports'!$J:$J)*_xlfn.XLOOKUP(_xlfn.CONCAT(_xlfn.TEXTSPLIT($D63,".")), 'S2. USITC Exports'!$B:$B,'S2. USITC Exports'!F:F) -> 609.48612 | G63: =_xlfn.XLOOKUP(_xlfn.CONCAT(_xlfn.TEXTSPLIT($D63,".")), 'S2. USITC Exports'!$B:$B,'S2. USITC Exports'!$J:$J)*_xlfn.XLOOKUP(_xlfn.CONCAT(_xlfn.TEXTSPLIT($D63,".")), 'S2. USITC Exports'!$B:$B,'S2. USITC Exports'!G:G) -> 545.6871 | H63: =_xlfn.XLOOKUP(_xlfn.CONCAT(_xlfn.TEXTSPLIT($D63,".")), 'S2. USITC Exports'!$B:$B,'S2. USITC Exports'!$J:$J)*_xlfn.XLOOKUP(_xlfn.CONCAT(_xlfn.TEXTSPLIT($D63,".")), 'S2. USITC Exports'!$B:$B,'S2. USITC Exports'!H:H) -> 597.38218 | I63: =_xlfn.XLOOKUP(_xlfn.CONCAT(_xlfn.TEXTSPLIT($D63,".")), 'S2. USITC Exports'!$B:$B,'S2. USITC Exports'!$J:$J)*_xlfn.XLOOKUP(_xlfn.CONCAT(_xlfn.TEXTSPLIT($D63,".")), 'S2. USITC Exports'!$B:$B,'S2. USITC Exports'!I:I) -> 514.04751
B64: Boric Acid1 | C64: kt gross weight | D64: 2810.00.0000 | E64: =_xlfn.XLOOKUP(_xlfn.CONCAT(_xlfn.TEXTSPLIT($D64,".")), 'S2. USITC Exports'!$B:$B,'S2. USITC Exports'!$J:$J)*_xlfn.XLOOKUP(_xlfn.CONCAT(_xlfn.TEXTSPLIT($D64,".")), 'S2. USITC Exports'!$B:$B,'S2. USITC Exports'!E:E) -> 279.788 | F64: =_xlfn.XLOOKUP(_xlfn.CONCAT(_xlfn.TEXTSPLIT($D64,".")), 'S2. USITC Exports'!$B:$B,'S2. USITC Exports'!$J:$J)*_xlfn.XLOOKUP(_xlfn.CONCAT(_xlfn.TEXTSPLIT($D64,".")), 'S2. USITC Exports'!$B:$B,'S2. USITC Exports'!F:F) -> 239.121 | G64: =_xlfn.XLOOKUP(_xlfn.CONCAT(_xlfn.TEXTSPLIT($D64,".")), 'S2. USITC Exports'!$B:$B,'S2. USITC Exports'!$J:$J)*_xlfn.XLOOKUP(_xlfn.CONCAT(_xlfn.TEXTSPLIT($D64,".")), 'S2. USITC Exports'!$B:$B,'S2. USITC Exports'!G:G) -> 253.119 | H64: =_xlfn.XLOOKUP(_xlfn.CONCAT(_xlfn.TEXTSPLIT($D64,".")), 'S2. USITC Exports'!$B:$B,'S2. USITC Exports'!$J:$J)*_xlfn.XLOOKUP(_xlfn.CONCAT(_xlfn.TEXTSPLIT($D64,".")), 'S2. USITC Exports'!$B:$B,'S2. USITC Exports'!H:H) -> 246.044 | I64: =_xlfn.XLOOKUP(_xlfn.CONCAT(_xlfn.TEXTSPLIT($D64,".")), 'S2. USITC Exports'!$B:$B,'S2. USITC Exports'!$J:$J)*_xlfn.XLOOKUP(_xlfn.CONCAT(_xlfn.TEXTSPLIT($D64,".")), 'S2. USITC Exports'!$B:$B,'S2. USITC Exports'!I:I) -> 247.883
B65: Total | C65: kt | D65: – | E65: =SUMPRODUCT(E62:E64,$M50:$M52) -> 273.92605 | F65: =SUMPRODUCT(F62:F64,$M50:$M52) -> 258.23427 | G65: =SUMPRODUCT(G62:G64,$M50:$M52) -> 260.36093 | H65: =SUMPRODUCT(H62:H64,$M50:$M52) -> 265.42705 | I65: =SUMPRODUCT(I62:I64,$M50:$M52) -> 245.20502
B66: (1) Source: USITC DataWeb, Domestic Exports
B70: Pricing
B71: Description | C71: Units | D71: 2021 | E71: 2022 | F71: 2023 | G71: 2024 | H71: 2025
B72: Price, average unit value of combined imports, cost, insurance, and freight1 | C72: $/t | D72: 394 | E72: 485 | F72: 606 | G72: 574 | H72: 540
B73: (2) Source: USGS Mineral Commodity Summaries 2026, Boron

Sheet B2. BaSO4
B2: Barium Sulfate
B3: (quantities are representative of quantified form listed below, unless otherwise specified)
B5: Byproduct Information
B6: Chemical Formula of Quantified Form: | C6: BaSO4
B7: USGS Mineral Commodity Summary Page: | C7: Barite
B8: Demand Data Market Specificity: | C8: Byproduct
B9: Demand Data Resolution: | C9: Domestic
B13: Major End-Use Markets1
B14: Assigned End-Use Category | C14: End-Use | D14: Demand (kt) | E14: % of Demand | G14: More than 90% of barite sold in the US is used as a weighting agent in oil and gas well drilling fluids. Barite also has several other applications in materials manufacturing (e.g. paints, plastics, rubber, etc.), which we collapse into the “Miscellaneous Manufacturing” category.
B15: Oil and Gas Drilling | C15: Weighting agent in oil and gas drilling fluids | D15: – | E15: 0.9
B16: Miscellaneous Manufacturing | C16: Filler, extender, weighting agent; metal casting; concrete aggregate; X-ray contrast | D16: – | E16: 0.1
B17: (1) Source: USGS Mineral Commodity Summaries 2026, Barite
B21: Domestic Demand
B22: Calculation Schema: | C22: Trade Balance Estimate
B23: Description | C23: Units | D23: 2021 | E23: 2022 | F23: 2023 | G23: 2024 | H23: 2025
B24: Domestic Production1 | C24: kt | D24: =D39 -> 1670 | E24: =E39 -> 2220 | F24: =F39 -> 2260 | G24: =G39 -> 2280 | H24: =H39 -> 2300
B25: Imports for Consumption2 | C25: kt | D25: =E48 -> 1202.236 | E25: =F48 -> 1683.152 | F25: =G48 -> 1413.413 | G25: =H48 -> 1440.243 | H25: =I48 -> 1465.785
B26: Domestic Exports3 | C26: kt | D26: =E55 -> 61.577952 | E26: =F55 -> 86.500848 | F26: =G55 -> 74.706951 | G26: =H55 -> 65.029602 | H26: =I55 -> 63.938504
B27: Consumption, apparent4 | C27: kt | D27: =D24+D25-D26 -> 2810.658 | E27: =E24+E25-E26 -> 3816.6512 | F27: =F24+F25-F26 -> 3598.706 | G27: =G24+G25-G26 -> 3655.2134 | H27: =H24+H25-H26 -> 3701.8465
B28: (1) See "Domestic Production" section below
B29: (2) See "Imports and Exports" section below
B30: (3) See "Imports and Exports" section below
B31: (4) Production + Imports – Exports
B33: Demand Calculations
B34: Domestic Production
B35: To avoid disclosing proprietary information, USGS has withheld total barite consumption (crude + ground and crushed) estimates since 2017. They do, however, report production of ground and crushed barite, which is the form of barite more relevant in this context.
B37: Domestic Production, Crushed and Ground Barite
B38: Description | C38: Units | D38: 2021 | E38: 2022 | F38: 2023 | G38: 2024 | H38: 2025
B39: Production1 | C39: kt | D39: 1670 | E39: 2220 | F39: 2260 | G39: 2280 | H39: 2300
B40: (1) Source: USGS Mineral Commodity Summaries 2026, Barite
B42: Imports and Exports
B43: While USITC tracks imports for ground barium sulfate (HTS Code 2511.10.1000), barium sulfate exports are tracked through HTS Codes 2511.10.0000 (Natural Barium Sulfate) and 2833.27.0000 (Barium Sulfate), which would include, but not be exclusive to, ground barium sulfate. Nevertheless, we treat these exports as representative of ground barium sulfate, which should have minimal affect on our consumption estimates, given the relative insignificance of export quantities in this trade balance.
B45: Imports for Consumption, Barium Sulfate
B46: Product Name | C46: Units | D46: HTS Code | E46: 2021 | F46: 2022 | G46: 2023 | H46: 2024 | I46: 2025
B47: Natural Barium Sulfate, Ground1 | C47: kt | D47: 2511.10.1000 | E47: =_xlfn.XLOOKUP(_xlfn.CONCAT(_xlfn.TEXTSPLIT($D47,".")), 'S1. USITC Imports'!$B:$B,'S1. USITC Imports'!$J:$J)*_xlfn.XLOOKUP(_xlfn.CONCAT(_xlfn.TEXTSPLIT($D47,".")), 'S1. USITC Imports'!$B:$B,'S1. USITC Imports'!E:E) -> 1202.236 | F47: =_xlfn.XLOOKUP(_xlfn.CONCAT(_xlfn.TEXTSPLIT($D47,".")), 'S1. USITC Imports'!$B:$B,'S1. USITC Imports'!$J:$J)*_xlfn.XLOOKUP(_xlfn.CONCAT(_xlfn.TEXTSPLIT($D47,".")), 'S1. USITC Imports'!$B:$B,'S1. USITC Imports'!F:F) -> 1683.152 | G47: =_xlfn.XLOOKUP(_xlfn.CONCAT(_xlfn.TEXTSPLIT($D47,".")), 'S1. USITC Imports'!$B:$B,'S1. USITC Imports'!$J:$J)*_xlfn.XLOOKUP(_xlfn.CONCAT(_xlfn.TEXTSPLIT($D47,".")), 'S1. USITC Imports'!$B:$B,'S1. USITC Imports'!G:G) -> 1413.413 | H47: =_xlfn.XLOOKUP(_xlfn.CONCAT(_xlfn.TEXTSPLIT($D47,".")), 'S1. USITC Imports'!$B:$B,'S1. USITC Imports'!$J:$J)*_xlfn.XLOOKUP(_xlfn.CONCAT(_xlfn.TEXTSPLIT($D47,".")), 'S1. USITC Imports'!$B:$B,'S1. USITC Imports'!H:H) -> 1440.243 | I47: =_xlfn.XLOOKUP(_xlfn.CONCAT(_xlfn.TEXTSPLIT($D47,".")), 'S1. USITC Imports'!$B:$B,'S1. USITC Imports'!$J:$J)*_xlfn.XLOOKUP(_xlfn.CONCAT(_xlfn.TEXTSPLIT($D47,".")), 'S1. USITC Imports'!$B:$B,'S1. USITC Imports'!I:I) -> 1465.785
B48: Total | C48: kt | D48: – | E48: =E47 -> 1202.236 | F48: =F47 -> 1683.152 | G48: =G47 -> 1413.413 | H48: =H47 -> 1440.243 | I48: =I47 -> 1465.785
B49: (1) Source: USITC DataWeb, Imports for Consumption
B51: Domestic Exports, Boron Products
B52: Product Name | C52: Units | D52: HTS Code | E52: 2021 | F52: 2022 | G52: 2023 | H52: 2024 | I52: 2025
B53: Natural Barium Sulfate1 | C53: kt | D53: 2511.10.0000 | E53: =_xlfn.XLOOKUP(_xlfn.CONCAT(_xlfn.TEXTSPLIT($D53,".")), 'S2. USITC Exports'!$B:$B,'S2. USITC Exports'!$J:$J)*_xlfn.XLOOKUP(_xlfn.CONCAT(_xlfn.TEXTSPLIT($D53,".")), 'S2. USITC Exports'!$B:$B,'S2. USITC Exports'!E:E) -> 53.05 | F53: =_xlfn.XLOOKUP(_xlfn.CONCAT(_xlfn.TEXTSPLIT($D53,".")), 'S2. USITC Exports'!$B:$B,'S2. USITC Exports'!$J:$J)*_xlfn.XLOOKUP(_xlfn.CONCAT(_xlfn.TEXTSPLIT($D53,".")), 'S2. USITC Exports'!$B:$B,'S2. USITC Exports'!F:F) -> 77.075 | G53: =_xlfn.XLOOKUP(_xlfn.CONCAT(_xlfn.TEXTSPLIT($D53,".")), 'S2. USITC Exports'!$B:$B,'S2. USITC Exports'!$J:$J)*_xlfn.XLOOKUP(_xlfn.CONCAT(_xlfn.TEXTSPLIT($D53,".")), 'S2. USITC Exports'!$B:$B,'S2. USITC Exports'!G:G) -> 61.975 | H53: =_xlfn.XLOOKUP(_xlfn.CONCAT(_xlfn.TEXTSPLIT($D53,".")), 'S2. USITC Exports'!$B:$B,'S2. USITC Exports'!$J:$J)*_xlfn.XLOOKUP(_xlfn.CONCAT(_xlfn.TEXTSPLIT($D53,".")), 'S2. USITC Exports'!$B:$B,'S2. USITC Exports'!H:H) -> 53.134 | I53: =_xlfn.XLOOKUP(_xlfn.CONCAT(_xlfn.TEXTSPLIT($D53,".")), 'S2. USITC Exports'!$B:$B,'S2. USITC Exports'!$J:$J)*_xlfn.XLOOKUP(_xlfn.CONCAT(_xlfn.TEXTSPLIT($D53,".")), 'S2. USITC Exports'!$B:$B,'S2. USITC Exports'!I:I) -> 53.879
B54: Barium Sulfate1 | C54: kt | D54: 2833.27.0000 | E54: =_xlfn.XLOOKUP(_xlfn.CONCAT(_xlfn.TEXTSPLIT($D54,".")), 'S2. USITC Exports'!$B:$B,'S2. USITC Exports'!$J:$J)*_xlfn.XLOOKUP(_xlfn.CONCAT(_xlfn.TEXTSPLIT($D54,".")), 'S2. USITC Exports'!$B:$B,'S2. USITC Exports'!E:E) -> 8.527952 | F54: =_xlfn.XLOOKUP(_xlfn.CONCAT(_xlfn.TEXTSPLIT($D54,".")), 'S2. USITC Exports'!$B:$B,'S2. USITC Exports'!$J:$J)*_xlfn.XLOOKUP(_xlfn.CONCAT(_xlfn.TEXTSPLIT($D54,".")), 'S2. USITC Exports'!$B:$B,'S2. USITC Exports'!F:F) -> 9.425848 | G54: =_xlfn.XLOOKUP(_xlfn.CONCAT(_xlfn.TEXTSPLIT($D54,".")), 'S2. USITC Exports'!$B:$B,'S2. USITC Exports'!$J:$J)*_xlfn.XLOOKUP(_xlfn.CONCAT(_xlfn.TEXTSPLIT($D54,".")), 'S2. USITC Exports'!$B:$B,'S2. USITC Exports'!G:G) -> 12.731951 | H54: =_xlfn.XLOOKUP(_xlfn.CONCAT(_xlfn.TEXTSPLIT($D54,".")), 'S2. USITC Exports'!$B:$B,'S2. USITC Exports'!$J:$J)*_xlfn.XLOOKUP(_xlfn.CONCAT(_xlfn.TEXTSPLIT($D54,".")), 'S2. USITC Exports'!$B:$B,'S2. USITC Exports'!H:H) -> 11.895602 | I54: =_xlfn.XLOOKUP(_xlfn.CONCAT(_xlfn.TEXTSPLIT($D54,".")), 'S2. USITC Exports'!$B:$B,'S2. USITC Exports'!$J:$J)*_xlfn.XLOOKUP(_xlfn.CONCAT(_xlfn.TEXTSPLIT($D54,".")), 'S2. USITC Exports'!$B:$B,'S2. USITC Exports'!I:I) -> 10.059504
B55: Total | C55: kt | D55: – | E55: =SUM(E53:E54) -> 61.577952 | F55: =SUM(F53:F54) -> 86.500848 | G55: =SUM(G53:G54) -> 74.706951 | H55: =SUM(H53:H54) -> 65.029602 | I55: =SUM(I53:I54) -> 63.938504
B56: (1) Source: USITC DataWeb, Domestic Exports
B60: Pricing
B61: Description | C61: Units | D61: 2021 | E61: 2022 | F61: 2023 | G61: 2024 | H61: 2025
B62: Price, average unit value, ground, ex-works1 | C62: $/t | D62: 167 | E62: 145 | F62: 218 | G62: 210 | H62: 210
B63: (1) Source: USGS Mineral Commodity Summaries 2026, Barite

Sheet B3. Br
B2: Bromine
B3: (quantities are representative of quantified form listed below, unless otherwise specified)
B5: Byproduct Information
B6: Chemical Formula of Quantified Form: | C6: Br
B7: USGS Mineral Commodity Summary Page: | C7: Bromine
B8: Demand Data Market Specificity: | C8: Byproduct
B9: Demand Data Resolution: | C9: Domestic
B13: Major End-Use Markets1
B14: Assigned End-Use Category | C14: End-Use | D14: Demand (kt) | E14: % of Demand | G14: The 2026 USGS Mineral Commodity Summary for Bromine lists production of brominated flame retardants (BFRs) and clear brine drilling fluids as the leading global applications of bromine, but do not provide quantitative market shares for any end use. We instead derive percent of demand by end use from Ullmann’s Encyclopedia for Industrial Chemistry, which lists a similar set of end uses on the global scale. We assume that domestic bromine market shares by end use mirror global proportions, with the exception of pesticide manufacturing, as the EPA has phased out production and consumption of methyl bromide fumigants due to ozone depletion concerns.1 After removal of pesticide manufacturing, we reallocate all other market shares to total 100%.
B15: Miscellaneous Chemical Manufacturing | C15: Flame retardant | D15: 483000 | E15: =D15/SUM($D$15:$D$19) -> 0.5894557
B16: Oil and Gas Drilling | C16: Drilling fluids | D16: 103500 | E16: =D16/SUM($D$15:$D$19) -> 0.12631194
B17: Organic Chemical Manufacturing | C17: Organic synthesis | D17: 86300 | E17: =D17/SUM($D$15:$D$19) -> 0.10532097
B18: Pharmaceutical Manufacturing | C18: Pharmaceuticals | D18: 77600 | E18: =D18/SUM($D$15:$D$19) -> 0.094703442
B19: Industrial Water Treatment | C19: Water treatment | D19: 69000 | E19: =D19/SUM($D$15:$D$19) -> 0.084207957
B20: (1) Source: Ullmann's Encyclopedia for Industrial Chemistry, Bromine | G20: (1) U.S. Environmental Protection Agency
B24: Domestic Demand
B25: Calculation Schema: | C25: Trade Balance Estimate
B26: Description | C26: Units | D26: 2021 | E26: 2022 | F26: 2023 | G26: 2024 | H26: 2025
B27: Domestic Production1 | C27: kt | D27: =D47 -> 201 | E27: =E47 -> 203 | F27: =F47 -> 195 | G27: =G47 -> 195 | H27: =H47 -> 199
B28: Imports for Consumption2 | C28: kt | D28: =D55 -> 27.2 | E28: =E55 -> 36.5 | F28: =F55 -> 50.8 | G28: =G55 -> 58.3 | H28: =H55 -> 40
B29: Domestic Exports3 | C29: kt | D29: =D60 -> 27.9 | E29: =E60 -> 19.4 | F29: =F60 -> 38.9 | G29: =G60 -> 33.8 | H29: =H60 -> 33
B30: Consumption, apparent4 | C30: kt | D30: =D27+D28-D29 -> 200.3 | E30: =E27+E28-E29 -> 220.1 | F30: =F27+F28-F29 -> 206.9 | G30: =G27+G28-G29 -> 219.5 | H30: =H27+H28-H29 -> 206
B31: (1) See "Domestic Production" section below
B32: (2) See "Imports and Exports" section below
B33: (3) See "Imports and Exports" section below
B34: (4) Production + Imports – Exports
B36: Demand Calculations
B37: Domestic Production
B38: To avoid disclosing proprietary information, USGS has withheld bromine consumption and production estimates since 2006. Domestic bromine production, however, is entirely attributable to two companies in Arkansas: Albemarle Corporation and Chemtura.1, 2 Since 2020, Albemarle Corporation has disclosed its annual aggregate bromine production in the US in its annual reports. Chemtura, on the other hand, was acquired by German company LANXESS AG in 2017 and withholds its production data as proprietary.3 The most recent measure of both companies’ annual bromine production capacities reported a value of 148 kt for Albemarle and 130 kt for Chemtura.2 To remain conservative in our consumption estimates, we assume Chemtura's annual production is equal to their capacity, and add it to reported Albemarle production to get total domestic production of Bromine.
B39: (1) Source: USGS Mineral Commodity Summaries 2026, Bromine
B40: (2) Source: Arkansas Geological Survey
B41: (3) Source: LANXESS AG
B43: Domestic Production, Bromine
B44: Description | C44: Units | D44: 2021 | E44: 2022 | F44: 2023 | G44: 2024 | H44: 2025
B45: Albemarle Corporation Production1 | C45: kt | D45: 71 | E45: 73 | F45: 65 | G45: 65 | H45: 69
B46: Assumed Chemtura Production2 | C46: kt | D46: 130 | E46: 130 | F46: 130 | G46: 130 | H46: 130
B47: Total Domestic Production | C47: kt | D47: =D45+D46 -> 201 | E47: =E45+E46 -> 203 | F47: =F45+F46 -> 195 | G47: =G45+G46 -> 195 | H47: =H45+H46 -> 199
B48: (1) Source: Annual Reports, Albemarle Corporation. Retrieved from the U.S. Securities and Exchange Commission's Electronic Data Gathering, Analysis, and Retrieval (EDGAR) system for ALBEMARLE CORP (CIK 0000915913).
B49: (2) Assumed based on reported capacity of Chemtura bromine facilities (Arkansas Geological Survey)
B51: Imports and Exports
B53: Imports for Consumption, Bromine
B54: Product Name | C54: Units | D54: 2021 | E54: 2022 | F54: 2023 | G54: 2024 | H54: 2025
B55: Imports for consumption, elemental bromine and compounds1 | C55: kt | D55: 27.2 | E55: 36.5 | F55: 50.8 | G55: 58.3 | H55: 40
B56: (1) Source: USGS Mineral Commodity Summaries 2026, Bromine
B58: Domestic Exports, Bromine
B59: Product Name | C59: Units | D59: 2021 | E59: 2022 | F59: 2023 | G59: 2024 | H59: 2025
B60: Exports, elemental bromine and compounds1 | C60: kt | D60: 27.9 | E60: 19.4 | F60: 38.9 | G60: 33.8 | H60: 33
B61: (1) Source: USGS Mineral Commodity Summaries 2026, Bromine
B65: Pricing
B66: Description | C66: Units | D66: 2021 | E66: 2022 | F66: 2023 | G66: 2024 | H66: 2025
B67: Price, average unit value of imports (cost, insurance, and freight)1 | C67: $/kg | D67: 2.85 | E67: 3.29 | F67: 2.92 | G67: 2.7 | H67: 3
B68: Price, average unit value of imports (cost, insurance, and freight)2 | C68: $/t | D68: =D67*907.2 -> 2585.52 | E68: =E67*907.2 -> 2984.688 | F68: =F67*907.2 -> 2649.024 | G68: =G67*907.2 -> 2449.44 | H68: =H67*907.2 -> 2721.6
B69: (1) Source: USGS Mineral Commodity Summaries 2026, Bromine
B70: (2) Converted from $/kg to $/t

Sheet B4. CaCO3
B2: Calcium Carbonate
B3: (quantities are representative of quantified form listed below, unless otherwise specified)
B5: Byproduct Information
B6: Chemical Formula of Quantified Form: | C6: CaCO3
B7: USGS Mineral Commodity Summary Page: | C7: Stone (Crushed)
B8: Demand Data Market Specificity: | C8: Byproduct-Market
B9: Demand Data Resolution: | C9: State
B13: Major End-Use Markets1
B14: Assigned End-Use Category | C14: End-Use | D14: Demand (kt) | E14: % of Demand | G14: Major end use markets for limestone (CaCO3) are reported and quantified in Table 10 of the most recent USGS Minerals Yearbook (2023) for Crushed Stone. We consider all end uses listed for limestone with the exception of Construction Aggregate, as precipitated calcium carbonate from brines would not be sufficiently coarse for this end use. With shares of remaining demand less than 5%, agricultural uses and sulfur dioxide removal are consolidated into the “Other” category and ignored, leaving Cement and Lime Manufacturing as the key domestic end uses of (precipitated) calcium carbonate.
B15: Other | C15: Agricultural uses | D15: 13004 | E15: =D15/SUM($D$15:$D$19) -> 0.018516251
B16: Cement Manufacturing | C16: Cement Manufacture | D16: 110000 | E16: =D16/SUM($D$15:$D$19) -> 0.15662778
B17: Lime Manufacturing | C17: Lime Manufacture | D17: 32500 | E17: =D17/SUM($D$15:$D$19) -> 0.046276388
B18: Other | C18: Sulfur oxide removal | D18: 4120 | E18: =D18/SUM($D$15:$D$19) -> 0.0058664221
B19: Other | C19: Miscellaneous and unspecified uses | D19: 542678 | E19: =D19/SUM($D$15:$D$19) -> 0.77271316
B20: (1) Source: USGS Minerals Yearbook 2023, Stone (Crushed)
B26: State-Level Demand by End-Use
B27: In all of its publications, USGS typically groups limestone and dolomite statistics, making it difficult to extract an isolated demand for limestone. Within these key end use markets (cement and lime manufacturing), however, both limestone and dolomite are suitable, interchangeable raw materials, so their aggregate demand in these markets can still be considered an upper bound on calcium carbonate demand.
B28: USGS Minerals Yearbook, Stone (Crushed) reports limestone and dolomite sale/use at a state level for both cement and lime manufacturing for years 2021, 2022, and 2023. Because imports/export volumes of all types of crushed stone are negligible compared to domestic production/consumption1, we use these values directly and distribute the total quantities withheld among the remaining states using the appropriate disaggregation proxies.
B29: For years 2024 and 2025, state level data is not yet available, so we disaggregate total byproduct-market demand using the same proxies. To estimate byproduct-market demand, we first assume that limestone and dolomite account for 70% of total crushed stone consumption in the US, a reasonable assumption given that limestone and dolomite account for 70% of domestic crushed stone production and imports and exports are relatively negligible compared to these volumes.1 We then calculate the fraction of total domestic demand attributable to each end use based on the table above.
B30: (1) Source: USGS Mineral Commodity Summaries 2026, Stone (Crushed)
B32: Cement Manufacturing1,2
B33: State | C33: Units | D33: 2021 | E33: 2022 | F33: 2023 | G33: 2024 | H33: 2025
B34: Alabama | C34: kt | D34: 5200 | E34: 4180 | F34: 4660 | G34: W | H34: W
B35: Alaska | C35: kt | D35: 0 | E35: 0 | F35: 0 | G35: W | H35: W
B36: Arizona | C36: kt | D36: W | E36: 3540 | F36: W | G36: W | H36: W
B37: Arkansas | C37: kt | D37: W | E37: W | F37: W | G37: W | H37: W
B38: California | C38: kt | D38: 12300 | E38: 12800 | F38: 12300 | G38: W | H38: W
B39: Colorado | C39: kt | D39: 1780 | E39: W | F39: 3140 | G39: W | H39: W
B40: Connecticut | C40: kt | D40: 0 | E40: 0 | F40: 0 | G40: W | H40: W
B41: Delaware | C41: kt | D41: 0 | E41: 0 | F41: 0 | G41: W | H41: W
B42: Florida | C42: kt | D42: 8580 | E42: 7370 | F42: 5370 | G42: W | H42: W
B43: Georgia | C43: kt | D43: 801 | E43: 617 | F43: 530 | G43: W | H43: W
B44: Hawaii | C44: kt | D44: 0 | E44: 0 | F44: 0 | G44: W | H44: W
B45: Idaho | C45: kt | D45: 0 | E45: 0 | F45: 0 | G45: W | H45: W
B46: Illinois | C46: kt | D46: W | E46: W | F46: W | G46: W | H46: W
B47: Indiana | C47: kt | D47: W | E47: 3250 | F47: 3520 | G47: W | H47: W
B48: Iowa | C48: kt | D48: 2170 | E48: 2130 | F48: 2150 | G48: W | H48: W
B49: Kansas | C49: kt | D49: W | E49: W | F49: W | G49: W | H49: W
B50: Kentucky | C50: kt | D50: 2040 | E50: 2000 | F50: 1770 | G50: W | H50: W
B51: Louisiana | C51: kt | D51: W | E51: 0 | F51: 0 | G51: W | H51: W
B52: Maine | C52: kt | D52: 466 | E52: 466 | F52: 394 | G52: W | H52: W
B53: Maryland | C53: kt | D53: 4010 | E53: 3910 | F53: 3660 | G53: W | H53: W
B54: Massachusetts | C54: kt | D54: 0 | E54: 0 | F54: 0 | G54: W | H54: W
B55: Michigan | C55: kt | D55: 4780 | E55: 5980 | F55: W | G55: W | H55: W
B56: Minnesota | C56: kt | D56: 0 | E56: 0 | F56: 0 | G56: W | H56: W
B57: Mississippi | C57: kt | D57: 0 | E57: 0 | F57: 0 | G57: W | H57: W
B58: Missouri | C58: kt | D58: 12100 | E58: 12300 | F58: 11900 | G58: W | H58: W
B59: Montana | C59: kt | D59: 781 | E59: 750 | F59: 718 | G59: W | H59: W
B60: Nebraska | C60: kt | D60: 0 | E60: W | F60: W | G60: W | H60: W
B61: Nevada | C61: kt | D61: W | E61: 464 | F61: 599 | G61: W | H61: W
B62: New Hampshire | C62: kt | D62: 0 | E62: 0 | F62: 0 | G62: W | H62: W
B63: New Jersey | C63: kt | D63: 0 | E63: 0 | F63: 0 | G63: W | H63: W
B64: New Mexico | C64: kt | D64: 494 | E64: 514 | F64: 514 | G64: W | H64: W
B65: New York | C65: kt | D65: 1910 | E65: 1940 | F65: 2150 | G65: W | H65: W
B66: North Carolina | C66: kt | D66: 0 | E66: 0 | F66: 0 | G66: W | H66: W
B67: North Dakota | C67: kt | D67: 0 | E67: 0 | F67: 0 | G67: W | H67: W
B68: Ohio | C68: kt | D68: W | E68: 1280 | F68: 1140 | G68: W | H68: W
B69: Oklahoma | C69: kt | D69: 2090 | E69: 1040 | F69: 1890 | G69: W | H69: W
B70: Oregon | C70: kt | D70: 1070 | E70: 1180 | F70: W | G70: W | H70: W
B71: Pennsylvania | C71: kt | D71: 5810 | E71: 5990 | F71: 5190 | G71: W | H71: W
B72: Rhode Island | C72: kt | D72: 0 | E72: 0 | F72: 0 | G72: W | H72: W
B73: South Carolina | C73: kt | D73: 2010 | E73: 2310 | F73: 2060 | G73: W | H73: W
B74: South Dakota | C74: kt | D74: 971 | E74: 1100 | F74: W | G74: W | H74: W
B75: Tennessee | C75: kt | D75: W | E75: W | F75: W | G75: W | H75: W
B76: Texas | C76: kt | D76: 17400 | E76: 17700 | F76: 20300 | G76: W | H76: W
B77: Utah | C77: kt | D77: W | E77: W | F77: W | G77: W | H77: W
B78: Vermont | C78: kt | D78: 0 | E78: 0 | F78: 0 | G78: W | H78: W
B79: Virginia | C79: kt | D79: 1340 | E79: 1410 | F79: 1460 | G79: W | H79: W
B80: Washington | C80: kt | D80: W | E80: 599 | F80: 637 | G80: W | H80: W
B81: West Virginia | C81: kt | D81: W | E81: W | F81: W | G81: W | H81: W
B82: Wisconsin | C82: kt | D82: 0 | E82: 0 | F82: 0 | G82: W | H82: W
B83: Wyoming | C83: kt | D83: 826 | E83: W | F83: W | G83: W | H83: W
B84: Total Withheld | C84: kt | D84: 20800 | E84: 14400 | F84: 23500 | G84: =1500000*0.7*E16 -> 164459.16 | H84: =1500000*0.7*E16 -> 164459.16
B85: W - Withheld to avoid disclosing company proprietary data; included in "Total Withheld"
B86: (1) Data for 2021-2023 extracted directly from USGS Minerals Yearbook 2022-2023, Stone (Crushed) (Table 11)
B87: (2) Data for 2024-2025 estimated at the domestic level (i.e. all states withholding) based on USGS Mineral Commodity Summaries 2026, Stone (Crushed) estimate of 1500 million metric tons of crushed stone production in 2024 and 2025.
B89: Lime Manufacturing1,2
B90: State | C90: Units | D90: 2021 | E90: 2022 | F90: 2023 | G90: 2024 | H90: 2025
B91: Alabama | C91: kt | D91: 7920 | E91: 8190 | F91: 6360 | G91: W | H91: W
B92: Alaska | C92: kt | D92: 0 | E92: 0 | F92: 0 | G92: W | H92: W
B93: Arizona | C93: kt | D93: 330 | E93: 506 | F93: 1440 | G93: W | H93: W
B94: Arkansas | C94: kt | D94: W | E94: W | F94: W | G94: W | H94: W
B95: California | C95: kt | D95: 555 | E95: W | F95: W | G95: W | H95: W
B96: Colorado | C96: kt | D96: 0 | E96: 0 | F96: 0 | G96: W | H96: W
B97: Connecticut | C97: kt | D97: 0 | E97: 0 | F97: 0 | G97: W | H97: W
B98: Delaware | C98: kt | D98: 0 | E98: 0 | F98: 0 | G98: W | H98: W
B99: Florida | C99: kt | D99: 1890 | E99: 519 | F99: 2790 | G99: W | H99: W
B100: Georgia | C100: kt | D100: 0 | E100: 0 | F100: 0 | G100: W | H100: W
B101: Hawaii | C101: kt | D101: 0 | E101: 0 | F101: 0 | G101: W | H101: W
B102: Idaho | C102: kt | D102: 0 | E102: 0 | F102: 0 | G102: W | H102: W
B103: Illinois | C103: kt | D103: 0 | E103: 0 | F103: 0 | G103: W | H103: W
B104: Indiana | C104: kt | D104: 0 | E104: 0 | F104: 0 | G104: W | H104: W
B105: Iowa | C105: kt | D105: 406 | E105: W | F105: W | G105: W | H105: W
B106: Kansas | C106: kt | D106: 0 | E106: 0 | F106: 0 | G106: W | H106: W
B107: Kentucky | C107: kt | D107: 2210 | E107: W | F107: 6 | G107: W | H107: W
B108: Louisiana | C108: kt | D108: 0 | E108: 0 | F108: 0 | G108: W | H108: W
B109: Maine | C109: kt | D109: 0 | E109: 0 | F109: 0 | G109: W | H109: W
B110: Maryland | C110: kt | D110: 0 | E110: 0 | F110: 0 | G110: W | H110: W
B111: Massachusetts | C111: kt | D111: 212 | E111: 425 | F111: 418 | G111: W | H111: W
B112: Michigan | C112: kt | D112: W | E112: W | F112: 0 | G112: W | H112: W
...

Sheet B5. CaF2
B2: Calcium Fluoride
B3: (quantities are representative of quantified form listed below, unless otherwise specified)
B5: Byproduct Information
B6: Chemical Formula of Quantified Form: | C6: CaF2
B7: USGS Mineral Commodity Summary Page: | C7: Fluorspar
B8: Demand Data Market Specificity: | C8: Byproduct
B9: Demand Data Resolution: | C9: Domestic
B13: Major End-Use Markets1
B14: Assigned End-Use Category | C14: End-Use | D14: Demand (kt) | E14: % of Demand | G14: Given the expected purity (high) and grain size (fine) of calcium fluoride recoverable from brines, we focus on acid-grade fluorspar, which is used almost exclusively to manufacture hyrofluoric acid.
B15: Hydrofluoric Acid Manufacturing | C15: HF production | D15: – | E15: 1
B16: (1) Source: USGS Mineral Commodity Summaries 2026, Fluorspar
B20: Domestic Demand
B21: Calculation Schema: | C21: Direct Report
B22: Description | C22: Units | D22: 2021 | E22: 2022 | F22: 2023 | G22: 2024 | H22: 2025 | J22: Because the US is 100% net import reliant for fluorspar, we use USGS-reported imports for consumption of acid grade fluorspar as our demand estimates.
B23: Consumpton, apparent, acid grade fluorspar1 | C23: kt | D23: 391 | E23: 448 | F23: 378 | G23: 372 | H23: 360
B24: (1) Source: USGS Mineral Commodity Summaries 2026, Fluorspar
B28: Pricing
B29: Description | C29: Units | D29: 2021 | E29: 2022 | F29: 2023 | G29: 2024 | H29: 2025
B30: Price, average unit value of imports, cost, insurance, and freight1 | C30: $/t | D30: 322 | E30: 387 | F30: 428 | G30: 464 | H30: 470
B31: (1) Source: USGS Mineral Commodity Summaries 2026, Fluorspar

Sheet B6. Ca(OH)2
B2: Calcium Hydroxide
B3: (quantities are representative of quantified form listed below, unless otherwise specified)
B5: Byproduct Information
B6: Chemical Formula of Quantified Form: | C6: Ca(OH)2
B7: USGS Mineral Commodity Summary Page: | C7: Lime
B8: Demand Data Market Specificity: | C8: Byproduct
B9: Demand Data Resolution: | C9: Domestic
B13: Major End-Use Markets1
B14: Assigned End-Use Category | C14: End-Use | D14: Demand (kt) | E14: % of Demand | G14: Major end use markets for hydrated/slaked lime (Ca(OH)2) are reported and quantified in Table 4 of the most recent USGS Minerals Yearbook for Lime (2023). We consider each listed end use at the highest level of granularity for which reasonable disaggregation proxies would still exist, and consolidate all end uses with a market share <5% into the “Other” category.
B15: Miscellaneous Chemical Manufacturing | C15: Chemical and Industrial | D15: 615 | E15: =D15/SUM(D$15:D$23) -> 0.2494929
B16: Miscellaneous Construction | C16: Asphalt, building uses, soil stabilization, etc. | D16: 878 | E16: =D16/SUM(D$15:D$23) -> 0.35618661
B17: Flue Gas Desulfurization | C17: Flue gas treatment | D17: 446 | E17: =D17/SUM(D$15:D$23) -> 0.18093306
B18: Wastewater Treatment | C18: Sludge treatment | D18: 128 | E18: =D18/SUM(D$15:D$23) -> 0.051926978
B19: Other | C19: Acid-mine drainage | D19: 47 | E19: =D19/SUM(D$15:D$23) -> 0.019066937
B20: Drinking Water Treatment | C20: Drinking water treatment | D20: 137 | E20: =D20/SUM(D$15:D$23) -> 0.055578093
B21: Other | C21: Wastewater treatment | D21: 108 | E21: =D21/SUM(D$15:D$23) -> 0.043813387
B22: Other | C22: Other environmental | D22: 43 | E22: =D22/SUM(D$15:D$23) -> 0.017444219
B23: Other | C23: Metallurgy | D23: 63 | E23: =D23/SUM(D$15:D$23) -> 0.025557809
B24: (1) Source: USGS Minerals Yearbook 2023, Lime
B28: Domestic Demand
B29: Calculation Schema: | C29: Indirect Report
B30: Description | C30: Units | D30: 2021 | E30: 2022 | F30: 2023 | G30: 2024 | H30: 2025 | J30: USGS reports total domestic lime consumption for years 2021-2025. We assume that roughly 15% of domestic lime consumption is in the form of hydrated lime (Ca(OH)2) versus quicklime (CaO), based on historical data, and scale down total lime consumption accordingly.
B31: Consumption, apparent, total lime1 | C31: kt | D31: 16600 | E31: 16800 | F31: 15800 | G31: 15000 | H31: 15000
B32: Assumed fraction of consumed lime attribuable to hydrated lime2 | C32: – | D32: 0.15 | E32: 0.15 | F32: 0.15 | G32: 0.15 | H32: 0.15
B33: Consumption, apparent, hydrated lime | C33: kt | D33: =D31*D32 -> 2490 | E33: =E31*E32 -> 2520 | F33: =F31*F32 -> 2370 | G33: =G31*G32 -> 2250 | H33: =H31*H32 -> 2250
B34: (1) Source: USGS Mineral Commodity Summaries 2026, Lime
B35: (2) Based on commercial lime sales data from Table 1 of USGS Minerals Yearbook 2023, Lime
B39: Pricing
B40: Description | C40: Units | D40: 2021 | E40: 2022 | F40: 2023 | G40: 2024 | H40: 2025
B41: Price, average value, at plant, hydrated lime1 | C41: $/t | D41: 158 | E41: 179.1 | F41: 234.6 | G41: 274.2 | H41: 280
B42: (1) Source: USGS Mineral Commodity Summaries 2026, Lime

Sheet B7. CaSO4
B2: Calcium Sulfate
B3: (quantities are representative of quantified form listed below, unless otherwise specified)
B5: Byproduct Information
B6: Chemical Formula of Quantified Form: | C6: CaSO4
B7: USGS Mineral Commodity Summary Page: | C7: Gypsum
B8: Demand Data Market Specificity: | C8: Byproduct
B9: Demand Data Resolution: | C9: Domestic
B13: Major End-Use Markets1
B14: Assigned End-Use Category | C14: End-Use | D14: Demand (kt) | E14: % of Demand | G14: Major end uses for gypsum (CaSO4) are reported and quantified in Table 3 of the most recent USGS Minerals Yearbook for Gypsum. We consider each listed end use at the highest level of granularity for which reasonable disaggregation proxies would still exist. Quantities of gypsum used in plaster are withheld but represented in “Other”, so we consolidate all calcined gypsum products into “Gypsum-Based Product Manufacturing”
B15: Cement Manufacturing | C15: Portland and masonry cement | D15: 4400 | E15: =D15/SUM(D$15:D$17) -> 0.11859838
B16: Miscellaneous Fertilizer Application | C16: Agriculture and other | D16: 14400 | E16: =D16/SUM(D$15:D$17) -> 0.38814016
B17: Gypsum-Based Product Manufacturing | C17: Plaster and prefabricated gypsum products | D17: 18300 | E17: =D17/SUM(D$15:D$17) -> 0.49326146
B18: (1) Source: USGS Minerals Yearbook 2023, Gypsum
B22: Domestic Demand
B23: Calculation Schema: | C23: Direct Report
B24: Description | C24: Units | D24: 2021 | E24: 2022 | F24: 2023 | G24: 2024 | H24: 2025
B25: Consumption, apparent1 | C25: kt | D25: 3200 | E25: 44600 | F25: 5800 | G25: 44900 | H25: 44000
B26: (1) Source: USGS Mineral Commodity Summaries 2026 Gypsum
B30: Pricing
B31: Description | C31: Units | D31: 2021 | E31: 2022 | F31: 2023 | G31: 2024 | H31: 2025
B32: Price, annual average, calcined, f.o.b. plant1 | C32: $/t | D32: 42 | E32: 50 | F32: 60 | G32: 60 | H32: 62
B33: (1) Source: USGS Mineral Commodity Summaries 2026 Gypsum

Sheet B8. HCl
B2: Hydrochloric Acid
B3: (quantities are representative of quantified form listed below, unless otherwise specified)
B5: Byproduct Information
B6: Chemical Formula of Quantified Form: | C6: HCl
B7: 8-Digit USITC HTS Number: | C7: 2806.10.00
B8: Demand Data Market Specificity: | C8: Byproduct
B9: Demand Data Resolution: | C9: Domestic
B13: Major End-Use Markets1
B14: Assigned End-Use Category | C14: End-Use | D14: Demand (kt) | E14: % of Demand
B15: Oil and Gas Well Acidification | C15: Oil and gas well acidification | D15: – | E15: 0.3
B16: Steel Pickling | C16: Steel pickling | D16: – | E16: 0.19
B17: Miscellaneous Manufacturing | C17: Food processing | D17: – | E17: 0.19
B18: Other | C18: Other | D18: – | E18: 0.32
B19: (1) Source: EPA Water Treatment Chemical Supply Chain Profile, Hydrochloric Acid
B23: Domestic Demand
B24: Calculation Schema: | C24: Trade Balance Estimate
B25: Description | C25: Units | D25: 2021 | E25: 2022 | F25: 2023 | G25: 2024 | H25: 2025
B26: Domestic Production1 | C26: kt | D26: =D43 -> 1214 | E26: =E43 -> 1158 | F26: =F43 -> 1191 | G26: =G43 -> 1200 | H26: =H43 -> 1200
B27: Imports for Consumption2 | C27: kt | D27: =E51 -> 328.677 | E27: =F51 -> 317.119 | F27: =G51 -> 350.072 | G27: =H51 -> 320.388 | H27: =I51 -> 270.188
B28: Domestic Exports3 | C28: kt | D28: =E56 -> 63.097 | E28: =F56 -> 84.293 | F28: =G56 -> 125.409 | G28: =H56 -> 120.031 | H28: =I56 -> 115.645
B29: Consumption, apparent4 | C29: kt | D29: =D26+D27-D28 -> 1479.58 | E29: =E26+E27-E28 -> 1390.826 | F29: =F26+F27-F28 -> 1415.663 | G29: =G26+G27-G28 -> 1400.357 | H29: =H26+H27-H28 -> 1354.543
B30: (1) See "Domestic Production" section below
B31: (2) See "Imports and Exports" section below
B32: (3) See "Imports and Exports" section below
B33: (4) Production + Imports – Exports
B35: Demand Calculations
B36: Domestic Production
B37: Domestic production of hydrochloric acid is tracked by the U.S. EPA under the Toxic Substances Control Act. We estimate domestic production by filtering 2024 CDR data for hydrochloric acid manufacturing production volumes, and sum the values for each year for which data is available (2021-2023). From this data, we see that hydrochloric acid production has remained relatively stable around 1,200 kt each year during this time period, so we adopt that as the production value for missing years (2024 and 2025).
B39: Domestic Production, Hydrochloric Acid
B40: Description | C40: Units | D40: 2021 | E40: 2022 | F40: 2023 | G40: 2024 | H40: 2025
B41: Reported domestic production1 | C41: kt | D41: 1214 | E41: 1158 | F41: 1191 | G41: – | H41: –
B42: Estimated domestic production2 | C42: kt | D42: – | E42: – | F42: – | G42: 1200 | H42: 1200
B43: Assumed domestic production | C43: kt | D43: =D41 -> 1214 | E43: =E41 -> 1158 | F43: =F41 -> 1191 | G43: =G42 -> 1200 | H43: =H42 -> 1200
B44: (1) Source: US EPA Chemical Data Reporting Data, 2024
B45: (2) Assumed based on patterns of consistent HCl production of ~1200 kt
B47: Imports and Exports
B49: Imports for Consumption, Hydrochloric Acid
B50: Product Name | C50: Units | D50: HTS Code | E50: 2021 | F50: 2022 | G50: 2023 | H50: 2024 | I50: 2025
B51: Hydrogen chloride (hydrochloric acid)1 | C51: kt | D51: 2806.10.0000 | E51: =_xlfn.XLOOKUP(_xlfn.CONCAT(_xlfn.TEXTSPLIT($D51,".")), 'S1. USITC Imports'!$B:$B,'S1. USITC Imports'!$J:$J)*_xlfn.XLOOKUP(_xlfn.CONCAT(_xlfn.TEXTSPLIT($D51,".")), 'S1. USITC Imports'!$B:$B,'S1. USITC Imports'!E:E) -> 328.677 | F51: =_xlfn.XLOOKUP(_xlfn.CONCAT(_xlfn.TEXTSPLIT($D51,".")), 'S1. USITC Imports'!$B:$B,'S1. USITC Imports'!$J:$J)*_xlfn.XLOOKUP(_xlfn.CONCAT(_xlfn.TEXTSPLIT($D51,".")), 'S1. USITC Imports'!$B:$B,'S1. USITC Imports'!F:F) -> 317.119 | G51: =_xlfn.XLOOKUP(_xlfn.CONCAT(_xlfn.TEXTSPLIT($D51,".")), 'S1. USITC Imports'!$B:$B,'S1. USITC Imports'!$J:$J)*_xlfn.XLOOKUP(_xlfn.CONCAT(_xlfn.TEXTSPLIT($D51,".")), 'S1. USITC Imports'!$B:$B,'S1. USITC Imports'!G:G) -> 350.072 | H51: =_xlfn.XLOOKUP(_xlfn.CONCAT(_xlfn.TEXTSPLIT($D51,".")), 'S1. USITC Imports'!$B:$B,'S1. USITC Imports'!$J:$J)*_xlfn.XLOOKUP(_xlfn.CONCAT(_xlfn.TEXTSPLIT($D51,".")), 'S1. USITC Imports'!$B:$B,'S1. USITC Imports'!H:H) -> 320.388 | I51: =_xlfn.XLOOKUP(_xlfn.CONCAT(_xlfn.TEXTSPLIT($D51,".")), 'S1. USITC Imports'!$B:$B,'S1. USITC Imports'!$J:$J)*_xlfn.XLOOKUP(_xlfn.CONCAT(_xlfn.TEXTSPLIT($D51,".")), 'S1. USITC Imports'!$B:$B,'S1. USITC Imports'!I:I) -> 270.188
B52: (1) Source: USITC DataWeb, Imports for Consumption
B54: Domestic Exports, Hydrochloric Acid
B55: Product Name | C55: Units | D55: HTS Code | E55: 2021 | F55: 2022 | G55: 2023 | H55: 2024 | I55: 2025
B56: Hydrogen chloride (hydrochloric acid)1 | C56: kt | D56: 2806.10.0000 | E56: =_xlfn.XLOOKUP(_xlfn.CONCAT(_xlfn.TEXTSPLIT($D56,".")), 'S2. USITC Exports'!$B:$B,'S2. USITC Exports'!$J:$J)*_xlfn.XLOOKUP(_xlfn.CONCAT(_xlfn.TEXTSPLIT($D56,".")), 'S2. USITC Exports'!$B:$B,'S2. USITC Exports'!E:E) -> 63.097 | F56: =_xlfn.XLOOKUP(_xlfn.CONCAT(_xlfn.TEXTSPLIT($D56,".")), 'S2. USITC Exports'!$B:$B,'S2. USITC Exports'!$J:$J)*_xlfn.XLOOKUP(_xlfn.CONCAT(_xlfn.TEXTSPLIT($D56,".")), 'S2. USITC Exports'!$B:$B,'S2. USITC Exports'!F:F) -> 84.293 | G56: =_xlfn.XLOOKUP(_xlfn.CONCAT(_xlfn.TEXTSPLIT($D56,".")), 'S2. USITC Exports'!$B:$B,'S2. USITC Exports'!$J:$J)*_xlfn.XLOOKUP(_xlfn.CONCAT(_xlfn.TEXTSPLIT($D56,".")), 'S2. USITC Exports'!$B:$B,'S2. USITC Exports'!G:G) -> 125.409 | H56: =_xlfn.XLOOKUP(_xlfn.CONCAT(_xlfn.TEXTSPLIT($D56,".")), 'S2. USITC Exports'!$B:$B,'S2. USITC Exports'!$J:$J)*_xlfn.XLOOKUP(_xlfn.CONCAT(_xlfn.TEXTSPLIT($D56,".")), 'S2. USITC Exports'!$B:$B,'S2. USITC Exports'!H:H) -> 120.031 | I56: =_xlfn.XLOOKUP(_xlfn.CONCAT(_xlfn.TEXTSPLIT($D56,".")), 'S2. USITC Exports'!$B:$B,'S2. USITC Exports'!$J:$J)*_xlfn.XLOOKUP(_xlfn.CONCAT(_xlfn.TEXTSPLIT($D56,".")), 'S2. USITC Exports'!$B:$B,'S2. USITC Exports'!I:I) -> 115.645
B57: (1) Source: USITC DataWeb, Domestic Exports
B61: Pricing
B62: Description | C62: Units | D62: HTS Code | E62: 2021 | F62: 2022 | G62: 2023 | H62: 2024 | I62: 2025
B63: Total FAS Value, Domestic Exports1 | C63: $ | D63: 2806.10.0000 | E63: =_xlfn.XLOOKUP(_xlfn.CONCAT(_xlfn.TEXTSPLIT($D63,".")), 'S3. USITC FAS Value'!$B:$B,'S3. USITC FAS Value'!E:E) -> 20458388 | F63: =_xlfn.XLOOKUP(_xlfn.CONCAT(_xlfn.TEXTSPLIT($D63,".")), 'S3. USITC FAS Value'!$B:$B,'S3. USITC FAS Value'!F:F) -> 22061173 | G63: =_xlfn.XLOOKUP(_xlfn.CONCAT(_xlfn.TEXTSPLIT($D63,".")), 'S3. USITC FAS Value'!$B:$B,'S3. USITC FAS Value'!G:G) -> 26783655 | H63: =_xlfn.XLOOKUP(_xlfn.CONCAT(_xlfn.TEXTSPLIT($D63,".")), 'S3. USITC FAS Value'!$B:$B,'S3. USITC FAS Value'!H:H) -> 25480468 | I63: =_xlfn.XLOOKUP(_xlfn.CONCAT(_xlfn.TEXTSPLIT($D63,".")), 'S3. USITC FAS Value'!$B:$B,'S3. USITC FAS Value'!I:I) -> 24442975
B64: Total Domestic Exports2 | C64: t | D64: 2806.10.0000 | E64: =E56*1000 -> 63097 | F64: =F56*1000 -> 84293 | G64: =G56*1000 -> 125409 | H64: =H56*1000 -> 120031 | I64: =I56*1000 -> 115645
B65: Price, average unit value, domestic exports FAS | C65: $/t | D65: – | E65: =E63/E64 -> 324.2371 | F65: =F63/F64 -> 261.72011 | G65: =G63/G64 -> 213.57044 | H65: =H63/H64 -> 212.28239 | I65: =I63/I64 -> 211.36214
B66: (1) Source: USITC DataWeb, Domestic Exports
B67: (2) See "Imports and Exports" section above

Sheet B9. HF
B2: Hydrofluoric Acid
B3: (quantities are representative of quantified form listed below, unless otherwise specified)
B5: Byproduct Information
B6: Chemical Formula of Quantified Form: | C6: HF
B7: 8-Digit USITC HTS Number: | C7: 2811.11.00
B8: Demand Data Market Specificity: | C8: Byproduct
B9: Demand Data Resolution: | C9: Domestic
B13: Major End-Use Markets1
B14: Assigned End-Use Category | C14: End-Use | D14: Demand (kt) | E14: % of Demand | G14: "Glass etching" was assigned to Semiconductor Manufacturing, based on reports from USGS that hydrofluoric acid is essential in cleaning and etching process during semiconductor manufacturing.1 End-uses with a market share <5% are consolidated into the "Other" category.
B15: Organic Chemical Manufacturing | C15: Fluorocarbon | D15: – | E15: 0.56
B16: Organic Chemical Manufacturing | C16: Fluorinated derivatives | D16: – | E16: 0.18333333
B17: Steel Pickling | C17: Metal pickling | D17: – | E17: 0.11388889
B18: Semiconductor Manufacturing | C18: Glass etching | D18: – | E18: 0.06
B19: Other | C19: Oil refining | D19: – | E19: 0.04
B20: Other | C20: Others | D20: – | E20: 0.047222222
B21: (1) Source: Grand View Research, Hydrofluoric Acid Market 2022-2030 | G21: (1) Source: USGS Mineral Commodity Summaries 2026, Fluorspar
B25: Domestic Demand
B26: Calculation Schema: | C26: Trade Balance Estimate
B27: Description | C27: Units | D27: 2021 | E27: 2022 | F27: 2023 | G27: 2024 | H27: 2025
B28: Domestic Production1 | C28: kt | D28: =D47 -> 200.3803 | E28: =E47 -> 229.59175 | F28: =F47 -> 193.71804 | G28: =G47 -> 190.64315 | H28: =H47 -> 184.49337
B29: Imports for Consumption2 | C29: kt | D29: =E57 -> 103.27172 | E29: =F57 -> 99.439092 | F29: =G57 -> 86.756697 | G29: =H57 -> 68.949172 | H29: =I57 -> 76.05068
B30: Domestic Exports3 | C30: kt | D30: =E62 -> 16.608258 | E30: =F62 -> 9.8888 | F30: =G62 -> 10.460104 | G30: =H62 -> 13.948911 | H30: =I62 -> 12.203279
B31: Consumption, apparent4 | C31: kt | D31: =D28+D29-D30 -> 287.04376 | E31: =E28+E29-E30 -> 319.14204 | F31: =F28+F29-F30 -> 270.01463 | G31: =G28+G29-G30 -> 245.64341 | H31: =H28+H29-H30 -> 248.34077
B32: (1) See "Domestic Production" section below
B33: (2) See "Imports and Exports" section below
B34: (3) See "Imports and Exports" section below
B35: (4) Production + Imports – Exports
B37: Demand Calculations
B38: Domestic Production
B39: Domestic production of hydrofluoric acid is tracked by the U.S. EPA under the Toxic Substances Control Act. When calculating the total production volumes of hydrofluoric acid from the 2024 CDR dataset, however, we find that the disclosed production volumes (~2-6 kt in total, each year) represent only a small fraction of total U.S. hydrofluoric acid manufacturing capacity (200 kt),1 likely due to information withheld from the public CDR dataset as confidential business information (CBI). Instead, we calculate hydrofluoric acid production indirectly, as a function of acid-grade fluorspar consumption, which is used entirely for hydrofluoric acid manufacturing (see B5. CaF2). To generate a conservative estimate (erring towards overestimation to provide an upper bound of demand), we perform these calculations stoichiometrically, where a single molecule of fluorspar translates to 2 hydrofluoric acid molecules. We assume 100% purity in the fluorspar feedstock. These calculations yield production estimates well in line with approximate US production capacities, but likely slightly overestimate hydrofluoric acid production volumes.
B40: (1) Source: ATSDR Toxicological Profile for Fluorides, Hydrogen Fluoride, and Fluorine
B42: Domestic Production, Hydrofluoric Acid
B43: Description | C43: Units | D43: 2021 | E43: 2022 | F43: 2023 | G43: 2024 | H43: 2025
B44: Consumption, apparent, acid-grade fluorspar1 | C44: kt | D44: ='B5. CaF2'!D23 -> 391 | E44: ='B5. CaF2'!E23 -> 448 | F44: ='B5. CaF2'!F23 -> 378 | G44: ='B5. CaF2'!G23 -> 372 | H44: ='B5. CaF2'!H23 -> 360
B45: Consumption, estimated calcium, fluoride2 | C45: Mmol | D45: =D44/(78.075) -> 5.0080051 | E45: =E44/(78.075) -> 5.7380724 | F45: =F44/(78.075) -> 4.8414986 | G45: =G44/(78.075) -> 4.7646494 | H45: =H44/(78.075) -> 4.610951
B46: Production, estimated, hydrofluoric acid3 | C46: Mmol | D46: =2*D45 -> 10.01601 | E46: =2*E45 -> 11.476145 | F46: =2*F45 -> 9.6829971 | G46: =2*G45 -> 9.5292988 | H46: =2*H45 -> 9.221902
B47: Production, estimated, hydrofluoric acid4 | C47: kt | D47: =D46*20.006 -> 200.3803 | E47: =E46*20.006 -> 229.59175 | F47: =F46*20.006 -> 193.71804 | G47: =G46*20.006 -> 190.64315 | H47: =H46*20.006 -> 184.49337
B48: (1) See B5. CaF2
B49: (2) Converted from fluorspar consumption assuming 100% calcium fluoride purity and molecular weight of 78.075 kt/Mmol. Molecular weight obtained from Python molmass package.
B50: (3) Stoichiometric yield of hydrofluoric acid from 1 mol calcium fluoride (CaF2 + H2SO4 --> 2HF + CaSO4)
B51: (4) Converted from molar hydrofluoric acid yield to weight in metric tons. Molecular weight obtained from Python molmass package.
B53: Imports and Exports
B55: Imports for Consumption, Hydrofluoric Acid
B56: Product Name | C56: Units | D56: HTS Code | E56: 2021 | F56: 2022 | G56: 2023 | H56: 2024 | I56: 2025
B57: Hydrogen fluoride (hydrofluoric acid)1 | C57: kt | D57: 2811.11.0000 | E57: =_xlfn.XLOOKUP(_xlfn.CONCAT(_xlfn.TEXTSPLIT($D57,".")), 'S1. USITC Imports'!$B:$B,'S1. USITC Imports'!$J:$J)*_xlfn.XLOOKUP(_xlfn.CONCAT(_xlfn.TEXTSPLIT($D57,".")), 'S1. USITC Imports'!$B:$B,'S1. USITC Imports'!E:E) -> 103.27172 | F57: =_xlfn.XLOOKUP(_xlfn.CONCAT(_xlfn.TEXTSPLIT($D57,".")), 'S1. USITC Imports'!$B:$B,'S1. USITC Imports'!$J:$J)*_xlfn.XLOOKUP(_xlfn.CONCAT(_xlfn.TEXTSPLIT($D57,".")), 'S1. USITC Imports'!$B:$B,'S1. USITC Imports'!F:F) -> 99.439092 | G57: =_xlfn.XLOOKUP(_xlfn.CONCAT(_xlfn.TEXTSPLIT($D57,".")), 'S1. USITC Imports'!$B:$B,'S1. USITC Imports'!$J:$J)*_xlfn.XLOOKUP(_xlfn.CONCAT(_xlfn.TEXTSPLIT($D57,".")), 'S1. USITC Imports'!$B:$B,'S1. USITC Imports'!G:G) -> 86.756697 | H57: =_xlfn.XLOOKUP(_xlfn.CONCAT(_xlfn.TEXTSPLIT($D57,".")), 'S1. USITC Imports'!$B:$B,'S1. USITC Imports'!$J:$J)*_xlfn.XLOOKUP(_xlfn.CONCAT(_xlfn.TEXTSPLIT($D57,".")), 'S1. USITC Imports'!$B:$B,'S1. USITC Imports'!H:H) -> 68.949172 | I57: =_xlfn.XLOOKUP(_xlfn.CONCAT(_xlfn.TEXTSPLIT($D57,".")), 'S1. USITC Imports'!$B:$B,'S1. USITC Imports'!$J:$J)*_xlfn.XLOOKUP(_xlfn.CONCAT(_xlfn.TEXTSPLIT($D57,".")), 'S1. USITC Imports'!$B:$B,'S1. USITC Imports'!I:I) -> 76.05068
B58: (1) Source: USITC DataWeb, Imports for Consumption
B60: Domestic Exports, Hydrofluoric Acid
B61: Product Name | C61: Units | D61: HTS Code | E61: 2021 | F61: 2022 | G61: 2023 | H61: 2024 | I61: 2025
B62: Hydrogen fluoride (hydrofluoric acid)1 | C62: kt | D62: 2811.11.0000 | E62: =_xlfn.XLOOKUP(_xlfn.CONCAT(_xlfn.TEXTSPLIT($D62,".")), 'S2. USITC Exports'!$B:$B,'S2. USITC Exports'!$J:$J)*_xlfn.XLOOKUP(_xlfn.CONCAT(_xlfn.TEXTSPLIT($D62,".")), 'S2. USITC Exports'!$B:$B,'S2. USITC Exports'!E:E) -> 16.608258 | F62: =_xlfn.XLOOKUP(_xlfn.CONCAT(_xlfn.TEXTSPLIT($D62,".")), 'S2. USITC Exports'!$B:$B,'S2. USITC Exports'!$J:$J)*_xlfn.XLOOKUP(_xlfn.CONCAT(_xlfn.TEXTSPLIT($D62,".")), 'S2. USITC Exports'!$B:$B,'S2. USITC Exports'!F:F) -> 9.8888 | G62: =_xlfn.XLOOKUP(_xlfn.CONCAT(_xlfn.TEXTSPLIT($D62,".")), 'S2. USITC Exports'!$B:$B,'S2. USITC Exports'!$J:$J)*_xlfn.XLOOKUP(_xlfn.CONCAT(_xlfn.TEXTSPLIT($D62,".")), 'S2. USITC Exports'!$B:$B,'S2. USITC Exports'!G:G) -> 10.460104 | H62: =_xlfn.XLOOKUP(_xlfn.CONCAT(_xlfn.TEXTSPLIT($D62,".")), 'S2. USITC Exports'!$B:$B,'S2. USITC Exports'!$J:$J)*_xlfn.XLOOKUP(_xlfn.CONCAT(_xlfn.TEXTSPLIT($D62,".")), 'S2. USITC Exports'!$B:$B,'S2. USITC Exports'!H:H) -> 13.948911 | I62: =_xlfn.XLOOKUP(_xlfn.CONCAT(_xlfn.TEXTSPLIT($D62,".")), 'S2. USITC Exports'!$B:$B,'S2. USITC Exports'!$J:$J)*_xlfn.XLOOKUP(_xlfn.CONCAT(_xlfn.TEXTSPLIT($D62,".")), 'S2. USITC Exports'!$B:$B,'S2. USITC Exports'!I:I) -> 12.203279
B63: (1) Source: USITC DataWeb, Domestic Exports
B67: Pricing
B68: Description | C68: Units | D68: HTS Code | E68: 2021 | F68: 2022 | G68: 2023 | H68: 2024 | I68: 2025
B69: Total FAS Value, Domestic Exports1 | C69: $ | D69: 2811.11.0000 | E69: =_xlfn.XLOOKUP(_xlfn.CONCAT(_xlfn.TEXTSPLIT($D69,".")), 'S3. USITC FAS Value'!$B:$B,'S3. USITC FAS Value'!E:E) -> 29011838 | F69: =_xlfn.XLOOKUP(_xlfn.CONCAT(_xlfn.TEXTSPLIT($D69,".")), 'S3. USITC FAS Value'!$B:$B,'S3. USITC FAS Value'!F:F) -> 23403531 | G69: =_xlfn.XLOOKUP(_xlfn.CONCAT(_xlfn.TEXTSPLIT($D69,".")), 'S3. USITC FAS Value'!$B:$B,'S3. USITC FAS Value'!G:G) -> 23922471 | H69: =_xlfn.XLOOKUP(_xlfn.CONCAT(_xlfn.TEXTSPLIT($D69,".")), 'S3. USITC FAS Value'!$B:$B,'S3. USITC FAS Value'!H:H) -> 32122156 | I69: =_xlfn.XLOOKUP(_xlfn.CONCAT(_xlfn.TEXTSPLIT($D69,".")), 'S3. USITC FAS Value'!$B:$B,'S3. USITC FAS Value'!I:I) -> 33293771
B70: Total Domestic Exports2 | C70: t | D70: 2811.11.0000 | E70: =E62*1000 -> 16608.258 | F70: =F62*1000 -> 9888.8 | G70: =G62*1000 -> 10460.104 | H70: =H62*1000 -> 13948.911 | I70: =I62*1000 -> 12203.279
B71: Price, average unit value, domestic exports FAS | C71: $/t | D71: – | E71: =E69/E70 -> 1746.8321 | F71: =F69/F70 -> 2366.6705 | G71: =G69/G70 -> 2287.0204 | H71: =H69/H70 -> 2302.8433 | I71: =I69/I70 -> 2728.2643
B72: (1) Source: USITC DataWeb, Domestic Exports
B73: (2) See "Imports and Exports" section above

Sheet B10. K2O
B2: Potash
B3: (quantities are representative of quantified form listed below, unless otherwise specified)
B5: Byproduct Information
B6: Chemical Formula of Quantified Form: | C6: K2O
B7: USGS Mineral Commodity Summary Page: | C7: Potash
B8: Demand Data Market Specificity: | C8: Byproduct
B9: Demand Data Resolution: | C9: Domestic
B13: Major End-Use Markets1
B14: Assigned End-Use Category | C14: End-Use | D14: Demand (kt) | E14: % of Demand
B15: Potash Fertilizer Application | C15: Fertilizer industry | D15: – | E15: 0.85
B16: Miscellaneous Chemical Manufacturing | C16: Chemical and industrial applications | D16: – | E16: 0.15
B17: (1) Source: USGS Mineral Commodity Summaries 2026, Potash
B21: Domestic Demand
B22: Calculation Schema: | C22: Direct Report
B23: Description | C23: Units | D23: 2021 | E23: 2022 | F23: 2023 | G23: 2024 | H23: 2025
B24: Consumption, apparent1 | C24: kt | D24: 6900 | E24: 5100 | F24: 5900 | G24: 6200 | H24: 5900
B25: (1) Source: USGS Mineral Commodity Summaries 2026, Potash
B29: Pricing
B30: Description | C30: Units | D30: 2021 | E30: 2022 | F30: 2023 | G30: 2024 | H30: 2025
B31: Price, average, f.o.b. mine, all products1 | C31: $/t | D31: 1120 | E31: 1790 | F31: 1250 | G31: 1150 | H31: 1200
B32: (1) Source: USGS Mineral Commodity Summaries 2026, Potash

Sheet B11. Li
B2: Lithium
B3: (quantities are representative of quantified form listed below, unless otherwise specified)
B5: Byproduct Information
B6: Chemical Formula of Quantified Form: | C6: Li
B7: USGS Mineral Commodity Summary Page: | C7: Lithium
B8: Demand Data Market Specificity: | C8: Byproduct
B9: Demand Data Resolution: | C9: Domestic
B13: Major End-Use Markets1
B14: Assigned End-Use Category | C14: End-Use | D14: Demand (kt) | E14: % of Demand | G14: End-uses with a market share <5% are consolidated into the "Other" category.
B15: Lithium Battery Manufacturing | C15: Batteries | D15: – | E15: 0.88
B16: Other | C16: Ceramics and glass | D16: – | E16: 0.04
B17: Other | C17: Lubricating greases | D17: – | E17: 0.02
B18: Other | C18: Air treatment | D18: – | E18: 0.01
B19: Other | C19: Continuous casting mold flux powders | D19: – | E19: 0.01
B20: Other | C20: Medical | D20: – | E20: 0.01
B21: Other | C21: Other | D21: – | E21: 0.03
B22: (1) Source: USGS Mineral Commodity Summaries 2026, Lithium
B26: Domestic Demand
B27: Calculation Schema: | C27: Trade Balance Estimate
B28: To avoid disclosing proprietary information, USGS withholds lithium consumption and production estimates. Because there is currently only one commercial-scale lithium producer in the United States, domestic lithium consumption is heavily import reliant. Though USGS does not report precise net import reliance, they provide a lower bound (e.g. >50%) that can be used to conservatively estimate an upper bound on domestic lithium demand.
B30: Description | C30: Units | D30: 2021 | E30: 2022 | F30: 2023 | G30: 2024 | H30: 2025
B31: Imports for Consumption1 | C31: kt | D31: 2.64 | E31: 3.26 | F31: 3.39 | G31: 3.02 | H31: 3.8
B32: Domestic Exports1 | C32: kt | D32: 1.87 | E32: 2.44 | F32: 1.96 | G32: 1.69 | H32: 2
B33: Minimum net import reliance1,2 | C33: – | D33: 0.25 | E33: 0.25 | F33: 0.5 | G33: 0.5 | H33: 0.5
B34: Consumption, apparent3 | C34: kt | D34: =(D31-D32)/D33 -> 3.08 | E34: =(E31-E32)/E33 -> 3.28 | F34: =(F31-F32)/F33 -> 2.86 | G34: =(G31-G32)/G33 -> 2.66 | H34: =(H31-H32)/H33 -> 3.6
B35: (1) Source: USGS Mineral Commodity Summaries 2026, Lithium
B36: (2) Defined by USGS as imports – exports +/- adjustments for industry stock changes, as a percentage of consumption. We ignore industry stock changes for the purposes of these estimations.
B37: (3) (Imports – Exports)/Net Import Reliance
B41: Pricing
B42: Description | C42: Units | D42: 2021 | E42: 2022 | F42: 2023 | G42: 2024 | H42: 2025
B43: Price, annual average-real, battery-grade lithium carbonate1 | C43: $/t Li2CO3 | D43: 11700 | E43: 63700 | F43: 39000 | G43: 11800 | H43: 9000
B44: Price, annual average-real, battery-grade lithium carbonate, lithium content2 | C44: $/t | D44: =D43/(2*6.94/73.888955) -> 62283.917 | E44: =E43/(2*6.94/73.888955) -> 339101.33 | F44: =F43/(2*6.94/73.888955) -> 207613.06 | G44: =G43/(2*6.94/73.888955) -> 62816.259 | H44: =H43/(2*6.94/73.888955) -> 47910.706
B45: (1) Source: USGS Mineral Commodity Summaries 2026, Lithium
B46: (2) Calculated from molcular weight ratio Lithium and Lithium Carbonate

Sheet B12. MgCl2
B2: Magnesium Chloride
B3: (quantities are representative of quantified form listed below, unless otherwise specified)
B5: Byproduct Information
B6: Chemical Formula of Quantified Form: | C6: MgCl2
B7: USGS Mineral Commodity Summary Page: | C7: Magnesium Compounds
B8: Demand Data Market Specificity: | C8: Byproduct-Market
B9: Demand Data Resolution: | C9: State
B13: Major End-Use Markets1
B14: Assigned End-Use Category | C14: End-Use | D14: Demand (kt) | E14: % of Demand2
B15: Deicing and Dust Control | C15: Deicing and dust control | D15: – | E15: 1
B16: (1) Source: USGS Minerals Yearbook 2020, Magnesium Compounds
B20: State-Level Demand by End-Use
B21: The Clear Roads Research Program conducts an annual survey of road maintenance data from U.S. states, from which we can extract magnesium chloride use as road salts by state directly.1 Magnesium chloride use is reported for both dry salt (in tons) and brine (in gallons). To calculate total magnesium chloride use (in tons), we assume brines are 22% MgCl2 by weight and have a density of about 10 lbs/gallon (0.005 tons/gal).2,3 We then add dry tons and equivalent dry tons from brine together to get total magnesium chloride application in each state in each year.
B22: In cases where a state did not provide a survey response in a given year, the maximum value across all 10 years of avaialble survey data is used, resulting in a conservative estimate of magnesium chloride demand. For a few states in CONUS (FL, MS, NC), there is no available data for any year covered by the survey (2015-2025). Because all of these states are in the southern US, where typical temperatures are warmer, we assume they apply zero magnesium chloride for deicing and dust control.
B23: (1) Source: Clear Roads Annual Survey of State Winter Maintenance Data
B24: (2) Source: Texas Department of Transportation
B25: (3) Source: General References Physical Properties of Pure Substances
B27: Deicing and Dust Control1
B28: State | C28: Units | D28: 2021 | E28: 2022 | F28: 2023 | G28: 2024 | H28: 2025
B29: Alabama | C29: kt | D29: {=IF(ISNUMBER(J196),J196,MAX(IF(ISNUMBER($D196:$N196),$D196:$N196,0)))} -> 0 | E29: {=IF(ISNUMBER(K196),K196,MAX(IF(ISNUMBER($D196:$N196),$D196:$N196,0)))} -> 10.477987 | F29: {=IF(ISNUMBER(L196),L196,MAX(IF(ISNUMBER($D196:$N196),$D196:$N196,0)))} -> 10.477987 | G29: {=IF(ISNUMBER(M196),M196,MAX(IF(ISNUMBER($D196:$N196),$D196:$N196,0)))} -> 10.477987 | H29: {=IF(ISNUMBER(N196),N196,MAX(IF(ISNUMBER($D196:$N196),$D196:$N196,0)))} -> 10.477987
B30: Alaska | C30: kt | D30: {=IF(ISNUMBER(J197),J197,MAX(IF(ISNUMBER($D197:$N197),$D197:$N197,0)))} -> 13616.847 | E30: {=IF(ISNUMBER(K197),K197,MAX(IF(ISNUMBER($D197:$N197),$D197:$N197,0)))} -> 13616.847 | F30: {=IF(ISNUMBER(L197),L197,MAX(IF(ISNUMBER($D197:$N197),$D197:$N197,0)))} -> 13616.847 | G30: {=IF(ISNUMBER(M197),M197,MAX(IF(ISNUMBER($D197:$N197),$D197:$N197,0)))} -> 13616.847 | H30: {=IF(ISNUMBER(N197),N197,MAX(IF(ISNUMBER($D197:$N197),$D197:$N197,0)))} -> 27.941298
B31: Arizona | C31: kt | D31: {=IF(ISNUMBER(J198),J198,MAX(IF(ISNUMBER($D198:$N198),$D198:$N198,0)))} -> 13.970649 | E31: {=IF(ISNUMBER(K198),K198,MAX(IF(ISNUMBER($D198:$N198),$D198:$N198,0)))} -> 223.47949 | F31: {=IF(ISNUMBER(L198),L198,MAX(IF(ISNUMBER($D198:$N198),$D198:$N198,0)))} -> 469.01465 | G31: {=IF(ISNUMBER(M198),M198,MAX(IF(ISNUMBER($D198:$N198),$D198:$N198,0)))} -> 295.28863 | H31: {=IF(ISNUMBER(N198),N198,MAX(IF(ISNUMBER($D198:$N198),$D198:$N198,0)))} -> 149.30342
B32: Arkansas | C32: kt | D32: {=IF(ISNUMBER(J199),J199,MAX(IF(ISNUMBER($D199:$N199),$D199:$N199,0)))} -> 14.669181 | E32: {=IF(ISNUMBER(K199),K199,MAX(IF(ISNUMBER($D199:$N199),$D199:$N199,0)))} -> 14.669181 | F32: {=IF(ISNUMBER(L199),L199,MAX(IF(ISNUMBER($D199:$N199),$D199:$N199,0)))} -> 14.669181 | G32: {=IF(ISNUMBER(M199),M199,MAX(IF(ISNUMBER($D199:$N199),$D199:$N199,0)))} -> 14.669181 | H32: {=IF(ISNUMBER(N199),N199,MAX(IF(ISNUMBER($D199:$N199),$D199:$N199,0)))} -> 14.669181
B33: California | C33: kt | D33: {=IF(ISNUMBER(J200),J200,MAX(IF(ISNUMBER($D200:$N200),$D200:$N200,0)))} -> 18235.326 | E33: {=IF(ISNUMBER(K200),K200,MAX(IF(ISNUMBER($D200:$N200),$D200:$N200,0)))} -> 18235.326 | F33: {=IF(ISNUMBER(L200),L200,MAX(IF(ISNUMBER($D200:$N200),$D200:$N200,0)))} -> 0 | G33: {=IF(ISNUMBER(M200),M200,MAX(IF(ISNUMBER($D200:$N200),$D200:$N200,0)))} -> 0 | H33: {=IF(ISNUMBER(N200),N200,MAX(IF(ISNUMBER($D200:$N200),$D200:$N200,0)))} -> 0
B34: Colorado | C34: kt | D34: {=IF(ISNUMBER(J201),J201,MAX(IF(ISNUMBER($D201:$N201),$D201:$N201,0)))} -> 12207.962 | E34: {=IF(ISNUMBER(K201),K201,MAX(IF(ISNUMBER($D201:$N201),$D201:$N201,0)))} -> 10165.646 | F34: {=IF(ISNUMBER(L201),L201,MAX(IF(ISNUMBER($D201:$N201),$D201:$N201,0)))} -> 11718.856 | G34: {=IF(ISNUMBER(M201),M201,MAX(IF(ISNUMBER($D201:$N201),$D201:$N201,0)))} -> 8605.357 | H34: {=IF(ISNUMBER(N201),N201,MAX(IF(ISNUMBER($D201:$N201),$D201:$N201,0)))} -> 20641.306
B35: Connecticut | C35: kt | D35: {=IF(ISNUMBER(J202),J202,MAX(IF(ISNUMBER($D202:$N202),$D202:$N202,0)))} -> 945.20122 | E35: {=IF(ISNUMBER(K202),K202,MAX(IF(ISNUMBER($D202:$N202),$D202:$N202,0)))} -> 603.33745 | F35: {=IF(ISNUMBER(L202),L202,MAX(IF(ISNUMBER($D202:$N202),$D202:$N202,0)))} -> 184813.4 | G35: {=IF(ISNUMBER(M202),M202,MAX(IF(ISNUMBER($D202:$N202),$D202:$N202,0)))} -> 695.83911 | H35: {=IF(ISNUMBER(N202),N202,MAX(IF(ISNUMBER($D202:$N202),$D202:$N202,0)))} -> 682.53705
B36: Delaware | C36: kt | D36: {=IF(ISNUMBER(J203),J203,MAX(IF(ISNUMBER($D203:$N203),$D203:$N203,0)))} -> 0 | E36: {=IF(ISNUMBER(K203),K203,MAX(IF(ISNUMBER($D203:$N203),$D203:$N203,0)))} -> 0 | F36: {=IF(ISNUMBER(L203),L203,MAX(IF(ISNUMBER($D203:$N203),$D203:$N203,0)))} -> 0 | G36: {=IF(ISNUMBER(M203),M203,MAX(IF(ISNUMBER($D203:$N203),$D203:$N203,0)))} -> 0 | H36: {=IF(ISNUMBER(N203),N203,MAX(IF(ISNUMBER($D203:$N203),$D203:$N203,0)))} -> 0
B37: District of Columbia | C37: kt | D37: {=IF(ISNUMBER(J204),J204,MAX(IF(ISNUMBER($D204:$N204),$D204:$N204,0)))} -> 0 | E37: {=IF(ISNUMBER(K204),K204,MAX(IF(ISNUMBER($D204:$N204),$D204:$N204,0)))} -> 0 | F37: {=IF(ISNUMBER(L204),L204,MAX(IF(ISNUMBER($D204:$N204),$D204:$N204,0)))} -> 0 | G37: {=IF(ISNUMBER(M204),M204,MAX(IF(ISNUMBER($D204:$N204),$D204:$N204,0)))} -> 0 | H37: {=IF(ISNUMBER(N204),N204,MAX(IF(ISNUMBER($D204:$N204),$D204:$N204,0)))} -> 0
B38: Florida | C38: kt | D38: {=IF(ISNUMBER(J205),J205,MAX(IF(ISNUMBER($D205:$N205),$D205:$N205,0)))} -> 0 | E38: {=IF(ISNUMBER(K205),K205,MAX(IF(ISNUMBER($D205:$N205),$D205:$N205,0)))} -> 0 | F38: {=IF(ISNUMBER(L205),L205,MAX(IF(ISNUMBER($D205:$N205),$D205:$N205,0)))} -> 0 | G38: {=IF(ISNUMBER(M205),M205,MAX(IF(ISNUMBER($D205:$N205),$D205:$N205,0)))} -> 0 | H38: {=IF(ISNUMBER(N205),N205,MAX(IF(ISNUMBER($D205:$N205),$D205:$N205,0)))} -> 0
B39: Georgia | C39: kt | D39: {=IF(ISNUMBER(J206),J206,MAX(IF(ISNUMBER($D206:$N206),$D206:$N206,0)))} -> 0 | E39: {=IF(ISNUMBER(K206),K206,MAX(IF(ISNUMBER($D206:$N206),$D206:$N206,0)))} -> 0 | F39: {=IF(ISNUMBER(L206),L206,MAX(IF(ISNUMBER($D206:$N206),$D206:$N206,0)))} -> 0 | G39: {=IF(ISNUMBER(M206),M206,MAX(IF(ISNUMBER($D206:$N206),$D206:$N206,0)))} -> 0 | H39: {=IF(ISNUMBER(N206),N206,MAX(IF(ISNUMBER($D206:$N206),$D206:$N206,0)))} -> 0
B40: Hawaii | C40: kt | D40: {=IF(ISNUMBER(J207),J207,MAX(IF(ISNUMBER($D207:$N207),$D207:$N207,0)))} -> 0 | E40: {=IF(ISNUMBER(K207),K207,MAX(IF(ISNUMBER($D207:$N207),$D207:$N207,0)))} -> 0 | F40: {=IF(ISNUMBER(L207),L207,MAX(IF(ISNUMBER($D207:$N207),$D207:$N207,0)))} -> 0 | G40: {=IF(ISNUMBER(M207),M207,MAX(IF(ISNUMBER($D207:$N207),$D207:$N207,0)))} -> 0 | H40: {=IF(ISNUMBER(N207),N207,MAX(IF(ISNUMBER($D207:$N207),$D207:$N207,0)))} -> 0
... B79: Wyoming | C79: kt | D79: {=IF(ISNUMBER(J246),J246,MAX(IF(ISNUMBER($D246:$N246),$D246:$N246,0)))} -> 3847.0098 | E79: {=IF(ISNUMBER(K246),K246,MAX(IF(ISNUMBER($D246:$N246),$D246:$N246,0)))} -> 54.862739 | F79: {=IF(ISNUMBER(L246),L246,MAX(IF(ISNUMBER($D246:$N246),$D246:$N246,0)))} -> 45.271888 | G79: {=IF(ISNUMBER(M246),M246,MAX(IF(ISNUMBER($D246:$N246),$D246:$N246,0)))} -> 45.830714 | H79: {=IF(ISNUMBER(N246),N246,MAX(IF(ISNUMBER($D246:$N246),$D246:$N246,0)))} -> 150.72135
B80: Total Withheld | C80: kt | D80: 0 | E80: 0 | F80: 0 | G80: 0 | H80: 0
B81: (1) Taken directly from Total Magnesium Chloride Applied table below, if available. Where no data is available, maximum across 10 years of data is assumed. Where no data is available for entire time period, 0 is assumed.
B83: Demand Calculations
B84: Dry Magnesium Chloride Applied
B85: State | C85: Units | D85: 2015 | E85: 2016 | F85: 2017 | G85: 2018 | H85: 2019 | I85: 2020 | J85: 2021 | K85: 2022 | L85: 2023 | M85: 2024 | N85: 2025
B86: Alabama | C86: tons | E86: 0 | F86: 0 | G86: 0 | H86: 11 | I86: 5 | J86: 0
B87: Alaska | C87: tons | E87: 0 | G87: 0 | M87: 15010 | N87: 0
B88: Arizona | C88: tons | D88: 0 | E88: 0 | H88: 0 | J88: 0 | L88: 0 | M88: 0 | N88: 1
B89: Arkansas | C89: tons | D89: 0
B90: California | C90: tons | D90: 0 | E90: 19518 | F90: 20101 | G90: 10000 | I90: 4000 | L90: 0 | M90: 0 | N90: 0
B91: Colorado | C91: tons | D91: 214009 | E91: 4414 | F91: 1423 | G91: 910 | H91: 270 | I91: 106 | J91: 75 | K91: 262 | L91: 0 | N91: 14600
B92: Connecticut | C92: tons | D92: 0 | E92: 0 | F92: 0 | G92: 0 | H92: 0 | I92: 0 | J92: 0 | K92: 0 | L92: 203498
B93: Delaware | C93: tons | D93: 0
B94: District of Columbia | C94: tons
B95: Florida | C95: tons
B96: Georgia | C96: tons | G96: 0 | H96: 0 | I96: 0 | K96: 0 | L96: 0 | M96: 0
B97: Hawaii | C97: tons
B98: Idaho | C98: tons | F98: 0 | G98: 0 | H98: 0 | I98: 0 | J98: 0 | K98: 0 | L98: 0 | M98: 0 | N98: 0
B99: Illinois | C99: tons | D99: 0 | E99: 0 | F99: 0 | H99: 0 | I99: 0 | J99: 0 | K99: 0 | L99: 0 | M99: 0 | N99: 0
B100: Indiana | C100: tons | H100: 0 | I100: 0 | J100: 0 | L100: 0 | M100: 0 | N100: 0
B101: Iowa | C101: tons | D101: 0 | E101: 0 | F101: 0 | G101: 0 | H101: 0 | I101: 0 | J101: 0 | K101: 0 | L101: 0 | M101: 0 | N101: 0
B102: Kansas | C102: tons | D102: 0 | E102: 0 | F102: 0 | G102: 0 | I102: 0 | J102: 0 | K102: 0 | M102: 0
B103: Kentucky | C103: tons | E103: 0 | F103: 0 | G103: 0 | L103: 0 | M103: 0 | N103: 0
B104: Louisiana | C104: tons | D104: 0
B105: Maine | C105: tons | D105: 0 | F105: 0 | I105: 0 | J105: 0 | K105: 0 | L105: 0 | N105: 0
B106: Maryland | C106: tons | F106: 0 | H106: 9570 | I106: 0 | J106: 0 | K106: 5385 | L106: 0 | M106: 0 | N106: 0
B107: Massachusetts | C107: tons | E107: 0 | F107: 703 | I107: 0 | K107: 0
B108: Michigan | C108: tons | J108: 0 | L108: 0
B109: Minnesota | C109: tons | F109: 43400 | G109: 41727 | H109: 0 | I109: 0 | J109: 0 | K109: 0 | L109: 0 | M109: 0 | N109: 0
B110: Mississippi | C110: tons
B111: Missouri | C111: tons | D111: 0 | E111: 0 | F111: 0 | G111: 0 | H111: 0 | I111: 0 | J111: 0 | K111: 0 | M111: 0
B112: Montana | C112: tons | D112: 0 | E112: 0 | G112: 0 | H112: 0 | I112: 0 | J112: 0 | K112: 0 | L112: 0 | M112: 0 | N112: 0
B113: Nebraska | C113: tons | D113: 9000 | G113: 0 | I113: 0 | L113: 0 | M113: 0 | N113: 0
B114: Nevada | C114: tons | D114: 0 | J114: 0 | N114: 0
B115: New Hampshire | C115: tons | E115: 0 | F115: 0 | G115: 0 | H115: 0 | I115: 0 | J115: 0 | K115: 0 | L115: 0 | M115: 0 | N115: 0
B116: New Jersey | C116: tons | D116: 0 | K116: 0 | L116: 0 | M116: 0 | N116: 0
B117: New Mexico | C117: tons | K117: 2678
B118: New York | C118: tons | E118: 0 | M118: 0 | N118: 0
B119: North Carolina | C119: tons
B120: North Dakota | C120: tons | D120: 0 | E120: 0 | F120: 0 | G120: 0 | H120: 0 | I120: 0 | J120: 0 | K120: 0 | M120: 0
B121: Ohio | C121: tons | D121: 0 | E121: 0 | F121: 0 | G121: 0 | H121: 0 | I121: 0 | J121: 0 | K121: 0 | L121: 0 | M121: 0 | N121: 0
B122: Oklahoma | C122: tons | L122: 0
B123: Oregon | C123: tons | D123: 0 | E123: 0 | F123: 0 | G123: 0 | H123: 0 | I123: 0 | J123: 0 | K123: 0 | L123: 0 | M123: 0 | N123: 0
B124: Pennsylvania | C124: tons | D124: 0 | E124: 0 | F124: 0 | G124: 0 | H124: 0 | I124: 0 | J124: 0
B125: Rhode Island | C125: tons | D125: 0 | G125: 0 | H125: 0 | I125: 0 | J125: 0 | K125: 0 | L125: 0 | M125: 0 | N125: 0
B126: South Carolina | C126: tons | D126: 0 | E126: 0 | L126: 0
B127: South Dakota | C127: tons | D127: 0 | E127: 0 | H127: 0 | I127: 0 | J127: 0
B128: Tennessee | C128: tons | E128: 7976
B129: Texas | C129: tons | E129: 169 | G129: 1256 | H129: 1386 | I129: 984 | J129: 4592 | K129: 3312 | L129: 1148 | M129: 878 | N129: 8580
B130: Utah | C130: tons | E130: 0 | F130: 0 | G130: 0 | H130: 0 | I130: 0 | J130: 51068 | K130: 48496 | L130: 0 | M130: 0
B131: Vermont | C131: tons | D131: 0 | E131: 0 | F131: 0 | G131: 0 | H131: 0 | I131: 0 | J131: 0 | L131: 0 | M131: 0
B132: Virginia | C132: tons | E132: 1109 | F132: 193 | N132: 58413
B133: Washington | C133: tons | D133: 0 | E133: 0 | H133: 0 | I133: 0 | J133: 0 | L133: 0 | N133: 0
B134: West Virginia | C134: tons | E134: 0 | F134: 0 | G134: 55 | H134: 0 | J134: 0 | K134: 0 | L134: 0 | M134: 0 | N134: 0
B135: Wisconsin | C135: tons | D135: 0 | E135: 0 | F135: 0 | G135: 0 | H135: 0 | I135: 0 | J135: 0 | K135: 0 | L135: 0 | M135: 0 | N135: 0
B136: Wyoming | C136: tons | H136: 0 | I136: 0 | J136: 4191
B137: (1) Source: Clear Roads Annual Survey of State Winter Maintenance Data
B139: Magnesium Chloride Brine Applied1
B140: State | C140: Units | D140: 2015 | E140: 2016 | F140: 2017 | G140: 2018 | H140: 2019 | I140: 2020 | J140: 2021 | K140: 2022 | L140: 2023 | M140: 2024 | N140: 2025
B141: Alabama | C141: tons | E141: 0 | F141: 0 | G141: 0 | H141: 500 | I141: 225 | J141: 0
B142: Alaska | C142: tons | E142: 0 | G142: 50000 | N142: 28000
B143: Arizona | C143: tons | D143: 80000 | E143: 112000 | F143: 192000 | G143: 38463 | H143: 289057 | I143: 37000 | J143: 14000 | K143: 223949 | L143: 470000 | M143: 295909 | N143: 148708
B144: Arkansas | C144: tons | D144: 14700
B145: California | C145: tons | D145: 38027 | F145: 0 | G145: 450000 | H145: 15670 | I145: 0 | L145: 0 | M145: 0 | N145: 0
B146: Colorado | C146: tons | D146: 12965037 | E146: 12603829 | F146: 0 | G146: 10266402 | H146: 15581361 | I146: 15586700 | J146: 12165428 | K146: 9948821 | L146: 11743476 | M146: 8623436 | N146: 7411944
B147: Connecticut | C147: tons | D147: 1384400 | E147: 649000 | F147: 1163270 | G147: 1231650 | H147: 926801 | I147: 359149 | J147: 947187 | K147: 604605 | L147: 203498 | M147: 697301 | N147: 683971
B148: Delaware | C148: tons | D148: 0
B149: District of Columbia | C149: tons
...

Sheet B13. Mg(OH)2
B2: Magnesium Hydroxide
B3: (quantities are representative of quantified form listed below, unless otherwise specified)
B5: Byproduct Information
B6: Chemical Formula of Quantified Form: | C6: Mg(OH)2
B7: USGS Mineral Commodity Summary Page: | C7: Magnesium Compounds
B8: Demand Data Market Specificity: | C8: Byproduct
B9: Demand Data Resolution: | C9: Domestic
B13: Major End-Use Markets1
B14: Assigned End-Use Category | C14: End-Use | D14: Demand (kt) | E14: % of Demand | G14: Major domestic end uses for magnesium hydroxide were quantified by market share in USGS Minerals Yearbook 2020, Magnesium Compounds. This report further specifies magnesium hydroxide's primary use in water treatment as largely for treatment of wastewater and industrial effluent, so we categorize it under "Wastewater Treatment".
B15: Wastewater Treatment | C15: Water treatment | D15: – | E15: 0.8
B16: Miscellaneous Chemical Manufacturing | C16: Chemical intermediates | D16: – | E16: 0.11
B17: Other | C17: Other | D17: – | E17: 0.09
B18: (1) Source: USGS Minerals Yearbook 2020, Magnesium Compounds
B22: Domestic Demand
B23: Calculation Schema: | C23: Trade Balance Estimate
B24: Description | C24: Units | D24: 2021 | E24: 2022 | F24: 2023 | G24: 2024 | H24: 2025
B25: Domestic Production1 | C25: kt | D25: =D42 -> 188 | E25: =E42 -> 197 | F25: =F42 -> 173 | G25: =G42 -> 200 | H25: =H42 -> 200
B26: Imports for Consumption2 | C26: kt | D26: =E50 -> 12.765202 | E26: =F50 -> 13.075305 | F26: =G50 -> 9.980971 | G26: =H50 -> 11.150462 | H26: =I50 -> 13.101851
B27: Domestic Exports3 | C27: kt | D27: =E55 -> 17.71021 | E27: =F55 -> 16.046904 | F27: =G55 -> 14.518258 | G27: =H55 -> 17.811352 | H27: =I55 -> 17.483064
B28: Consumption, apparent4 | C28: kt | D28: =D25+D26-D27 -> 183.05499 | E28: =E25+E26-E27 -> 194.0284 | F28: =F25+F26-F27 -> 168.46271 | G28: =G25+G26-G27 -> 193.33911 | H28: =H25+H26-H27 -> 195.61879
B29: (1) See "Domestic Production" section below
B30: (2) See "Imports and Exports" section below
B31: (3) See "Imports and Exports" section below
B32: (4) Production + Imports – Exports
B34: Demand Calculations
B35: Domestic Production
B36: Reported volumes of magnesium hydroxide production are available from USGS for the years 2021-2023, so we adopt these values directly. With no production data yet available for 2024-2025, we approximate magnesium hydroxide production in these years based on production and trade balance data from 2021-2023. Throughout this time period, we see that production, imports for consumption, and exports for consumption remain quite stable, so we assume that there are no significant changes in magnesium hydroxide production in the two years to follow. To reflect this stability while erring on the side of overestimation to ensure we obtain a reasonable upper bound on demand, we round estimated production 200 kt for both years.
B38: Domestic Production, Magnesium Hydroxide
B39: Description | C39: Units | D39: 2021 | E39: 2022 | F39: 2023 | G39: 2024 | H39: 2025
B40: Reported domestic production1 | C40: kt | D40: 188 | E40: 197 | F40: 173 | G40: – | H40: –
B41: Estimated domestic production2 | C41: kt | D41: – | E41: – | F41: – | G41: 200 | H41: 200
B42: Assumed domestic production | C42: kt | D42: =D40 -> 188 | E42: =E40 -> 197 | F42: =F40 -> 173 | G42: =G41 -> 200 | H42: =H41 -> 200
B43: (1) Source: USGS Minerals Yearbook 2023, Magnesium Compounds
B44: (2) Conservative estimate based on previous years' production volumes
B46: Imports and Exports
B48: Imports for Consumption, Magnesium Hydroxide
B49: Product Name | C49: Units | D49: HTS Code | E49: 2021 | F49: 2022 | G49: 2023 | H49: 2024 | I49: 2025
B50: Magnesium hydroxide and peroxide1 | C50: kt | D50: 2816.10.0000 | E50: =_xlfn.XLOOKUP(_xlfn.CONCAT(_xlfn.TEXTSPLIT($D50,".")), 'S1. USITC Imports'!$B:$B,'S1. USITC Imports'!$J:$J)*_xlfn.XLOOKUP(_xlfn.CONCAT(_xlfn.TEXTSPLIT($D50,".")), 'S1. USITC Imports'!$B:$B,'S1. USITC Imports'!E:E) -> 12.765202 | F50: =_xlfn.XLOOKUP(_xlfn.CONCAT(_xlfn.TEXTSPLIT($D50,".")), 'S1. USITC Imports'!$B:$B,'S1. USITC Imports'!$J:$J)*_xlfn.XLOOKUP(_xlfn.CONCAT(_xlfn.TEXTSPLIT($D50,".")), 'S1. USITC Imports'!$B:$B,'S1. USITC Imports'!F:F) -> 13.075305 | G50: =_xlfn.XLOOKUP(_xlfn.CONCAT(_xlfn.TEXTSPLIT($D50,".")), 'S1. USITC Imports'!$B:$B,'S1. USITC Imports'!$J:$J)*_xlfn.XLOOKUP(_xlfn.CONCAT(_xlfn.TEXTSPLIT($D50,".")), 'S1. USITC Imports'!$B:$B,'S1. USITC Imports'!G:G) -> 9.980971 | H50: =_xlfn.XLOOKUP(_xlfn.CONCAT(_xlfn.TEXTSPLIT($D50,".")), 'S1. USITC Imports'!$B:$B,'S1. USITC Imports'!$J:$J)*_xlfn.XLOOKUP(_xlfn.CONCAT(_xlfn.TEXTSPLIT($D50,".")), 'S1. USITC Imports'!$B:$B,'S1. USITC Imports'!H:H) -> 11.150462 | I50: =_xlfn.XLOOKUP(_xlfn.CONCAT(_xlfn.TEXTSPLIT($D50,".")), 'S1. USITC Imports'!$B:$B,'S1. USITC Imports'!$J:$J)*_xlfn.XLOOKUP(_xlfn.CONCAT(_xlfn.TEXTSPLIT($D50,".")), 'S1. USITC Imports'!$B:$B,'S1. USITC Imports'!I:I) -> 13.101851
B51: (1) Source: USITC DataWeb, Imports for Consumption
B53: Domestic Exports, Magnesium Hydroxide
B54: Product Name | C54: Units | D54: HTS Code | E54: 2021 | F54: 2022 | G54: 2023 | H54: 2024 | I54: 2025
B55: Magnesium hydroxide and peroxide1 | C55: kt | D55: 2816.10.0000 | E55: =_xlfn.XLOOKUP(_xlfn.CONCAT(_xlfn.TEXTSPLIT($D55,".")), 'S2. USITC Exports'!$B:$B,'S2. USITC Exports'!$J:$J)*_xlfn.XLOOKUP(_xlfn.CONCAT(_xlfn.TEXTSPLIT($D55,".")), 'S2. USITC Exports'!$B:$B,'S2. USITC Exports'!E:E) -> 17.71021 | F55: =_xlfn.XLOOKUP(_xlfn.CONCAT(_xlfn.TEXTSPLIT($D55,".")), 'S2. USITC Exports'!$B:$B,'S2. USITC Exports'!$J:$J)*_xlfn.XLOOKUP(_xlfn.CONCAT(_xlfn.TEXTSPLIT($D55,".")), 'S2. USITC Exports'!$B:$B,'S2. USITC Exports'!F:F) -> 16.046904 | G55: =_xlfn.XLOOKUP(_xlfn.CONCAT(_xlfn.TEXTSPLIT($D55,".")), 'S2. USITC Exports'!$B:$B,'S2. USITC Exports'!$J:$J)*_xlfn.XLOOKUP(_xlfn.CONCAT(_xlfn.TEXTSPLIT($D55,".")), 'S2. USITC Exports'!$B:$B,'S2. USITC Exports'!G:G) -> 14.518258 | H55: =_xlfn.XLOOKUP(_xlfn.CONCAT(_xlfn.TEXTSPLIT($D55,".")), 'S2. USITC Exports'!$B:$B,'S2. USITC Exports'!$J:$J)*_xlfn.XLOOKUP(_xlfn.CONCAT(_xlfn.TEXTSPLIT($D55,".")), 'S2. USITC Exports'!$B:$B,'S2. USITC Exports'!H:H) -> 17.811352 | I55: =_xlfn.XLOOKUP(_xlfn.CONCAT(_xlfn.TEXTSPLIT($D55,".")), 'S2. USITC Exports'!$B:$B,'S2. USITC Exports'!$J:$J)*_xlfn.XLOOKUP(_xlfn.CONCAT(_xlfn.TEXTSPLIT($D55,".")), 'S2. USITC Exports'!$B:$B,'S2. USITC Exports'!I:I) -> 17.483064
B56: (1) Source: USITC DataWeb, Domestic Exports
B60: Pricing
B61: Description | C61: Units | D61: HTS Code | E61: 2021 | F61: 2022 | G61: 2023 | H61: 2024 | I61: 2025
B62: Total FAS Value, Domestic Exports1 | C62: $ | D62: 2816.10.0000 | E62: =_xlfn.XLOOKUP(_xlfn.CONCAT(_xlfn.TEXTSPLIT($D62,".")), 'S3. USITC FAS Value'!$B:$B,'S3. USITC FAS Value'!E:E) -> 16706683 | F62: =_xlfn.XLOOKUP(_xlfn.CONCAT(_xlfn.TEXTSPLIT($D62,".")), 'S3. USITC FAS Value'!$B:$B,'S3. USITC FAS Value'!F:F) -> 18313175 | G62: =_xlfn.XLOOKUP(_xlfn.CONCAT(_xlfn.TEXTSPLIT($D62,".")), 'S3. USITC FAS Value'!$B:$B,'S3. USITC FAS Value'!G:G) -> 15579453 | H62: =_xlfn.XLOOKUP(_xlfn.CONCAT(_xlfn.TEXTSPLIT($D62,".")), 'S3. USITC FAS Value'!$B:$B,'S3. USITC FAS Value'!H:H) -> 17360829 | I62: =_xlfn.XLOOKUP(_xlfn.CONCAT(_xlfn.TEXTSPLIT($D62,".")), 'S3. USITC FAS Value'!$B:$B,'S3. USITC FAS Value'!I:I) -> 17112550
B63: Total Domestic Exports2 | C63: t | D63: 2816.10.0000 | E63: =E55*1000 -> 17710.21 | F63: =F55*1000 -> 16046.904 | G63: =G55*1000 -> 14518.258 | H63: =H55*1000 -> 17811.352 | I63: =I55*1000 -> 17483.064
B64: Price, average unit value, domestic exports FAS | C64: $/t | D64: – | E64: =E62/E63 -> 943.33625 | F64: =F62/F63 -> 1141.2279 | G64: =G62/G63 -> 1073.0938 | H64: =H62/H63 -> 974.70585 | I64: =I62/I63 -> 978.80726
B65: (1) Source: USITC DataWeb, Domestic Exports
B66: (2) See "Imports and Exports" section above

Sheet B14. MgSO4
B2: Magnesium Sulfate
B3: (quantities are representative of quantified form listed below, unless otherwise specified)
B5: Byproduct Information
B6: Chemical Formula of Quantified Form: | C6: MgSO4
B7: USGS Mineral Commodity Summary Page: | C7: Magnesium Compounds
B8: Demand Data Market Specificity: | C8: Byproduct
B9: Demand Data Resolution: | C9: Domestic
B13: Major End-Use Markets1
B14: Assigned End-Use Category | C14: End-Use | D14: Demand (kt) | E14: % of Demand | G14: Major domestic end uses for magnesium sulfate were most recently quantified by market share in USGS Minerals Yearbook 2020, Magnesium Compounds.
B15: Cosmetics and Personal Care Product Manufacturing | C15: Cosmetics and personal care | D15: – | E15: 0.48
B16: Miscellaneous Chemical Manufacturing | C16: Chemical intermediates | D16: – | E16: 0.22
B17: Pulp and Paper Manufacturing | C17: Pulp and paper | D17: – | E17: 0.12
B18: Miscellaneous Fertilizer Application | C18: Fertilizer | D18: – | E18: 0.1
B19: Other | C19: Other | D19: – | E19: 0.08
B20: (1) Source: USGS Minerals Yearbook 2020, Magnesium Compounds
B24: Domestic Demand
B25: Calculation Schema: | C25: Trade Balance Estimate
B26: Description | C26: Units | D26: 2021 | E26: 2022 | F26: 2023 | G26: 2024 | H26: 2025
B27: Domestic Production1 | C27: kt | D27: =I44 -> 81.9 | E27: =J44 -> 88.68 | F27: =K44 -> 95.46 | G27: =L44 -> 102.24 | H27: =M44 -> 109.02
B28: Imports for Consumption2 | C28: kt | D28: =E55 -> 48.172394 | E28: =F55 -> 39.152402 | F28: =G55 -> 27.625271 | G28: =H55 -> 46.59511 | H28: =I55 -> 44.332581
B29: Domestic Exports3 | C29: kt | D29: =E62 -> 14.372326 | E29: =F62 -> 15.343387 | F29: =G62 -> 14.007673 | G29: =H62 -> 12.996956 | H29: =I62 -> 10.677463
B30: Consumption, apparent4 | C30: kt | D30: =D27+D28-D29 -> 115.70007 | E30: =E27+E28-E29 -> 112.48901 | F30: =F27+F28-F29 -> 109.0776 | G30: =G27+G28-G29 -> 135.83815 | H30: =H27+H28-H29 -> 142.67512
B31: (1) See "Domestic Production" section below
B32: (2) See "Imports and Exports" section below
B33: (3) See "Imports and Exports" section below
B34: (4) Production + Imports – Exports
B36: Demand Calculations
B37: Domestic Production
B38: USGS has withheld magnesium sulfate production values since 2020. In the five years leading up to that, however, we see a near-linear increase in magnesium sulfate production (R2=0.96). To generate conservative estimates of magnesium sulfate production, we assume this linear increase remains steady from 2020-2025. To calculate the rate of increase, we fit a linear trendline to the 2016-2020 data and use the resulting equation to predict future production.
B40: Domestic Production, Magnesium Sulfate
B41: Description | C41: Units | D41: 2016 | E41: 2017 | F41: 2018 | G41: 2019 | H41: 2020 | I41: 2021 | J41: 2022 | K41: 2023 | L41: 2024 | M41: 2025
B42: Reported domestic production1 | C42: kt | D42: 48.1 | E42: 52.8 | F42: 63 | G42: 71 | H42: 72.9 | I42: – | J42: – | K42: – | L42: – | M42: –
B43: Estimated domestic production2 | C43: kt | D43: =(SLOPE($D$42:$H$42,$D$41:$H$41)*D41)+INTERCEPT($D$42:$H$42,$D$41:$H$41) -> 48 | E43: =(SLOPE($D$42:$H$42,$D$41:$H$41)*E41)+INTERCEPT($D$42:$H$42,$D$41:$H$41) -> 54.78 | F43: =(SLOPE($D$42:$H$42,$D$41:$H$41)*F41)+INTERCEPT($D$42:$H$42,$D$41:$H$41) -> 61.56 | G43: =(SLOPE($D$42:$H$42,$D$41:$H$41)*G41)+INTERCEPT($D$42:$H$42,$D$41:$H$41) -> 68.34 | H43: =(SLOPE($D$42:$H$42,$D$41:$H$41)*H41)+INTERCEPT($D$42:$H$42,$D$41:$H$41) -> 75.12 | I43: =(SLOPE($D$42:$H$42,$D$41:$H$41)*I41)+INTERCEPT($D$42:$H$42,$D$41:$H$41) -> 81.9 | J43: =(SLOPE($D$42:$H$42,$D$41:$H$41)*J41)+INTERCEPT($D$42:$H$42,$D$41:$H$41) -> 88.68 | K43: =(SLOPE($D$42:$H$42,$D$41:$H$41)*K41)+INTERCEPT($D$42:$H$42,$D$41:$H$41) -> 95.46 | ... M43: =(SLOPE($D$42:$H$42,$D$41:$H$41)*M41)+INTERCEPT($D$42:$H$42,$D$41:$H$41) -> 109.02
B44: Assumed domestic production | C44: kt | D44: – | E44: – | F44: – | G44: – | H44: – | I44: =I43 -> 81.9 | J44: =J43 -> 88.68 | K44: =K43 -> 95.46 | L44: =L43 -> 102.24 | M44: =M43 -> 109.02
B45: (1) Source: USGS Minerals Yearbook 2016-2020, Magnesium Compounds
B46: (2) Conservative estimate assuming constant linear increase in production based on best fit line for production from 2016-2020
B48: Imports and Exports
B50: Imports for Consumption, Magnesium Sulfate
B51: Product Name | C51: Units | D51: HTS Code | E51: 2021 | F51: 2022 | G51: 2023 | H51: 2024 | I51: 2025
B52: Magnesium sulfate1 | C52: kt | D52: 2833.21.0000 | E52: =_xlfn.XLOOKUP(_xlfn.CONCAT(_xlfn.TEXTSPLIT($D52,".")), 'S1. USITC Imports'!$B:$B,'S1. USITC Imports'!$J:$J)*_xlfn.XLOOKUP(_xlfn.CONCAT(_xlfn.TEXTSPLIT($D52,".")), 'S1. USITC Imports'!$B:$B,'S1. USITC Imports'!E:E) -> 44.531212 | F52: =_xlfn.XLOOKUP(_xlfn.CONCAT(_xlfn.TEXTSPLIT($D52,".")), 'S1. USITC Imports'!$B:$B,'S1. USITC Imports'!$J:$J)*_xlfn.XLOOKUP(_xlfn.CONCAT(_xlfn.TEXTSPLIT($D52,".")), 'S1. USITC Imports'!$B:$B,'S1. USITC Imports'!F:F) -> 31.059237 | G52: =_xlfn.XLOOKUP(_xlfn.CONCAT(_xlfn.TEXTSPLIT($D52,".")), 'S1. USITC Imports'!$B:$B,'S1. USITC Imports'!$J:$J)*_xlfn.XLOOKUP(_xlfn.CONCAT(_xlfn.TEXTSPLIT($D52,".")), 'S1. USITC Imports'!$B:$B,'S1. USITC Imports'!G:G) -> 26.138337 | H52: =_xlfn.XLOOKUP(_xlfn.CONCAT(_xlfn.TEXTSPLIT($D52,".")), 'S1. USITC Imports'!$B:$B,'S1. USITC Imports'!$J:$J)*_xlfn.XLOOKUP(_xlfn.CONCAT(_xlfn.TEXTSPLIT($D52,".")), 'S1. USITC Imports'!$B:$B,'S1. USITC Imports'!H:H) -> 36.880121 | I52: =_xlfn.XLOOKUP(_xlfn.CONCAT(_xlfn.TEXTSPLIT($D52,".")), 'S1. USITC Imports'!$B:$B,'S1. USITC Imports'!$J:$J)*_xlfn.XLOOKUP(_xlfn.CONCAT(_xlfn.TEXTSPLIT($D52,".")), 'S1. USITC Imports'!$B:$B,'S1. USITC Imports'!I:I) -> 39.877143
B53: Kieserite1 | C53: kt | D53: 2530.20.1000 | E53: =_xlfn.XLOOKUP(_xlfn.CONCAT(_xlfn.TEXTSPLIT($D53,".")), 'S1. USITC Imports'!$B:$B,'S1. USITC Imports'!$J:$J)*_xlfn.XLOOKUP(_xlfn.CONCAT(_xlfn.TEXTSPLIT($D53,".")), 'S1. USITC Imports'!$B:$B,'S1. USITC Imports'!E:E) -> 2.727343 | F53: =_xlfn.XLOOKUP(_xlfn.CONCAT(_xlfn.TEXTSPLIT($D53,".")), 'S1. USITC Imports'!$B:$B,'S1. USITC Imports'!$J:$J)*_xlfn.XLOOKUP(_xlfn.CONCAT(_xlfn.TEXTSPLIT($D53,".")), 'S1. USITC Imports'!$B:$B,'S1. USITC Imports'!F:F) -> 7.481285 | G53: =_xlfn.XLOOKUP(_xlfn.CONCAT(_xlfn.TEXTSPLIT($D53,".")), 'S1. USITC Imports'!$B:$B,'S1. USITC Imports'!$J:$J)*_xlfn.XLOOKUP(_xlfn.CONCAT(_xlfn.TEXTSPLIT($D53,".")), 'S1. USITC Imports'!$B:$B,'S1. USITC Imports'!G:G) -> 0.661359 | H53: =_xlfn.XLOOKUP(_xlfn.CONCAT(_xlfn.TEXTSPLIT($D53,".")), 'S1. USITC Imports'!$B:$B,'S1. USITC Imports'!$J:$J)*_xlfn.XLOOKUP(_xlfn.CONCAT(_xlfn.TEXTSPLIT($D53,".")), 'S1. USITC Imports'!$B:$B,'S1. USITC Imports'!H:H) -> 8.841482 | I53: =_xlfn.XLOOKUP(_xlfn.CONCAT(_xlfn.TEXTSPLIT($D53,".")), 'S1. USITC Imports'!$B:$B,'S1. USITC Imports'!$J:$J)*_xlfn.XLOOKUP(_xlfn.CONCAT(_xlfn.TEXTSPLIT($D53,".")), 'S1. USITC Imports'!$B:$B,'S1. USITC Imports'!I:I) -> 2.130753
B54: Epsom salts1 | C54: kt | D54: 2530.20.2000 | E54: =_xlfn.XLOOKUP(_xlfn.CONCAT(_xlfn.TEXTSPLIT($D54,".")), 'S1. USITC Imports'!$B:$B,'S1. USITC Imports'!$J:$J)*_xlfn.XLOOKUP(_xlfn.CONCAT(_xlfn.TEXTSPLIT($D54,".")), 'S1. USITC Imports'!$B:$B,'S1. USITC Imports'!E:E) -> 0.913839 | F54: =_xlfn.XLOOKUP(_xlfn.CONCAT(_xlfn.TEXTSPLIT($D54,".")), 'S1. USITC Imports'!$B:$B,'S1. USITC Imports'!$J:$J)*_xlfn.XLOOKUP(_xlfn.CONCAT(_xlfn.TEXTSPLIT($D54,".")), 'S1. USITC Imports'!$B:$B,'S1. USITC Imports'!F:F) -> 0.61188 | G54: =_xlfn.XLOOKUP(_xlfn.CONCAT(_xlfn.TEXTSPLIT($D54,".")), 'S1. USITC Imports'!$B:$B,'S1. USITC Imports'!$J:$J)*_xlfn.XLOOKUP(_xlfn.CONCAT(_xlfn.TEXTSPLIT($D54,".")), 'S1. USITC Imports'!$B:$B,'S1. USITC Imports'!G:G) -> 0.825575 | H54: =_xlfn.XLOOKUP(_xlfn.CONCAT(_xlfn.TEXTSPLIT($D54,".")), 'S1. USITC Imports'!$B:$B,'S1. USITC Imports'!$J:$J)*_xlfn.XLOOKUP(_xlfn.CONCAT(_xlfn.TEXTSPLIT($D54,".")), 'S1. USITC Imports'!$B:$B,'S1. USITC Imports'!H:H) -> 0.873507 | I54: =_xlfn.XLOOKUP(_xlfn.CONCAT(_xlfn.TEXTSPLIT($D54,".")), 'S1. USITC Imports'!$B:$B,'S1. USITC Imports'!$J:$J)*_xlfn.XLOOKUP(_xlfn.CONCAT(_xlfn.TEXTSPLIT($D54,".")), 'S1. USITC Imports'!$B:$B,'S1. USITC Imports'!I:I) -> 2.324685
B55: Total | C55: kt | D55: – | E55: =SUM(E52:E54) -> 48.172394 | F55: =SUM(F52:F54) -> 39.152402 | G55: =SUM(G52:G54) -> 27.625271 | H55: =SUM(H52:H54) -> 46.59511 | I55: =SUM(I52:I54) -> 44.332581
B56: (1) Source: USITC DataWeb, Imports for Consumption
B58: Domestic Exports, Magnesium Sulfate
B59: Product Name | C59: Units | D59: HTS Code | E59: 2021 | F59: 2022 | G59: 2023 | H59: 2024 | I59: 2025
B60: Magnesium sulfate1 | C60: kt | D60: 2833.21.0000 | E60: =_xlfn.XLOOKUP(_xlfn.CONCAT(_xlfn.TEXTSPLIT($D60,".")), 'S2. USITC Exports'!$B:$B,'S2. USITC Exports'!$J:$J)*_xlfn.XLOOKUP(_xlfn.CONCAT(_xlfn.TEXTSPLIT($D60,".")), 'S2. USITC Exports'!$B:$B,'S2. USITC Exports'!E:E) -> 14.203936 | F60: =_xlfn.XLOOKUP(_xlfn.CONCAT(_xlfn.TEXTSPLIT($D60,".")), 'S2. USITC Exports'!$B:$B,'S2. USITC Exports'!$J:$J)*_xlfn.XLOOKUP(_xlfn.CONCAT(_xlfn.TEXTSPLIT($D60,".")), 'S2. USITC Exports'!$B:$B,'S2. USITC Exports'!F:F) -> 15.135331 | G60: =_xlfn.XLOOKUP(_xlfn.CONCAT(_xlfn.TEXTSPLIT($D60,".")), 'S2. USITC Exports'!$B:$B,'S2. USITC Exports'!$J:$J)*_xlfn.XLOOKUP(_xlfn.CONCAT(_xlfn.TEXTSPLIT($D60,".")), 'S2. USITC Exports'!$B:$B,'S2. USITC Exports'!G:G) -> 13.639578 | H60: =_xlfn.XLOOKUP(_xlfn.CONCAT(_xlfn.TEXTSPLIT($D60,".")), 'S2. USITC Exports'!$B:$B,'S2. USITC Exports'!$J:$J)*_xlfn.XLOOKUP(_xlfn.CONCAT(_xlfn.TEXTSPLIT($D60,".")), 'S2. USITC Exports'!$B:$B,'S2. USITC Exports'!H:H) -> 12.844323 | I60: =_xlfn.XLOOKUP(_xlfn.CONCAT(_xlfn.TEXTSPLIT($D60,".")), 'S2. USITC Exports'!$B:$B,'S2. USITC Exports'!$J:$J)*_xlfn.XLOOKUP(_xlfn.CONCAT(_xlfn.TEXTSPLIT($D60,".")), 'S2. USITC Exports'!$B:$B,'S2. USITC Exports'!I:I) -> 10.581756
B61: Kieserite and epsom salts (natural magnesium sulfates)1 | C61: kt | D61: 2530.20.0000 | E61: =_xlfn.XLOOKUP(_xlfn.CONCAT(_xlfn.TEXTSPLIT($D61,".")), 'S2. USITC Exports'!$B:$B,'S2. USITC Exports'!$J:$J)*_xlfn.XLOOKUP(_xlfn.CONCAT(_xlfn.TEXTSPLIT($D61,".")), 'S2. USITC Exports'!$B:$B,'S2. USITC Exports'!E:E) -> 0.16839 | F61: =_xlfn.XLOOKUP(_xlfn.CONCAT(_xlfn.TEXTSPLIT($D61,".")), 'S2. USITC Exports'!$B:$B,'S2. USITC Exports'!$J:$J)*_xlfn.XLOOKUP(_xlfn.CONCAT(_xlfn.TEXTSPLIT($D61,".")), 'S2. USITC Exports'!$B:$B,'S2. USITC Exports'!F:F) -> 0.208056 | G61: =_xlfn.XLOOKUP(_xlfn.CONCAT(_xlfn.TEXTSPLIT($D61,".")), 'S2. USITC Exports'!$B:$B,'S2. USITC Exports'!$J:$J)*_xlfn.XLOOKUP(_xlfn.CONCAT(_xlfn.TEXTSPLIT($D61,".")), 'S2. USITC Exports'!$B:$B,'S2. USITC Exports'!G:G) -> 0.368095 | H61: =_xlfn.XLOOKUP(_xlfn.CONCAT(_xlfn.TEXTSPLIT($D61,".")), 'S2. USITC Exports'!$B:$B,'S2. USITC Exports'!$J:$J)*_xlfn.XLOOKUP(_xlfn.CONCAT(_xlfn.TEXTSPLIT($D61,".")), 'S2. USITC Exports'!$B:$B,'S2. USITC Exports'!H:H) -> 0.152633 | I61: =_xlfn.XLOOKUP(_xlfn.CONCAT(_xlfn.TEXTSPLIT($D61,".")), 'S2. USITC Exports'!$B:$B,'S2. USITC Exports'!$J:$J)*_xlfn.XLOOKUP(_xlfn.CONCAT(_xlfn.TEXTSPLIT($D61,".")), 'S2. USITC Exports'!$B:$B,'S2. USITC Exports'!I:I) -> 0.095707
B62: Total | C62: kt | D62: – | E62: =SUM(E60:E61) -> 14.372326 | F62: =SUM(F60:F61) -> 15.343387 | G62: =SUM(G60:G61) -> 14.007673 | H62: =SUM(H60:H61) -> 12.996956 | I62: =SUM(I60:I61) -> 10.677463
B63: (1) Source: USITC DataWeb, Domestic Exports
B67: Pricing
B68: Description | C68: Units | D68: HTS Code | E68: 2021 | F68: 2022 | G68: 2023 | H68: 2024 | I68: 2025
B69: Total FAS Value, Domestic Exports1,3 | C69: $ | D69: 2833.21.0000 | E69: =_xlfn.XLOOKUP(_xlfn.CONCAT(_xlfn.TEXTSPLIT($D69,".")), 'S3. USITC FAS Value'!$B:$B,'S3. USITC FAS Value'!E:E) -> 9553018 | F69: =_xlfn.XLOOKUP(_xlfn.CONCAT(_xlfn.TEXTSPLIT($D69,".")), 'S3. USITC FAS Value'!$B:$B,'S3. USITC FAS Value'!F:F) -> 10044505 | G69: =_xlfn.XLOOKUP(_xlfn.CONCAT(_xlfn.TEXTSPLIT($D69,".")), 'S3. USITC FAS Value'!$B:$B,'S3. USITC FAS Value'!G:G) -> 8952369 | H69: =_xlfn.XLOOKUP(_xlfn.CONCAT(_xlfn.TEXTSPLIT($D69,".")), 'S3. USITC FAS Value'!$B:$B,'S3. USITC FAS Value'!H:H) -> 9018796 | I69: =_xlfn.XLOOKUP(_xlfn.CONCAT(_xlfn.TEXTSPLIT($D69,".")), 'S3. USITC FAS Value'!$B:$B,'S3. USITC FAS Value'!I:I) -> 8055095
B70: Total Domestic Exports2,3 | C70: t | D70: 2833.21.0000 | E70: =E60*1000 -> 14203.936 | F70: =F60*1000 -> 15135.331 | G70: =G60*1000 -> 13639.578 | H70: =H60*1000 -> 12844.323 | I70: =I60*1000 -> 10581.756
B71: Price, average unit value, domestic exports FAS | C71: $/t | D71: – | E71: =E69/E70 -> 672.56132 | F71: =F69/F70 -> 663.64621 | G71: =G69/G70 -> 656.35234 | H71: =H69/H70 -> 702.16204 | I71: =I69/I70 -> 761.22479
B72: (1) Source: USITC DataWeb, Domestic Exports
B73: (2) See "Imports and Exports" section above
B74: (3) Export statistics for HTS Code 2833.21.0000 Magnesium Sulfate used as representative for all forms of magnesium sulfate

Sheet B15. NaCl
B2: Sodium Chloride
B3: (quantities are representative of quantified form listed below, unless otherwise specified)
B5: Byproduct Information
B6: Chemical Formula of Quantified Form: | C6: NaCl
B7: USGS Mineral Commodity Summary Page: | C7: Salt
B8: Demand Data Market Specificity: | C8: Byproduct
B9: Demand Data Resolution: | C9: Domestic
B13: Major End-Use Markets1
B14: Assigned End-Use Category | C14: End-Use | D14: Demand (kt) | E14: % of Demand
B15: Miscellaneous Chemical Manufacturing | C15: Chemical industry | E15: 0.42
B16: Deicing and Dust Control | C16: Highway deicing | E16: 0.37
B17: Other | C17: Other applications | E17: 0.21
B18: (1) Source: USGS Mineral Commodity Summaries 2026, Salt
B22: Domestic Demand
B23: Calculation Schema: | C23: Direct Report
B24: Description | C24: Units | D24: 2021 | E24: 2022 | F24: 2023 | G24: 2024 | H24: 2025
B25: Consumption, apparent1 | C25: kt | D25: 63400 | E25: 62300 | F25: 53200 | G25: 51300 | H25: 57000
B26: (1) Source: USGS Mineral Commodity Summaries 2026, Salt
B30: Pricing
B31: Description | C31: Units | D31: HTS Code | E31: 2021 | F31: 2022 | G31: 2023 | H31: 2024 | I31: 2025
B32: Total FAS Value, Domestic Exports1 | C32: $ | D32: 2501.00.0000 | E32: =_xlfn.XLOOKUP(_xlfn.CONCAT(_xlfn.TEXTSPLIT($D32,".")), 'S3. USITC FAS Value'!$B:$B,'S3. USITC FAS Value'!E:E) -> 206922349 | F32: =_xlfn.XLOOKUP(_xlfn.CONCAT(_xlfn.TEXTSPLIT($D32,".")), 'S3. USITC FAS Value'!$B:$B,'S3. USITC FAS Value'!F:F) -> 206013111 | G32: =_xlfn.XLOOKUP(_xlfn.CONCAT(_xlfn.TEXTSPLIT($D32,".")), 'S3. USITC FAS Value'!$B:$B,'S3. USITC FAS Value'!G:G) -> 258942576 | H32: =_xlfn.XLOOKUP(_xlfn.CONCAT(_xlfn.TEXTSPLIT($D32,".")), 'S3. USITC FAS Value'!$B:$B,'S3. USITC FAS Value'!H:H) -> 259216789 | I32: =_xlfn.XLOOKUP(_xlfn.CONCAT(_xlfn.TEXTSPLIT($D32,".")), 'S3. USITC FAS Value'!$B:$B,'S3. USITC FAS Value'!I:I) -> 233434303
B33: Total Domestic Exports1 | C33: t | D33: 2501.00.0000 | E33: =1000*_xlfn.XLOOKUP(_xlfn.CONCAT(_xlfn.TEXTSPLIT($D33,".")), 'S2. USITC Exports'!$B:$B,'S2. USITC Exports'!$J:$J)*_xlfn.XLOOKUP(_xlfn.CONCAT(_xlfn.TEXTSPLIT($D33,".")), 'S2. USITC Exports'!$B:$B,'S2. USITC Exports'!E:E) -> 1038492 | F33: =1000*_xlfn.XLOOKUP(_xlfn.CONCAT(_xlfn.TEXTSPLIT($D33,".")), 'S2. USITC Exports'!$B:$B,'S2. USITC Exports'!$J:$J)*_xlfn.XLOOKUP(_xlfn.CONCAT(_xlfn.TEXTSPLIT($D33,".")), 'S2. USITC Exports'!$B:$B,'S2. USITC Exports'!F:F) -> 927726 | G33: =1000*_xlfn.XLOOKUP(_xlfn.CONCAT(_xlfn.TEXTSPLIT($D33,".")), 'S2. USITC Exports'!$B:$B,'S2. USITC Exports'!$J:$J)*_xlfn.XLOOKUP(_xlfn.CONCAT(_xlfn.TEXTSPLIT($D33,".")), 'S2. USITC Exports'!$B:$B,'S2. USITC Exports'!G:G) -> 2321754 | H33: =1000*_xlfn.XLOOKUP(_xlfn.CONCAT(_xlfn.TEXTSPLIT($D33,".")), 'S2. USITC Exports'!$B:$B,'S2. USITC Exports'!$J:$J)*_xlfn.XLOOKUP(_xlfn.CONCAT(_xlfn.TEXTSPLIT($D33,".")), 'S2. USITC Exports'!$B:$B,'S2. USITC Exports'!H:H) -> 2177298 | I33: =1000*_xlfn.XLOOKUP(_xlfn.CONCAT(_xlfn.TEXTSPLIT($D33,".")), 'S2. USITC Exports'!$B:$B,'S2. USITC Exports'!$J:$J)*_xlfn.XLOOKUP(_xlfn.CONCAT(_xlfn.TEXTSPLIT($D33,".")), 'S2. USITC Exports'!$B:$B,'S2. USITC Exports'!I:I) -> 1832586
B34: Price, average unit value, domestic exports FAS | C34: $/t | D34: – | E34: =E32/E33 -> 199.25271 | F34: =F32/F33 -> 222.06245 | G34: =G32/G33 -> 111.52886 | H34: =H32/H33 -> 119.05435 | I34: =I32/I33 -> 127.37973
B35: (1) Source: USITC DataWeb, Domestic Exports

Sheet B16. Na2CO3
B2: Sodium Carbonate
B3: (quantities are representative of quantified form listed below, unless otherwise specified)
B5: Byproduct Information
B6: Chemical Formula of Quantified Form: | C6: Na2CO3
B7: USGS Mineral Commodity Summary Page: | C7: Soda Ash
B8: Demand Data Market Specificity: | C8: Byproduct
B9: Demand Data Resolution: | C9: Domestic
B13: Major End-Use Markets1
B14: Assigned End-Use Category | C14: End-Use | D14: Demand (kt) | E14: % of Demand | G14: End-uses with a market share <5% were consolidated into the "Other" category. "Distributors" was also assigned "Other," as it is too general to assign an appropriate disaggregation proxy.
B15: Glass Manufacturing | C15: Glass | D15: – | E15: 0.45
B16: Miscellaneous Chemical Manufacturing | C16: Chemicals | D16: – | E16: 0.28
B17: Other | C17: Miscellaneous uses | D17: – | E17: 0.09
B18: Other | C18: Distributors | D18: – | E18: 0.07
B19: Miscellaneous Chemical Manufacturing | C19: Soaps and detergents | D19: – | E19: 0.05
B20: Other | C20: Flue gas desulfurization | D20: – | E20: 0.04
B21: Other | C21: Pulp and paper | D21: – | E21: 0.01
B22: Other | C22: Water treatment | D22: – | E22: 0.01
B23: (1) Source: USGS Minera Commodity Summaries 2026, Soda Ash
B27: Domestic Demand
B28: Calculation Schema: | C28: Direct Report
B29: Description | C29: Units | D29: 2021 | E29: 2022 | F29: 2023 | G29: 2024 | H29: 2025
B30: Consumption, apparent1 | C30: kt | D30: 4550 | E30: 4760 | F30: 4360 | G30: 4350 | H30: 4700
B31: (1) Source: USGS Minera Commodity Summaries 2026, Soda Ash
B35: Pricing
B36: Description | C36: Units | D36: 2021 | E36: 2022 | F36: 2023 | G36: 2024 | H36: 2025
B37: Price, average unit value o sales (natural source), f.o.b. mine or plant1 | C37: $/t | D37: 133.37 | E37: 178.52 | F37: 211.48 | G37: 169.35 | H37: 150
B38: (1) Source: USGS Minera Commodity Summaries 2026, Soda Ash

Sheet B17. NaOH
B2: Sodium Hydroxide
B3: (quantities are representative of quantified form listed below, unless otherwise specified)
B5: Byproduct Information
B6: Chemical Formula of Quantified Form: | C6: NaOH
B7: 8-Digit USITC HTS Number: | C7: 2815.12.00
B8: Demand Data Market Specificity: | C8: Byproduct
B9: Demand Data Resolution: | C9: Domestic
B13: Major End-Use Markets1
B14: Assigned End-Use Category | C14: End-Use | D14: Demand (kt) | E14: % of Demand | G14: End-uses with a market share <5% are consolidated into the "Other" category.
B15: Organic Chemical Manufacturing | C15: Organic chemical synthesis | E15: 0.23
B16: Pulp and Paper Manufacturing | C16: Pulp and paper manufacturing | E16: 0.22
B17: Miscellaneous Chemical Manufacturing | C17: Inorganic chemical production | E17: 0.22
B18: Other | C18: Special applications | E18: 0.3
B19: Other | C19: Water treatment | E19: 0.03
B20: (1) Source: EPA Water Treatment Chemical Supply Chain Profile, Sodium Hydroxide
B24: Domestic Demand
B25: Calculation Schema: | C25: Trade Balance Estimate
B26: Description | C26: Units | D26: 2021 | E26: 2022 | F26: 2023 | G26: 2024 | H26: 2025
B27: Domestic Production1 | C27: kt | D27: =D44 -> 17000 | E27: =E44 -> 17000 | F27: =F44 -> 17000 | G27: =G44 -> 17000 | H27: =H44 -> 17000
B28: Imports for Consumption2 | C28: kt | D28: =E52 -> 1144.776 | E28: =F52 -> 1245.4077 | F28: =G52 -> 1123.0039 | G28: =H52 -> 1045.788 | H28: =I52 -> 918.25798
B29: Domestic Exports3 | C29: kt | D29: =E57 -> 5747.9576 | E29: =F57 -> 5654.8955 | F29: =G57 -> 5286.001 | G29: =H57 -> 5751.4521 | H29: =I57 -> 6472.504
B30: Consumption, apparent4 | C30: kt | D30: =D27+D28-D29 -> 12396.818 | E30: =E27+E28-E29 -> 12590.512 | F30: =F27+F28-F29 -> 12837.003 | G30: =G27+G28-G29 -> 12294.336 | H30: =H27+H28-H29 -> 11445.754
B31: (1) See "Domestic Production" section below
B32: (2) See "Imports and Exports" section below
B33: (3) See "Imports and Exports" section below
B34: (4) Production + Imports – Exports
B36: Demand Calculations
B37: Domestic Production
B38: Domestic production of sodium hydroxide (caustic soda) is tracked by the U.S. EPA under the Toxic Substances Control Act. When calculating the total production volumes of caustic soda from the 2024 CDR dataset, however, we find that the disclosed production volumes (~1,300-1,400 kt in total, each year) represent only a small fraction of total North American caustic soda manufacturing capacity (17,000 kt),1 likely due to information withheld from the public CDR dataset as confidential business information (CBI). With no reliable source of U.S. production, we adopt the reported caustic soda production capacity of North American chloralkali manufacturers (17,000 kt) as a conservative upper bound on domestic caustic soda production across all years.
B39: (1) Source: 2025 Annual Report, Olin Corporation
B41: Domestic Production, Sodium Hydroxide
B42: Description | C42: Units | D42: 2021 | E42: 2022 | F42: 2023 | G42: 2024 | H42: 2025
B43: Caustic soda production capacity of North American chloralkali plants1 | C43: kt | D43: 17000 | E43: 17000 | F43: 17000 | G43: 17000 | H43: 17000
B44: Assumed domestic production | C44: kt | D44: =D43 -> 17000 | E44: =E43 -> 17000 | F44: =F43 -> 17000 | G44: =G43 -> 17000 | H44: =H43 -> 17000
B45: (1) Source: Annual Reports, Olin Corporation. Retrieved from the U.S. Securities and Exchange Commission's Electronic Data Gathering, Analysis, and Retrieval (EDGAR) system for OLIN CORP (CIK 000074303).
B48: Imports and Exports
B50: Imports for Consumption, Sodium Hydroxide
B51: Product Name | C51: Units | D51: HTS Code | E51: 2021 | F51: 2022 | G51: 2023 | H51: 2024 | I51: 2025
B52: Sodium hydroxide (aqueous)1 | C52: kt | D52: 2815.12.0000 | E52: =_xlfn.XLOOKUP(_xlfn.CONCAT(_xlfn.TEXTSPLIT($D52,".")), 'S1. USITC Imports'!$B:$B,'S1. USITC Imports'!$J:$J)*_xlfn.XLOOKUP(_xlfn.CONCAT(_xlfn.TEXTSPLIT($D52,".")), 'S1. USITC Imports'!$B:$B,'S1. USITC Imports'!E:E) -> 1144.776 | F52: =_xlfn.XLOOKUP(_xlfn.CONCAT(_xlfn.TEXTSPLIT($D52,".")), 'S1. USITC Imports'!$B:$B,'S1. USITC Imports'!$J:$J)*_xlfn.XLOOKUP(_xlfn.CONCAT(_xlfn.TEXTSPLIT($D52,".")), 'S1. USITC Imports'!$B:$B,'S1. USITC Imports'!F:F) -> 1245.4077 | G52: =_xlfn.XLOOKUP(_xlfn.CONCAT(_xlfn.TEXTSPLIT($D52,".")), 'S1. USITC Imports'!$B:$B,'S1. USITC Imports'!$J:$J)*_xlfn.XLOOKUP(_xlfn.CONCAT(_xlfn.TEXTSPLIT($D52,".")), 'S1. USITC Imports'!$B:$B,'S1. USITC Imports'!G:G) -> 1123.0039 | H52: =_xlfn.XLOOKUP(_xlfn.CONCAT(_xlfn.TEXTSPLIT($D52,".")), 'S1. USITC Imports'!$B:$B,'S1. USITC Imports'!$J:$J)*_xlfn.XLOOKUP(_xlfn.CONCAT(_xlfn.TEXTSPLIT($D52,".")), 'S1. USITC Imports'!$B:$B,'S1. USITC Imports'!H:H) -> 1045.788 | I52: =_xlfn.XLOOKUP(_xlfn.CONCAT(_xlfn.TEXTSPLIT($D52,".")), 'S1. USITC Imports'!$B:$B,'S1. USITC Imports'!$J:$J)*_xlfn.XLOOKUP(_xlfn.CONCAT(_xlfn.TEXTSPLIT($D52,".")), 'S1. USITC Imports'!$B:$B,'S1. USITC Imports'!I:I) -> 918.25798
B53: (1) Source: USITC DataWeb, Imports for Consumption
B55: Domestic Exports, Sodium Hydroxide
B56: Product Name | C56: Units | D56: HTS Code | E56: 2021 | F56: 2022 | G56: 2023 | H56: 2024 | I56: 2025
B57: Sodium hydroxide (aqueous)1 | C57: kt | D57: 2815.12.0000 | E57: =_xlfn.XLOOKUP(_xlfn.CONCAT(_xlfn.TEXTSPLIT($D57,".")), 'S2. USITC Exports'!$B:$B,'S2. USITC Exports'!$J:$J)*_xlfn.XLOOKUP(_xlfn.CONCAT(_xlfn.TEXTSPLIT($D57,".")), 'S2. USITC Exports'!$B:$B,'S2. USITC Exports'!E:E) -> 5747.9576 | F57: =_xlfn.XLOOKUP(_xlfn.CONCAT(_xlfn.TEXTSPLIT($D57,".")), 'S2. USITC Exports'!$B:$B,'S2. USITC Exports'!$J:$J)*_xlfn.XLOOKUP(_xlfn.CONCAT(_xlfn.TEXTSPLIT($D57,".")), 'S2. USITC Exports'!$B:$B,'S2. USITC Exports'!F:F) -> 5654.8955 | G57: =_xlfn.XLOOKUP(_xlfn.CONCAT(_xlfn.TEXTSPLIT($D57,".")), 'S2. USITC Exports'!$B:$B,'S2. USITC Exports'!$J:$J)*_xlfn.XLOOKUP(_xlfn.CONCAT(_xlfn.TEXTSPLIT($D57,".")), 'S2. USITC Exports'!$B:$B,'S2. USITC Exports'!G:G) -> 5286.001 | H57: =_xlfn.XLOOKUP(_xlfn.CONCAT(_xlfn.TEXTSPLIT($D57,".")), 'S2. USITC Exports'!$B:$B,'S2. USITC Exports'!$J:$J)*_xlfn.XLOOKUP(_xlfn.CONCAT(_xlfn.TEXTSPLIT($D57,".")), 'S2. USITC Exports'!$B:$B,'S2. USITC Exports'!H:H) -> 5751.4521 | I57: =_xlfn.XLOOKUP(_xlfn.CONCAT(_xlfn.TEXTSPLIT($D57,".")), 'S2. USITC Exports'!$B:$B,'S2. USITC Exports'!$J:$J)*_xlfn.XLOOKUP(_xlfn.CONCAT(_xlfn.TEXTSPLIT($D57,".")), 'S2. USITC Exports'!$B:$B,'S2. USITC Exports'!I:I) -> 6472.504
B58: (1) Source: USITC DataWeb, Domestic Exports
B62: Pricing
B63: Description | C63: Units | D63: HTS Code | E63: 2021 | F63: 2022 | G63: 2023 | H63: 2024 | I63: 2025
B64: Total FAS Value, Domestic Exports1 | C64: $ | D64: 2815.12.0000 | E64: =_xlfn.XLOOKUP(_xlfn.CONCAT(_xlfn.TEXTSPLIT($D64,".")), 'S3. USITC FAS Value'!$B:$B,'S3. USITC FAS Value'!E:E) -> 1083669849 | F64: =_xlfn.XLOOKUP(_xlfn.CONCAT(_xlfn.TEXTSPLIT($D64,".")), 'S3. USITC FAS Value'!$B:$B,'S3. USITC FAS Value'!F:F) -> 2032985267 | G64: =_xlfn.XLOOKUP(_xlfn.CONCAT(_xlfn.TEXTSPLIT($D64,".")), 'S3. USITC FAS Value'!$B:$B,'S3. USITC FAS Value'!G:G) -> 1512521602 | H64: =_xlfn.XLOOKUP(_xlfn.CONCAT(_xlfn.TEXTSPLIT($D64,".")), 'S3. USITC FAS Value'!$B:$B,'S3. USITC FAS Value'!H:H) -> 1182270207 | I64: =_xlfn.XLOOKUP(_xlfn.CONCAT(_xlfn.TEXTSPLIT($D64,".")), 'S3. USITC FAS Value'!$B:$B,'S3. USITC FAS Value'!I:I) -> 1403180024
B65: Total Domestic Exports2 | C65: t | D65: 2815.12.0000 | E65: =E57*1000 -> 5747957.6 | F65: =F57*1000 -> 5654895.5 | G65: =G57*1000 -> 5286001 | H65: =H57*1000 -> 5751452.1 | I65: =I57*1000 -> 6472504
B66: Price, average unit value, domestic exports FAS | C66: $/t | D66: – | E66: =E64/E65 -> 188.53129 | F66: =F64/F65 -> 359.5089 | G66: =G64/G65 -> 286.13721 | H66: =H64/H65 -> 205.5603 | I66: =I64/I65 -> 216.79091
B67: (1) Source: USITC DataWeb, Domestic Exports
B68: (2) See "Imports and Exports" section above

Sheet B18. NH3
B2: Ammonia
B3: (quantities are representative of quantified form listed below, unless otherwise specified)
B5: Byproduct Information
B6: Chemical Formula of Quantified Form: | C6: NH3
B7: USGS Mineral Commodity Summary Page: | C7: Ammonia
B8: Demand Data Market Specificity: | C8: Byproduct
B9: Demand Data Resolution: | C9: Domestic
B13: Major End-Use Markets1,2
B14: Assigned End-Use Category | C14: End-Use | D14: Demand (kt) | E14: % of Demand | G14: USGS reports that 88% of domestic ammonia production is for fertilizer use, which inludes both direct application and use in fertilizer manufacturing. Because these end-uses involve different points of consumption (field vs factory), we split this end-use into "Nitrogenous Fertilizer Application" and "Nitrogenous Fertilizer Manufacturing" based on historical nitrogen fertilizer consumption data.
B15: Nitrogenous Fertilizer Application | C15: Anhydrous ammonia fertilizer | D15: – | E15: 0.21
B16: Nitrogenous Fertilizer Manufacturing | C16: Other fertilizer | D16: – | E16: 0.67
B17: Miscellaneous Chemical Manufacturing | C17: Miscellaneous chemical compounds | D17: – | E17: 0.12
B18: (1) Source: USGS Mineral Commodity Summaries 2026, Ammonia
B19: (2) 88% general fertilizer end use split between application and manufacturing based on fraction of 2023 US nitrogen fertilizer consumption attributable to anhydrous ammonia (24%) (USGS Minerals Yearbook 2023, Ammonia (Table 5))
B23: Domestic Demand
B24: Calculation Schema: | C24: Direct Report
B25: Description | C25: Units | D25: 2021 | E25: 2022 | F25: 2023 | G25: 2024 | H25: 2025
B26: Consumption, apparent1 | C26: kt N content | D26: 14600 | E26: 14800 | F26: 14700 | G26: 14400 | H26: 15000
B27: Ammonia-to-nitrogen molecular weight ratio2 | C27: kt NH3/kt N | D27: =17.0305/14.007 -> 1.2158564 | E27: =17.0305/14.007 -> 1.2158564 | F27: =17.0305/14.007 -> 1.2158564 | G27: =17.0305/14.007 -> 1.2158564 | H27: =17.0305/14.007 -> 1.2158564
B28: Consumption, apparent | C28: kt | D28: =D26*D27 -> 17751.503 | E28: =E26*E27 -> 17994.674 | F28: =F26*F27 -> 17873.088 | G28: =G26*G27 -> 17508.332 | H28: =H26*H27 -> 18237.845
B29: (1) Source: USGS Mineral Commodity Summaries 2026, Ammonia
B30: (2) Molecular weight ratio between ammonia (NH3) and nitrogen (N). Molecular weights obtained using Python molmass package.
B34: Pricing
B35: Description | C35: Units | D35: 2021 | E35: 2022 | F35: 2023 | G35: 2024 | H35: 2025
B36: Price, average, f.o.b. Gulf Coast1 | C36: $/short ton N | D36: 578 | E36: 1070 | F36: 470 | G36: 440 | H36: 450
B37: Price, average, f.o.b. Gulf Coast2 | C37: $/t | D37: =D36*1.10231/D27 -> 524.02175 | E37: =E36*1.10231/E27 -> 970.07487 | F37: =F36*1.10231/F27 -> 426.10765 | G37: =G36*1.10231/G27 -> 398.90929 | H37: =H36*1.10231/H27 -> 407.97541
B38: (1) Source: USGS Mineral Commodity Summaries 2026, Ammonia
B39: (2) Converted from $/short ton of N to $/t NH3

Sheet B19. P2O5
B2: Phosphate
B3: (quantities are representative of quantified form listed below, unless otherwise specified)
B5: Byproduct Information
B6: Chemical Formula of Quantified Form: | C6: P2O5
B7: USGS Mineral Commodity Summary Page: | C7: Phosphate Rock
B8: Demand Data Market Specificity: | C8: Byproduct
B9: Demand Data Resolution: | C9: Domestic
B13: Major End-Use Markets1
B14: Assigned End-Use Category | C14: End-Use | D14: Demand (kt) | E14: % of Demand
B15: Phosphoric Acid Manufacturing | C15: Wet-process phosphoric acid and superphosphoric acid manufacturing | D15: – | E15: 0.95
B16: Other | C16: Other | D16: – | E16: 0.05
B17: (1) Source: USGS Mineral Commodity Summaries 2026, Phosphate Rock
B21: Domestic Demand
B22: Calculation Schema: | C22: Indirect Report
B23: Description | C23: Units | D23: 2021 | E23: 2022 | F23: 2023 | G23: 2024 | H23: 2025 | J23: USGS reports consumption of phosphate rock in units of gross weight. To get consumption in unis of P2O5 content, we multiply these quantities by the ratio between P2O5 content and gross weight phosphate rock from historical data (28%), which shows strong stability over time.
B24: Consumption, apparent, marketable phosphate rock1 | C24: kt phosphate rock | D24: 24400 | E24: 22300 | F24: 22600 | G24: 22500 | H24: 21000
B25: Assumed P2O5 content of marketable phosphate rock2 | C25: kt P2O5 / kt phosphate rock | D25: 0.28 | E25: 0.28 | F25: 0.28 | G25: 0.28 | H25: 0.28
B26: Consumption, apparent | C26: kt | D26: =D24*D25 -> 6832 | E26: =E24*E25 -> 6244 | F26: =F24*F25 -> 6328 | G26: =G24*G25 -> 6300 | H26: =H24*H25 -> 5880
B27: (1) Source: USGS Mineral Commodity Summaries 2026, Phosphate Rock
B28: (2) Based on ratio between P2O5 content and gross weight quantities of phosphate rock sold or used by producers (USGS Minerals Yearbook 2023, Phosphate Rock (Table 1))
B32: Pricing
B33: Description | C33: Units | D33: 2021 | E33: 2022 | F33: 2023 | G33: 2024 | H33: 2025
B34: Price, average value, f.o.b. mine1 | C34: $/t phosphate rock | D34: 83 | E34: 99 | F34: 101 | G34: 96 | H34: 100
B35: Price, average value, f.o.b. mine2 | C35: $/t | D35: =D34/D25 -> 296.42857 | E35: =E34/E25 -> 353.57143 | F35: =F34/F25 -> 360.71429 | G35: =G34/G25 -> 342.85714 | H35: =H34/H25 -> 357.14286
B36: (1) Source: USGS Mineral Commodity Summaries 2026, Phosphate Rock
B37: (2) Converted from $/t phosphate rock to $/t P2O5 content

Sheet B20. SrSO4
B2: Strotium Sulfate
B3: (quantities are representative of quantified form listed below, unless otherwise specified)
B5: Byproduct Information
B6: Chemical Formula of Quantified Form: | C6: SrSO4
B7: USGS Mineral Commodity Summary Page: | C7: Strontium
B8: Demand Data Market Specificity: | C8: Byproduct
B9: Demand Data Resolution: | C9: Domestic
B13: Major End-Use Markets1
B14: Assigned End-Use Category | C14: End-Use | D14: Demand (kt) | E14: % of Demand | G14: Lacking appropriate disaggregation proxies for manufcturing of ceramic ferrite magnets and pyrotechnics and signals, we collapse these end-uses into the "Miscellaneous Manufacturing" category.
B15: Oil and Gas Drilling | C15: Drilling fluids | D15: – | E15: 0.65
B16: Miscellaneous Manufacturing | C16: Ceramic ferrite magnets | D16: – | E16: 0.14
B17: Miscellaneous Manufacturing | C17: Pyrotechnics and signals | D17: – | E17: 0.14
B18: Other | C18: Other | D18: – | E18: 0.07
B19: (1) Source: USGS Mineral Commodity Summaries 2026, Strontium
B23: Domestic Demand
B24: Calculation Schema: | C24: Indirect Report
B25: Description | C25: Units | D25: 2021 | E25: 2022 | F25: 2023 | G25: 2024 | H25: 2025
B26: Consumption, apparent, celestite1 | C26: t Sr | D26: 106 | E26: 9160 | F26: 2060 | G26: 29 | H26: 8100
B27: Molecular weight ratio of celestite to strontium2 | C27: kt SrSO4 / kt Sr | D27: =183.68242/87.62 -> 2.0963527 | E27: =183.68242/87.62 -> 2.0963527 | F27: =183.68242/87.62 -> 2.0963527 | G27: =183.68242/87.62 -> 2.0963527 | H27: =183.68242/87.62 -> 2.0963527
B28: Consumption, apparent | C28: kt | D28: =D26*D27/1000 -> 0.22221338 | E28: =E26*E27/1000 -> 19.20259 | F28: =F26*F27/1000 -> 4.3184865 | G28: =G26*G27/1000 -> 0.060794227 | H28: =H26*H27/1000 -> 16.980457
B29: (1) Source: USGS Mineral Commodity Summaries 2026, Strontium
B30: (2) Molecular weight ratio between celestite (SrSO44) and strontium (Sr). Molecular weights obtained using Python molmass package.
B34: Pricing
B35: Description | C35: Units | D35: 2021 | E35: 2022 | F35: 2023 | G35: 2024 | H35: 2025
B36: Price, average unit value of celestite imports at port of exportation1 | C36: $/t | D36: 210 | E36: 143 | F36: 82 | G36: 807 | H36: 160
B37: (1) Source: USGS Mineral Commodity Summaries 2026, Strontium

Sheet S1. USITC Imports
B2: USITC Imports for Consumption
B3: All data retrieved from USITC DataWeb
B5: HTS Number | C5: Description | D5: Units | E5: 2021 | F5: 2022 | G5: 2023 | H5: 2024 | I5: 2025 | J5: Unit Conversion Factor
B6: 2810000000 | C6: OXIDES OF BORON AND BORIC ACID | D6: metric tons | E6: 54190 | F6: 48158 | G6: 37978 | H6: 42535 | I6: 52382 | J6: =IF(D6="metric tons",0.001,IF(D6="kilograms",0.000001,NA())) -> 0.001
B7: 2840110000 | C7: ANHYDROUS DISODIUM TETRABORATE (REFINED BORAX) | D7: kilograms | E7: 6019420 | F7: 5375388 | G7: 3158040 | H7: 2955172 | I7: 4371018 | J7: =IF(D7="metric tons",0.001,IF(D7="kilograms",0.000001,NA())) -> 1e-06
B8: 2840190000 | C8: DISODIUM TETRABORATE (REFINED BORAX), EXCEPT ANHYDROUS, NESOI | D8: kilograms | E8: 225925623 | F8: 162307488 | G8: 152407793 | H8: 147197241 | I8: 143311218 | J8: =IF(D8="metric tons",0.001,IF(D8="kilograms",0.000001,NA())) -> 1e-06
B9: 2511101000 | C9: NATURAL BARIUM SULFATE (BARYTES) GROUND | D9: metric tons | E9: 1202236 | F9: 1683152 | G9: 1413413 | H9: 1440243 | I9: 1465785 | J9: =IF(D9="metric tons",0.001,IF(D9="kilograms",0.000001,NA())) -> 0.001
B10: 2806100000 | C10: HYDROGEN CHLORIDE (HYDROCHLORIC ACID) | D10: metric tons | E10: 328677 | F10: 317119 | G10: 350072 | H10: 320388 | I10: 270188 | J10: =IF(D10="metric tons",0.001,IF(D10="kilograms",0.000001,NA())) -> 0.001
B11: 2811110000 | C11: HYDROGEN FLUORIDE (HYDROFLUORIC ACID) | D11: kilograms | E11: 103271718 | F11: 99439092 | G11: 86756697 | H11: 68949172 | I11: 76050680 | J11: =IF(D11="metric tons",0.001,IF(D11="kilograms",0.000001,NA())) -> 1e-06
B12: 2815120000 | C12: SODIUM HYDROXIDE IN AQUEOUS SOLUTION (SODA LYE OR LIQUID SODA) | D12: kilograms | E12: 1144775985 | F12: 1245407748 | G12: 1123003939 | H12: 1045788013 | I12: 918257985 | J12: =IF(D12="metric tons",0.001,IF(D12="kilograms",0.000001,NA())) -> 1e-06
B13: 2530201000 | C13: KIESERITE | D13: kilograms | E13: 2727343 | F13: 7481285 | G13: 661359 | H13: 8841482 | I13: 2130753 | J13: =IF(D13="metric tons",0.001,IF(D13="kilograms",0.000001,NA())) -> 1e-06
B14: 2530202000 | C14: EPSOM SALTS | D14: kilograms | E14: 913839 | F14: 611880 | G14: 825575 | H14: 873507 | I14: 2324685 | J14: =IF(D14="metric tons",0.001,IF(D14="kilograms",0.000001,NA())) -> 1e-06
B15: 2816100000 | C15: MAGNESIUM HYDROXIDE AND MAGNESIUM PEROXIDE | D15: kilograms | E15: 12765202 | F15: 13075305 | G15: 9980971 | H15: 11150462 | I15: 13101851 | J15: =IF(D15="metric tons",0.001,IF(D15="kilograms",0.000001,NA())) -> 1e-06
B16: 2827310000 | C16: MAGNESIUM CHLORIDE | D16: kilograms | E16: 93962223 | F16: 57020048 | G16: 89004483 | H16: 74982349 | I16: 95049037 | J16: =IF(D16="metric tons",0.001,IF(D16="kilograms",0.000001,NA())) -> 1e-06
B17: 2833210000 | C17: MAGNESIUM SULFATE | D17: kilograms | E17: 44531212 | F17: 31059237 | G17: 26138337 | H17: 36880121 | I17: 39877143 | J17: =IF(D17="metric tons",0.001,IF(D17="kilograms",0.000001,NA())) -> 1e-06
... B19: 2836500000 | C19: CALCIUM CARBONATE | D19: kilograms | E19: 54587744 | F19: 84646120 | G19: 79856716 | H19: 85623784 | I19: 72167708 | J19: =IF(D19="metric tons",0.001,IF(D19="kilograms",0.000001,NA())) -> 1e-06
J20: =IF(D20="metric tons",0.001,IF(D20="kilograms",0.000001,NA())) -> #N/A
J21: =IF(D21="metric tons",0.001,IF(D21="kilograms",0.000001,NA())) -> #N/A
J22: =IF(D22="metric tons",0.001,IF(D22="kilograms",0.000001,NA())) -> #N/A
J23: =IF(D23="metric tons",0.001,IF(D23="kilograms",0.000001,NA())) -> #N/A
J24: =IF(D24="metric tons",0.001,IF(D24="kilograms",0.000001,NA())) -> #N/A
J25: =IF(D25="metric tons",0.001,IF(D25="kilograms",0.000001,NA())) -> #N/A
J26: =IF(D26="metric tons",0.001,IF(D26="kilograms",0.000001,NA())) -> #N/A
J27: =IF(D27="metric tons",0.001,IF(D27="kilograms",0.000001,NA())) -> #N/A
J28: =IF(D28="metric tons",0.001,IF(D28="kilograms",0.000001,NA())) -> #N/A
J29: =IF(D29="metric tons",0.001,IF(D29="kilograms",0.000001,NA())) -> #N/A
J30: =IF(D30="metric tons",0.001,IF(D30="kilograms",0.000001,NA())) -> #N/A
J31: =IF(D31="metric tons",0.001,IF(D31="kilograms",0.000001,NA())) -> #N/A
... J37: =IF(D37="metric tons",0.001,IF(D37="kilograms",0.000001,NA())) -> #N/A

Sheet S2. USITC Exports
B2: USITC Domestic Exports
B3: All data retrieved from USITC DataWeb
B5: HTS Number | C5: Description | D5: Units | E5: 2021 | F5: 2022 | G5: 2023 | H5: 2024 | I5: 2025 | J5: Unit Conversion Factor
B6: 2810000000 | C6: OXIDES OF BORON AND BORIC ACID | D6: metric tons | E6: 279788 | F6: 239121 | G6: 253119 | H6: 246044 | I6: 247883 | J6: =IF(D6="metric tons",0.001,IF(D6="kilograms",0.000001,NA())) -> 0.001
B7: 2840110000 | C7: ANHYDROUS DISODIUM TETRABORATE (REFINED BORAX) | D7: kilograms | E7: 47223602 | F7: 41768599 | G7: 58258883 | H7: 57467468 | I7: 39605678 | J7: =IF(D7="metric tons",0.001,IF(D7="kilograms",0.000001,NA())) -> 1e-06
B8: 2840190000 | C8: DISODIUM TETRABORATE (REFINED BORAX), EXCEPT ANHYDROUS, NESOI | D8: kilograms | E8: 559536189 | F8: 609486118 | G8: 545687104 | H8: 597382176 | I8: 514047508 | J8: =IF(D8="metric tons",0.001,IF(D8="kilograms",0.000001,NA())) -> 1e-06
B9: 2511100000 | C9: NATURAL BARIUM SULFATE (BARYTES) | D9: metric tons | E9: 53050 | F9: 77075 | G9: 61975 | H9: 53134 | I9: 53879 | J9: =IF(D9="metric tons",0.001,IF(D9="kilograms",0.000001,NA())) -> 0.001
B10: 2833270000 | C10: BARIUM SULFATE | D10: kilograms | E10: 8527952 | F10: 9425848 | G10: 12731951 | H10: 11895602 | I10: 10059504 | J10: =IF(D10="metric tons",0.001,IF(D10="kilograms",0.000001,NA())) -> 1e-06
B11: 2806100000 | C11: HYDROGEN CHLORIDE (HYDROCHLORIC ACID) | D11: metric tons | E11: 63097 | F11: 84293 | G11: 125409 | H11: 120031 | I11: 115645 | J11: =IF(D11="metric tons",0.001,IF(D11="kilograms",0.000001,NA())) -> 0.001
B12: 2811110000 | C12: HYDROGEN FLUORIDE (HYDROFLUORIC ACID) | D12: kilograms | E12: 16608258 | F12: 9888800 | G12: 10460104 | H12: 13948911 | I12: 12203279 | J12: =IF(D12="metric tons",0.001,IF(D12="kilograms",0.000001,NA())) -> 1e-06
B13: 2815120000 | C13: SODIUM HYDROXIDE IN AQUEOUS SOLUTION (SODA LYE OR LIQUID SODA) | D13: kilograms | E13: 5747957580 | F13: 5654895457 | G13: 5286001016 | H13: 5751452124 | I13: 6472503966 | J13: =IF(D13="metric tons",0.001,IF(D13="kilograms",0.000001,NA())) -> 1e-06
B14: 2816100000 | C14: MAGNESIUM HYDROXIDE AND MAGNESIUM PEROXIDE | D14: kilograms | E14: 17710210 | F14: 16046904 | G14: 14518258 | H14: 17811352 | I14: 17483064 | J14: =IF(D14="metric tons",0.001,IF(D14="kilograms",0.000001,NA())) -> 1e-06
B15: 2827310000 | C15: MAGNESIUM CHLORIDE | D15: kilograms | E15: 13385620 | F15: 16126195 | G15: 33302317 | H15: 56104715 | I15: 55920627 | J15: =IF(D15="metric tons",0.001,IF(D15="kilograms",0.000001,NA())) -> 1e-06
B16: 2833210000 | C16: MAGNESIUM SULFATE | D16: kilograms | E16: 14203936 | F16: 15135331 | G16: 13639578 | H16: 12844323 | I16: 10581756 | J16: =IF(D16="metric tons",0.001,IF(D16="kilograms",0.000001,NA())) -> 1e-06
B17: 2530200000 | C17: KIESERITE, EPSOM SALTS (NATURAL MAGNESIUM SULFATE) | D17: kilograms | E17: 168390 | F17: 208056 | G17: 368095 | H17: 152633 | I17: 95707 | J17: =IF(D17="metric tons",0.001,IF(D17="kilograms",0.000001,NA())) -> 1e-06
... B20: 2501000000 | C20: SALT INC TABLE & DENATURED & PURE SODIUM CHLORIDE, WH/NOT IN AQUEOUS SOLUTION OR CONTAINING ADDED ANTI-CRACKING OR FREE-FLOWING AGENTS; SEA WATER | D20: metric tons | E20: 1038492 | F20: 927726 | G20: 2321754 | H20: 2177298 | I20: 1832586 | J20: =IF(D20="metric tons",0.001,IF(D20="kilograms",0.000001,NA())) -> 0.001
J21: =IF(D21="metric tons",0.001,IF(D21="kilograms",0.000001,NA())) -> #N/A
J22: =IF(D22="metric tons",0.001,IF(D22="kilograms",0.000001,NA())) -> #N/A
J23: =IF(D23="metric tons",0.001,IF(D23="kilograms",0.000001,NA())) -> #N/A
J24: =IF(D24="metric tons",0.001,IF(D24="kilograms",0.000001,NA())) -> #N/A
J25: =IF(D25="metric tons",0.001,IF(D25="kilograms",0.000001,NA())) -> #N/A
J26: =IF(D26="metric tons",0.001,IF(D26="kilograms",0.000001,NA())) -> #N/A
J27: =IF(D27="metric tons",0.001,IF(D27="kilograms",0.000001,NA())) -> #N/A
J28: =IF(D28="metric tons",0.001,IF(D28="kilograms",0.000001,NA())) -> #N/A
J29: =IF(D29="metric tons",0.001,IF(D29="kilograms",0.000001,NA())) -> #N/A
J30: =IF(D30="metric tons",0.001,IF(D30="kilograms",0.000001,NA())) -> #N/A
J31: =IF(D31="metric tons",0.001,IF(D31="kilograms",0.000001,NA())) -> #N/A
J32: =IF(D32="metric tons",0.001,IF(D32="kilograms",0.000001,NA())) -> #N/A
... J34: =IF(D34="metric tons",0.001,IF(D34="kilograms",0.000001,NA())) -> #N/A

Sheet S3. USITC FAS Value
B2: USITC FAS Value
B3: All data retrieved from USITC DataWeb
B5: HTS Number | C5: Description | D5: Units | E5: 2021 | F5: 2022 | G5: 2023 | H5: 2024 | I5: 2025
B6: 2806100000 | C6: HYDROGEN CHLORIDE (HYDROCHLORIC ACID) | D6: Value for: metric tons | E6: 20458388 | F6: 22061173 | G6: 26783655 | H6: 25480468 | I6: 24442975
B7: 2806100000 | C7: HYDROGEN CHLORIDE (HYDROCHLORIC ACID) | D7: Value for: metric tons | E7: 20458388 | F7: 22061173 | G7: 26783655 | H7: 25480468 | I7: 24442975
B8: 2811110000 | C8: HYDROGEN FLUORIDE (HYDROFLUORIC ACID) | D8: Value for: kilograms | E8: 29011838 | F8: 23403531 | G8: 23922471 | H8: 32122156 | I8: 33293771
B9: 2815120000 | C9: SODIUM HYDROXIDE IN AQUEOUS SOLUTION (SODA LYE OR LIQUID SODA) | D9: Value for: kilograms | E9: 1083669849 | F9: 2032985267 | G9: 1512521602 | H9: 1182270207 | I9: 1403180024
B10: 2816100000 | C10: MAGNESIUM HYDROXIDE AND MAGNESIUM PEROXIDE | D10: Value for: kilograms | E10: 16706683 | F10: 18313175 | G10: 15579453 | H10: 17360829 | I10: 17112550
B11: 2827310000 | C11: MAGNESIUM CHLORIDE | D11: Value for: kilograms | E11: 9556447 | F11: 9983457 | G11: 13755439 | H11: 14020632 | I11: 12807541
B12: 2833210000 | C12: MAGNESIUM SULFATE | D12: Value for: kilograms | E12: 9553018 | F12: 10044505 | G12: 8952369 | H12: 9018796 | I12: 8055095
B13: 2530200000 | C13: KIESERITE, EPSOM SALTS (NATURAL MAGNESIUM SULFATE) | D13: Value for: kilograms | E13: 229431 | F13: 280389 | G13: 786371 | H13: 495981 | I13: 236282
B14: 2517100020 | C14: LIMESTONE, EXCEPT PEBBLES AND GRAVEL | D14: Value for: metric tons | E14: 9147202 | F14: 10897391 | G14: 8767076 | H14: 8754022 | I14: 9162709
B15: 2836500000 | C15: CALCIUM CARBONATE | D15: Value for: kilograms | E15: 37879357 | F15: 42682563 | G15: 40501972 | H15: 40731195 | I15: 42713436
B16: 2827310000 | C16: MAGNESIUM CHLORIDE | D16: Value for: kilograms | E16: 9556447 | F16: 9983457 | G16: 13755439 | H16: 14020632 | I16: 12807541
B17: 2501000000 | C17: SALT INC TABLE & DENATURED & PURE SODIUM CHLORIDE, WH/NOT IN AQUEOUS SOLUTION OR CONTAINING ADDED ANTI-CRACKING OR FREE-FLOWING AGENTS; SEA WATER | D17: Value for: metric tons | E17: 206922349 | F17: 206013111 | G17: 258942576 | H17: 259216789 | I17: 233434303

Sheet X1. Markets
A1: byproduct | B1: end_use_category | C1: end_use | D1: demand_kt | E1: pct_demand
A2: B | B2: {='B1. B'!B15:E16} -> Glass Manufacturing | C2: Glass and ceramics | D2: – | E2: 0.65
A3: B | B3: Miscellaneous Manufacturing | C3: Abrasives, cleaning products, insecticides, insulation, semiconductor production | D3: – | E3: 0.35
A4: BaSO4 | B4: {='B2. BaSO4'!B15:E16} -> Oil and Gas Drilling | C4: Weighting agent in oil and gas drilling fluids | D4: – | E4: 0.9
A5: BaSO4 | B5: Miscellaneous Manufacturing | C5: Filler, extender, weighting agent; metal casting; concrete aggregate; X-ray contrast | D5: – | E5: 0.1
A6: Br | B6: {='B3. Br'!B15:E19} -> Miscellaneous Chemical Manufacturing | C6: Flame retardant | D6: 483000 | E6: 0.5894557
A7: Br | B7: Oil and Gas Drilling | C7: Drilling fluids | D7: 103500 | E7: 0.12631194
A8: Br | B8: Organic Chemical Manufacturing | C8: Organic synthesis | D8: 86300 | E8: 0.10532097
A9: Br | B9: Pharmaceutical Manufacturing | C9: Pharmaceuticals | D9: 77600 | E9: 0.094703442
A10: Br | B10: Industrial Water Treatment | C10: Water treatment | D10: 69000 | E10: 0.084207957
A11: CaCO3 | B11: {='B4. CaCO3'!B15:E19} -> Other | C11: Agricultural uses | D11: 13004 | E11: 0.018516251
A12: CaCO3 | B12: Cement Manufacturing | C12: Cement Manufacture | D12: 110000 | E12: 0.15662778
A13: CaCO3 | B13: Lime Manufacturing | C13: Lime Manufacture | D13: 32500 | E13: 0.046276388
A14: CaCO3 | B14: Other | C14: Sulfur oxide removal | D14: 4120 | E14: 0.0058664221
A15: CaCO3 | B15: Other | C15: Miscellaneous and unspecified uses | D15: 542678 | E15: 0.77271316
A16: CaF2 | B16: {='B5. CaF2'!B15:E15} -> Hydrofluoric Acid Manufacturing | C16: HF production | D16: – | E16: 1
A17: Ca(OH)2 | B17: {='B6. Ca(OH)2'!B15:E23} -> Miscellaneous Chemical Manufacturing | C17: Chemical and Industrial | D17: 615 | E17: 0.2494929
A18: Ca(OH)2 | B18: Miscellaneous Construction | C18: Asphalt, building uses, soil stabilization, etc. | D18: 878 | E18: 0.35618661
A19: Ca(OH)2 | B19: Flue Gas Desulfurization | C19: Flue gas treatment | D19: 446 | E19: 0.18093306
A20: Ca(OH)2 | B20: Wastewater Treatment | C20: Sludge treatment | D20: 128 | E20: 0.051926978
A21: Ca(OH)2 | B21: Other | C21: Acid-mine drainage | D21: 47 | E21: 0.019066937
A22: Ca(OH)2 | B22: Drinking Water Treatment | C22: Drinking water treatment | D22: 137 | E22: 0.055578093
A23: Ca(OH)2 | B23: Other | C23: Wastewater treatment | D23: 108 | E23: 0.043813387
A24: Ca(OH)2 | B24: Other | C24: Other environmental | D24: 43 | E24: 0.017444219
A25: Ca(OH)2 | B25: Other | C25: Metallurgy | D25: 63 | E25: 0.025557809
A26: CaSO4 | B26: {='B7. CaSO4'!B15:E17} -> Cement Manufacturing | C26: Portland and masonry cement | D26: 4400 | E26: 0.11859838
A27: CaSO4 | B27: Miscellaneous Fertilizer Application | C27: Agriculture and other | D27: 14400 | E27: 0.38814016
A28: CaSO4 | B28: Gypsum-Based Product Manufacturing | C28: Plaster and prefabricated gypsum products | D28: 18300 | E28: 0.49326146
A29: HCl | B29: {='B8. HCl'!B15:E18} -> Oil and Gas Well Acidification | C29: Oil and gas well acidification | D29: – | E29: 0.3
A30: HCl | B30: Steel Pickling | C30: Steel pickling | D30: – | E30: 0.19
A31: HCl | B31: Miscellaneous Manufacturing | C31: Food processing | D31: – | E31: 0.19
A32: HCl | B32: Other | C32: Other | D32: – | E32: 0.32
A33: HF | B33: {='B9. HF'!B15:E20} -> Organic Chemical Manufacturing | C33: Fluorocarbon | D33: – | E33: 0.56
A34: HF | B34: Organic Chemical Manufacturing | C34: Fluorinated derivatives | D34: – | E34: 0.18333333
A35: HF | B35: Steel Pickling | C35: Metal pickling | D35: – | E35: 0.11388889
A36: HF | B36: Semiconductor Manufacturing | C36: Glass etching | D36: – | E36: 0.06
A37: HF | B37: Other | C37: Oil refining | D37: – | E37: 0.04
A38: HF | B38: Other | C38: Others | D38: – | E38: 0.047222222
A39: K2O | B39: {='B10. K2O'!B15:E16} -> Potash Fertilizer Application | C39: Fertilizer industry | D39: – | E39: 0.85
A40: K2O | B40: Miscellaneous Chemical Manufacturing | C40: Chemical and industrial applications | D40: – | E40: 0.15
A41: Li | B41: {='B11. Li'!B15:E21} -> Lithium Battery Manufacturing | C41: Batteries | D41: – | E41: 0.88
A42: Li | B42: Other | C42: Ceramics and glass | D42: – | E42: 0.04
A43: Li | B43: Other | C43: Lubricating greases | D43: – | E43: 0.02
A44: Li | B44: Other | C44: Air treatment | D44: – | E44: 0.01
A45: Li | B45: Other | C45: Continuous casting mold flux powders | D45: – | E45: 0.01
A46: Li | B46: Other | C46: Medical | D46: – | E46: 0.01
A47: Li | B47: Other | C47: Other | D47: – | E47: 0.03
A48: MgCl2 | B48: {='B12. MgCl2'!B15:E15} -> Deicing and Dust Control | C48: Deicing and dust control | D48: – | E48: 1
A49: Mg(OH)2 | B49: {='B13. Mg(OH)2'!B15:E17} -> Wastewater Treatment | C49: Water treatment | D49: – | E49: 0.8
A50: Mg(OH)2 | B50: Miscellaneous Chemical Manufacturing | C50: Chemical intermediates | D50: – | E50: 0.11
A51: Mg(OH)2 | B51: Other | C51: Other | D51: – | E51: 0.09
A52: MgSO4 | B52: {='B14. MgSO4'!B15:E19} -> Cosmetics and Personal Care Product Manufacturing | C52: Cosmetics and personal care | D52: – | E52: 0.48
A53: MgSO4 | B53: Miscellaneous Chemical Manufacturing | C53: Chemical intermediates | D53: – | E53: 0.22
A54: MgSO4 | B54: Pulp and Paper Manufacturing | C54: Pulp and paper | D54: – | E54: 0.12
A55: MgSO4 | B55: Miscellaneous Fertilizer Application | C55: Fertilizer | D55: – | E55: 0.1
A56: MgSO4 | B56: Other | C56: Other | D56: – | E56: 0.08
A57: NaCl | B57: {='B15. NaCl'!B15:E17} -> Miscellaneous Chemical Manufacturing | C57: Chemical industry | D57: 0 | E57: 0.42
A58: NaCl | B58: Deicing and Dust Control | C58: Highway deicing | D58: 0 | E58: 0.37
A59: NaCl | B59: Other | C59: Other applications | D59: 0 | E59: 0.21
A60: Na2CO3 | B60: {='B16. Na2CO3'!B15:E22} -> Glass Manufacturing | C60: Glass | D60: – | E60: 0.45
A61: Na2CO3 | B61: Miscellaneous Chemical Manufacturing | C61: Chemicals | D61: – | E61: 0.28
A62: Na2CO3 | B62: Other | C62: Miscellaneous uses | D62: – | E62: 0.09
A63: Na2CO3 | B63: Other | C63: Distributors | D63: – | E63: 0.07
A64: Na2CO3 | B64: Miscellaneous Chemical Manufacturing | C64: Soaps and detergents | D64: – | E64: 0.05
A65: Na2CO3 | B65: Other | C65: Flue gas desulfurization | D65: – | E65: 0.04
A66: Na2CO3 | B66: Other | C66: Pulp and paper | D66: – | E66: 0.01
A67: Na2CO3 | B67: Other | C67: Water treatment | D67: – | E67: 0.01
A68: NaOH | B68: {='B17. NaOH'!B15:E19} -> Organic Chemical Manufacturing | C68: Organic chemical synthesis | D68: 0 | E68: 0.23
A69: NaOH | B69: Pulp and Paper Manufacturing | C69: Pulp and paper manufacturing | D69: 0 | E69: 0.22
A70: NaOH | B70: Miscellaneous Chemical Manufacturing | C70: Inorganic chemical production | D70: 0 | E70: 0.22
A71: NaOH | B71: Other | C71: Special applications | D71: 0 | E71: 0.3
A72: NaOH | B72: Other | C72: Water treatment | D72: 0 | E72: 0.03
A73: NH3 | B73: {='B18. NH3'!B15:E17} -> Nitrogenous Fertilizer Application | C73: Anhydrous ammonia fertilizer | D73: – | E73: 0.21
A74: NH3 | B74: Nitrogenous Fertilizer Manufacturing | C74: Other fertilizer | D74: – | E74: 0.67
A75: NH3 | B75: Miscellaneous Chemical Manufacturing | C75: Miscellaneous chemical compounds | D75: – | E75: 0.12
A76: P2O5 | B76: {='B19. P2O5'!B15:E16} -> Phosphoric Acid Manufacturing | C76: Wet-process phosphoric acid and superphosphoric acid manufacturing | D76: – | E76: 0.95
A77: P2O5 | B77: Other | C77: Other | D77: – | E77: 0.05
A78: SrSO4 | B78: {='B20. SrSO4'!B15:E18} -> Oil and Gas Drilling | C78: Drilling fluids | D78: – | E78: 0.65
A79: SrSO4 | B79: Miscellaneous Manufacturing | C79: Ceramic ferrite magnets | D79: – | E79: 0.14
A80: SrSO4 | B80: Miscellaneous Manufacturing | C80: Pyrotechnics and signals | D80: – | E80: 0.14
A81: SrSO4 | B81: Other | C81: Other | D81: – | E81: 0.07

Sheet Sheet1
A1: {=_xlfn.UNIQUE('X1. Markets'!C:C)} -> end_use | B1: =_xlfn.XLOOKUP(A1,'X1. Markets'!C:C,'X1. Markets'!B:B) -> end_use_category
A2: Glass and ceramics | B2: =_xlfn.XLOOKUP(A2,'X1. Markets'!C:C,'X1. Markets'!B:B) -> Glass Manufacturing
A3: Abrasives, cleaning products, insecticides, insulation, semiconductor production | B3: =_xlfn.XLOOKUP(A3,'X1. Markets'!C:C,'X1. Markets'!B:B) -> Miscellaneous Manufacturing
A4: Weighting agent in oil and gas drilling fluids | B4: =_xlfn.XLOOKUP(A4,'X1. Markets'!C:C,'X1. Markets'!B:B) -> Oil and Gas Drilling
A5: Filler, extender, weighting agent; metal casting; concrete aggregate; X-ray contrast | B5: =_xlfn.XLOOKUP(A5,'X1. Markets'!C:C,'X1. Markets'!B:B) -> Miscellaneous Manufacturing
A6: Flame retardant | B6: =_xlfn.XLOOKUP(A6,'X1. Markets'!C:C,'X1. Markets'!B:B) -> Miscellaneous Chemical Manufacturing
A7: Drilling fluids | B7: =_xlfn.XLOOKUP(A7,'X1. Markets'!C:C,'X1. Markets'!B:B) -> Oil and Gas Drilling
A8: Organic synthesis | B8: =_xlfn.XLOOKUP(A8,'X1. Markets'!C:C,'X1. Markets'!B:B) -> Organic Chemical Manufacturing
A9: Pharmaceuticals | B9: =_xlfn.XLOOKUP(A9,'X1. Markets'!C:C,'X1. Markets'!B:B) -> Pharmaceutical Manufacturing
A10: Water treatment | B10: =_xlfn.XLOOKUP(A10,'X1. Markets'!C:C,'X1. Markets'!B:B) -> Industrial Water Treatment
A11: Agricultural uses | B11: =_xlfn.XLOOKUP(A11,'X1. Markets'!C:C,'X1. Markets'!B:B) -> Other
A12: Cement Manufacture | B12: =_xlfn.XLOOKUP(A12,'X1. Markets'!C:C,'X1. Markets'!B:B) -> Cement Manufacturing
A13: Lime Manufacture | B13: =_xlfn.XLOOKUP(A13,'X1. Markets'!C:C,'X1. Markets'!B:B) -> Lime Manufacturing
... A32: Other | B32: =_xlfn.XLOOKUP(A32,'X1. Markets'!C:C,'X1. Markets'!B:B) -> Other
A33: Fluorocarbon | B33: =_xlfn.XLOOKUP(A33,'X1. Markets'!C:C,'X1. Markets'!B:B) -> Organic Chemical Manufacturing | F33: Manufacturing
A34: Fluorinated derivatives | B34: =_xlfn.XLOOKUP(A34,'X1. Markets'!C:C,'X1. Markets'!B:B) -> Organic Chemical Manufacturing | F34: Borosilicate Glass Manufacturing
A35: Metal pickling | B35: =_xlfn.XLOOKUP(A35,'X1. Markets'!C:C,'X1. Markets'!B:B) -> Steel Pickling | F35: Miscellaneous Manufacturing
A36: Glass etching | B36: =_xlfn.XLOOKUP(A36,'X1. Markets'!C:C,'X1. Markets'!B:B) -> Semiconductor Manufacturing | F36: Miscellaneous Chemical Manufacturing
A37: Oil refining | B37: =_xlfn.XLOOKUP(A37,'X1. Markets'!C:C,'X1. Markets'!B:B) -> Other | F37: Organic Chemical Manufacturing
A38: Others | B38: =_xlfn.XLOOKUP(A38,'X1. Markets'!C:C,'X1. Markets'!B:B) -> Other | F38: Pharmaceutical Manufacturing
A39: Fertilizer industry | B39: =_xlfn.XLOOKUP(A39,'X1. Markets'!C:C,'X1. Markets'!B:B) -> Potash Fertilizer Application | F39: Cement Manufacturing
A40: Chemical and industrial applications | B40: =_xlfn.XLOOKUP(A40,'X1. Markets'!C:C,'X1. Markets'!B:B) -> Miscellaneous Chemical Manufacturing | F40: Lime Manufacturing
A41: Batteries | B41: =_xlfn.XLOOKUP(A41,'X1. Markets'!C:C,'X1. Markets'!B:B) -> Lithium Battery Manufacturing | F41: Hydrofluoric Acid Manufacturing
A42: Ceramics and glass | B42: =_xlfn.XLOOKUP(A42,'X1. Markets'!C:C,'X1. Markets'!B:B) -> Other | F42: Gypsum-Based Product Manufacturing
A43: Lubricating greases | B43: =_xlfn.XLOOKUP(A43,'X1. Markets'!C:C,'X1. Markets'!B:B) -> Other | F43: Semiconductor Manufacturing
A44: Air treatment | B44: =_xlfn.XLOOKUP(A44,'X1. Markets'!C:C,'X1. Markets'!B:B) -> Other | F44: Lithium Battery Manufacturing
... A50: Pulp and paper | B50: =_xlfn.XLOOKUP(A50,'X1. Markets'!C:C,'X1. Markets'!B:B) -> Pulp and Paper Manufacturing | F50: Steel Pickling
A51: Fertilizer | B51: =_xlfn.XLOOKUP(A51,'X1. Markets'!C:C,'X1. Markets'!B:B) -> Miscellaneous Fertilizer Application
A52: Chemical industry | B52: =_xlfn.XLOOKUP(A52,'X1. Markets'!C:C,'X1. Markets'!B:B) -> Miscellaneous Chemical Manufacturing | F52: Agriculture
A53: Highway deicing | B53: =_xlfn.XLOOKUP(A53,'X1. Markets'!C:C,'X1. Markets'!B:B) -> Deicing and Dust Control | F53: Nitrogenous Fertilizer Application
A54: Other applications | B54: =_xlfn.XLOOKUP(A54,'X1. Markets'!C:C,'X1. Markets'!B:B) -> Other | F54: Potash Fertilizer Application
A55: Glass | B55: =_xlfn.XLOOKUP(A55,'X1. Markets'!C:C,'X1. Markets'!B:B) -> Glass Manufacturing | F55: Miscellaneous Fertilizer Application
A56: Chemicals | B56: =_xlfn.XLOOKUP(A56,'X1. Markets'!C:C,'X1. Markets'!B:B) -> Miscellaneous Chemical Manufacturing
A57: Miscellaneous uses | B57: =_xlfn.XLOOKUP(A57,'X1. Markets'!C:C,'X1. Markets'!B:B) -> Other | F57: Energy
A58: Distributors | B58: =_xlfn.XLOOKUP(A58,'X1. Markets'!C:C,'X1. Markets'!B:B) -> Other | F58: Oil and Gas Well Acidification
A59: Soaps and detergents | B59: =_xlfn.XLOOKUP(A59,'X1. Markets'!C:C,'X1. Markets'!B:B) -> Miscellaneous Chemical Manufacturing | F59: Oil and Gas Drilling
A60: Flue gas desulfurization | B60: =_xlfn.XLOOKUP(A60,'X1. Markets'!C:C,'X1. Markets'!B:B) -> Other | F60: Flue Gas Desulfurization
A61: Organic chemical synthesis | B61: =_xlfn.XLOOKUP(A61,'X1. Markets'!C:C,'X1. Markets'!B:B) -> Organic Chemical Manufacturing
A62: Pulp and paper manufacturing | B62: =_xlfn.XLOOKUP(A62,'X1. Markets'!C:C,'X1. Markets'!B:B) -> Pulp and Paper Manufacturing | F62: Utilities/Infrastructure
A63: Inorganic chemical production | B63: =_xlfn.XLOOKUP(A63,'X1. Markets'!C:C,'X1. Markets'!B:B) -> Miscellaneous Chemical Manufacturing | F63: Industrial Water Treatment
A64: Special applications | B64: =_xlfn.XLOOKUP(A64,'X1. Markets'!C:C,'X1. Markets'!B:B) -> Other | F64: Miscellaneous Construction
A65: Anhydrous ammonia fertilizer | B65: =_xlfn.XLOOKUP(A65,'X1. Markets'!C:C,'X1. Markets'!B:B) -> Nitrogenous Fertilizer Application | F65: Deicing and Dust Control
A66: Other fertilizer | B66: =_xlfn.XLOOKUP(A66,'X1. Markets'!C:C,'X1. Markets'!B:B) -> Nitrogenous Fertilizer Manufacturing | F66: Wastewater Treatment
A67: Miscellaneous chemical compounds | B67: =_xlfn.XLOOKUP(A67,'X1. Markets'!C:C,'X1. Markets'!B:B) -> Miscellaneous Chemical Manufacturing | F67: Drinking Water Treatment
A68: Wet-process phosphoric acid and superphosphoric acid manufacturing | B68: =_xlfn.XLOOKUP(A68,'X1. Markets'!C:C,'X1. Markets'!B:B) -> Phosphoric Acid Manufacturing
A69: Ceramic ferrite magnets | B69: =_xlfn.XLOOKUP(A69,'X1. Markets'!C:C,'X1. Markets'!B:B) -> Miscellaneous Manufacturing
A70: Pyrotechnics and signals | B70: =_xlfn.XLOOKUP(A70,'X1. Markets'!C:C,'X1. Markets'!B:B) -> Miscellaneous Manufacturing
A71: 0 | B71: =_xlfn.XLOOKUP(A71,'X1. Markets'!C:C,'X1. Markets'!B:B) -> #N/A

Sheet X2. BP x Domestic
A1: byproduct | B1: demand_2021_kt | C1: demand_2022_kt | D1: demand_2023_kt | E1: demand_2024_kt | F1: demand_2025_kt
A2: B | B2: {='B1. B'!D27:H27} -> 536.49621 | C2: 565.14661 | D2: 496.16751 | E2: 510.43195 | F2: 536.41412
A3: BaSO4 | B3: {='B2. BaSO4'!D27:H27} -> 2810.658 | C3: 3816.6512 | D3: 3598.706 | E3: 3655.2134 | F3: 3701.8465
A4: Br | B4: {='B3. Br'!D30:H30} -> 200.3 | C4: 220.1 | D4: 206.9 | E4: 219.5 | F4: 206
A5: CaF2 | B5: {='B5. CaF2'!D23:H23} -> 391 | C5: 448 | D5: 378 | E5: 372 | F5: 360
A6: Ca(OH)2 | B6: {='B6. Ca(OH)2'!D33:H33} -> 2490 | C6: 2520 | D6: 2370 | E6: 2250 | F6: 2250
A7: CaSO4 | B7: {='B7. CaSO4'!D25:H25} -> 3200 | C7: 44600 | D7: 5800 | E7: 44900 | F7: 44000
A8: HCl | B8: {='B8. HCl'!D29:H29} -> 1479.58 | C8: 1390.826 | D8: 1415.663 | E8: 1400.357 | F8: 1354.543
A9: HF | B9: {='B9. HF'!D31:H31} -> 287.04376 | C9: 319.14204 | D9: 270.01463 | E9: 245.64341 | F9: 248.34077
A10: K2O | B10: {='B10. K2O'!D24:H24} -> 6900 | C10: 5100 | D10: 5900 | E10: 6200 | F10: 5900
A11: Li | B11: {='B11. Li'!D34:H34} -> 3.08 | C11: 3.28 | D11: 2.86 | E11: 2.66 | F11: 3.6
A12: Mg(OH)2 | B12: {='B13. Mg(OH)2'!D28:H28} -> 183.05499 | C12: 194.0284 | D12: 168.46271 | E12: 193.33911 | F12: 195.61879
A13: MgSO4 | B13: {='B14. MgSO4'!D30:H30} -> 115.70007 | C13: 112.48901 | D13: 109.0776 | E13: 135.83815 | F13: 142.67512
A14: NaCl | B14: {='B15. NaCl'!D25:H25} -> 63400 | C14: 62300 | D14: 53200 | E14: 51300 | F14: 57000
A15: Na2CO3 | B15: {='B16. Na2CO3'!D30:H30} -> 4550 | C15: 4760 | D15: 4360 | E15: 4350 | F15: 4700
A16: NaOH | B16: {='B17. NaOH'!D30:H30} -> 12396.818 | C16: 12590.512 | D16: 12837.003 | E16: 12294.336 | F16: 11445.754
A17: NH3 | B17: {='B18. NH3'!D28:H28} -> 17751.503 | C17: 17994.674 | D17: 17873.088 | E17: 17508.332 | F17: 18237.845
A18: P2O5 | B18: {='B19. P2O5'!D26:H26} -> 6832 | C18: 6244 | D18: 6328 | E18: 6300 | F18: 5880
A19: SrSO4 | B19: {='B20. SrSO4'!D28:H28} -> 0.22221338 | C19: 19.20259 | D19: 4.3184865 | E19: 0.060794227 | F19: 16.980457

Sheet X3. BP-Market x State
A1: byproduct | B1: end_use_category | C1: state | D1: demand_2021_kt | E1: demand_2022_kt | F1: demand_2023_kt | G1: demand_2024_kt | H1: demand_2025_kt
A2: CaCO3 | B2: Cement Manufacturing | C2: {=_xlfn.HSTACK('B4. CaCO3'!B34:B84,'B4. CaCO3'!D34:H84)} -> Alabama | D2: 5200 | E2: 4180 | F2: 4660 | G2: W | H2: W
A3: CaCO3 | B3: Cement Manufacturing | C3: Alaska | D3: 0 | E3: 0 | F3: 0 | G3: W | H3: W
A4: CaCO3 | B4: Cement Manufacturing | C4: Arizona | D4: W | E4: 3540 | F4: W | G4: W | H4: W
A5: CaCO3 | B5: Cement Manufacturing | C5: Arkansas | D5: W | E5: W | F5: W | G5: W | H5: W
A6: CaCO3 | B6: Cement Manufacturing | C6: California | D6: 12300 | E6: 12800 | F6: 12300 | G6: W | H6: W
A7: CaCO3 | B7: Cement Manufacturing | C7: Colorado | D7: 1780 | E7: W | F7: 3140 | G7: W | H7: W
A8: CaCO3 | B8: Cement Manufacturing | C8: Connecticut | D8: 0 | E8: 0 | F8: 0 | G8: W | H8: W
A9: CaCO3 | B9: Cement Manufacturing | C9: Delaware | D9: 0 | E9: 0 | F9: 0 | G9: W | H9: W
A10: CaCO3 | B10: Cement Manufacturing | C10: Florida | D10: 8580 | E10: 7370 | F10: 5370 | G10: W | H10: W
A11: CaCO3 | B11: Cement Manufacturing | C11: Georgia | D11: 801 | E11: 617 | F11: 530 | G11: W | H11: W
A12: CaCO3 | B12: Cement Manufacturing | C12: Hawaii | D12: 0 | E12: 0 | F12: 0 | G12: W | H12: W
A13: CaCO3 | B13: Cement Manufacturing | C13: Idaho | D13: 0 | E13: 0 | F13: 0 | G13: W | H13: W
A14: CaCO3 | B14: Cement Manufacturing | C14: Illinois | D14: W | E14: W | F14: W | G14: W | H14: W
A15: CaCO3 | B15: Cement Manufacturing | C15: Indiana | D15: W | E15: 3250 | F15: 3520 | G15: W | H15: W
A16: CaCO3 | B16: Cement Manufacturing | C16: Iowa | D16: 2170 | E16: 2130 | F16: 2150 | G16: W | H16: W
A17: CaCO3 | B17: Cement Manufacturing | C17: Kansas | D17: W | E17: W | F17: W | G17: W | H17: W
A18: CaCO3 | B18: Cement Manufacturing | C18: Kentucky | D18: 2040 | E18: 2000 | F18: 1770 | G18: W | H18: W
A19: CaCO3 | B19: Cement Manufacturing | C19: Louisiana | D19: W | E19: 0 | F19: 0 | G19: W | H19: W
A20: CaCO3 | B20: Cement Manufacturing | C20: Maine | D20: 466 | E20: 466 | F20: 394 | G20: W | H20: W
A21: CaCO3 | B21: Cement Manufacturing | C21: Maryland | D21: 4010 | E21: 3910 | F21: 3660 | G21: W | H21: W
A22: CaCO3 | B22: Cement Manufacturing | C22: Massachusetts | D22: 0 | E22: 0 | F22: 0 | G22: W | H22: W
A23: CaCO3 | B23: Cement Manufacturing | C23: Michigan | D23: 4780 | E23: 5980 | F23: W | G23: W | H23: W
A24: CaCO3 | B24: Cement Manufacturing | C24: Minnesota | D24: 0 | E24: 0 | F24: 0 | G24: W | H24: W
A25: CaCO3 | B25: Cement Manufacturing | C25: Mississippi | D25: 0 | E25: 0 | F25: 0 | G25: W | H25: W
A26: CaCO3 | B26: Cement Manufacturing | C26: Missouri | D26: 12100 | E26: 12300 | F26: 11900 | G26: W | H26: W
A27: CaCO3 | B27: Cement Manufacturing | C27: Montana | D27: 781 | E27: 750 | F27: 718 | G27: W | H27: W
A28: CaCO3 | B28: Cement Manufacturing | C28: Nebraska | D28: 0 | E28: W | F28: W | G28: W | H28: W
A29: CaCO3 | B29: Cement Manufacturing | C29: Nevada | D29: W | E29: 464 | F29: 599 | G29: W | H29: W
A30: CaCO3 | B30: Cement Manufacturing | C30: New Hampshire | D30: 0 | E30: 0 | F30: 0 | G30: W | H30: W
A31: CaCO3 | B31: Cement Manufacturing | C31: New Jersey | D31: 0 | E31: 0 | F31: 0 | G31: W | H31: W
A32: CaCO3 | B32: Cement Manufacturing | C32: New Mexico | D32: 494 | E32: 514 | F32: 514 | G32: W | H32: W
A33: CaCO3 | B33: Cement Manufacturing | C33: New York | D33: 1910 | E33: 1940 | F33: 2150 | G33: W | H33: W
A34: CaCO3 | B34: Cement Manufacturing | C34: North Carolina | D34: 0 | E34: 0 | F34: 0 | G34: W | H34: W
A35: CaCO3 | B35: Cement Manufacturing | C35: North Dakota | D35: 0 | E35: 0 | F35: 0 | G35: W | H35: W
A36: CaCO3 | B36: Cement Manufacturing | C36: Ohio | D36: W | E36: 1280 | F36: 1140 | G36: W | H36: W
A37: CaCO3 | B37: Cement Manufacturing | C37: Oklahoma | D37: 2090 | E37: 1040 | F37: 1890 | G37: W | H37: W
A38: CaCO3 | B38: Cement Manufacturing | C38: Oregon | D38: 1070 | E38: 1180 | F38: W | G38: W | H38: W
A39: CaCO3 | B39: Cement Manufacturing | C39: Pennsylvania | D39: 5810 | E39: 5990 | F39: 5190 | G39: W | H39: W
A40: CaCO3 | B40: Cement Manufacturing | C40: Rhode Island | D40: 0 | E40: 0 | F40: 0 | G40: W | H40: W
A41: CaCO3 | B41: Cement Manufacturing | C41: South Carolina | D41: 2010 | E41: 2310 | F41: 2060 | G41: W | H41: W
A42: CaCO3 | B42: Cement Manufacturing | C42: South Dakota | D42: 971 | E42: 1100 | F42: W | G42: W | H42: W
A43: CaCO3 | B43: Cement Manufacturing | C43: Tennessee | D43: W | E43: W | F43: W | G43: W | H43: W
A44: CaCO3 | B44: Cement Manufacturing | C44: Texas | D44: 17400 | E44: 17700 | F44: 20300 | G44: W | H44: W
A45: CaCO3 | B45: Cement Manufacturing | C45: Utah | D45: W | E45: W | F45: W | G45: W | H45: W
A46: CaCO3 | B46: Cement Manufacturing | C46: Vermont | D46: 0 | E46: 0 | F46: 0 | G46: W | H46: W
A47: CaCO3 | B47: Cement Manufacturing | C47: Virginia | D47: 1340 | E47: 1410 | F47: 1460 | G47: W | H47: W
A48: CaCO3 | B48: Cement Manufacturing | C48: Washington | D48: W | E48: 599 | F48: 637 | G48: W | H48: W
A49: CaCO3 | B49: Cement Manufacturing | C49: West Virginia | D49: W | E49: W | F49: W | G49: W | H49: W
A50: CaCO3 | B50: Cement Manufacturing | C50: Wisconsin | D50: 0 | E50: 0 | F50: 0 | G50: W | H50: W
A51: CaCO3 | B51: Cement Manufacturing | C51: Wyoming | D51: 826 | E51: W | F51: W | G51: W | H51: W
A52: CaCO3 | B52: Cement Manufacturing | C52: Total Withheld | D52: 20800 | E52: 14400 | F52: 23500 | G52: 164459.16 | H52: 164459.16
A53: CaCO3 | B53: Lime Manufacturing | C53: {=_xlfn.HSTACK('B4. CaCO3'!B91:B141,'B4. CaCO3'!D91:H141)} -> Alabama | D53: 7920 | E53: 8190 | F53: 6360 | G53: W | H53: W
A54: CaCO3 | B54: Lime Manufacturing | C54: Alaska | D54: 0 | E54: 0 | F54: 0 | G54: W | H54: W
A55: CaCO3 | B55: Lime Manufacturing | C55: Arizona | D55: 330 | E55: 506 | F55: 1440 | G55: W | H55: W
A56: CaCO3 | B56: Lime Manufacturing | C56: Arkansas | D56: W | E56: W | F56: W | G56: W | H56: W
A57: CaCO3 | B57: Lime Manufacturing | C57: California | D57: 555 | E57: W | F57: W | G57: W | H57: W
A58: CaCO3 | B58: Lime Manufacturing | C58: Colorado | D58: 0 | E58: 0 | F58: 0 | G58: W | H58: W
A59: CaCO3 | B59: Lime Manufacturing | C59: Connecticut | D59: 0 | E59: 0 | F59: 0 | G59: W | H59: W
A60: CaCO3 | B60: Lime Manufacturing | C60: Delaware | D60: 0 | E60: 0 | F60: 0 | G60: W | H60: W
A61: CaCO3 | B61: Lime Manufacturing | C61: Florida | D61: 1890 | E61: 519 | F61: 2790 | G61: W | H61: W
A62: CaCO3 | B62: Lime Manufacturing | C62: Georgia | D62: 0 | E62: 0 | F62: 0 | G62: W | H62: W
A63: CaCO3 | B63: Lime Manufacturing | C63: Hawaii | D63: 0 | E63: 0 | F63: 0 | G63: W | H63: W
A64: CaCO3 | B64: Lime Manufacturing | C64: Idaho | D64: 0 | E64: 0 | F64: 0 | G64: W | H64: W
A65: CaCO3 | B65: Lime Manufacturing | C65: Illinois | D65: 0 | E65: 0 | F65: 0 | G65: W | H65: W
A66: CaCO3 | B66: Lime Manufacturing | C66: Indiana | D66: 0 | E66: 0 | F66: 0 | G66: W | H66: W
A67: CaCO3 | B67: Lime Manufacturing | C67: Iowa | D67: 406 | E67: W | F67: W | G67: W | H67: W
A68: CaCO3 | B68: Lime Manufacturing | C68: Kansas | D68: 0 | E68: 0 | F68: 0 | G68: W | H68: W
A69: CaCO3 | B69: Lime Manufacturing | C69: Kentucky | D69: 2210 | E69: W | F69: 6 | G69: W | H69: W
A70: CaCO3 | B70: Lime Manufacturing | C70: Louisiana | D70: 0 | E70: 0 | F70: 0 | G70: W | H70: W
A71: CaCO3 | B71: Lime Manufacturing | C71: Maine | D71: 0 | E71: 0 | F71: 0 | G71: W | H71: W
A72: CaCO3 | B72: Lime Manufacturing | C72: Maryland | D72: 0 | E72: 0 | F72: 0 | G72: W | H72: W
A73: CaCO3 | B73: Lime Manufacturing | C73: Massachusetts | D73: 212 | E73: 425 | F73: 418 | G73: W | H73: W
A74: CaCO3 | B74: Lime Manufacturing | C74: Michigan | D74: W | E74: W | F74: 0 | G74: W | H74: W
A75: CaCO3 | B75: Lime Manufacturing | C75: Minnesota | D75: 0 | E75: 0 | F75: 0 | G75: W | H75: W
A76: CaCO3 | B76: Lime Manufacturing | C76: Mississippi | D76: 0 | E76: 0 | F76: 0 | G76: W | H76: W
A77: CaCO3 | B77: Lime Manufacturing | C77: Missouri | D77: 9130 | E77: 8540 | F77: 8150 | G77: W | H77: W
A78: CaCO3 | B78: Lime Manufacturing | C78: Montana | D78: W | E78: W | F78: W | G78: W | H78: W
A79: CaCO3 | B79: Lime Manufacturing | C79: Nebraska | D79: 0 | E79: 0 | F79: 0 | G79: W | H79: W
A80: CaCO3 | B80: Lime Manufacturing | C80: Nevada | D80: W | E80: W | F80: W | G80: W | H80: W
A81: CaCO3 | B81: Lime Manufacturing | C81: New Hampshire | D81: 0 | E81: 0 | F81: 0 | G81: W | H81: W
A82: CaCO3 | B82: Lime Manufacturing | C82: New Jersey | D82: 0 | E82: 0 | F82: 0 | G82: W | H82: W
A83: CaCO3 | B83: Lime Manufacturing | C83: New Mexico | D83: 0 | E83: 0 | F83: 0 | G83: W | H83: W
A84: CaCO3 | B84: Lime Manufacturing | C84: New York | D84: W | E84: W | F84: 0 | G84: W | H84: W
A85: CaCO3 | B85: Lime Manufacturing | C85: North Carolina | D85: 0 | E85: 0 | F85: 0 | G85: W | H85: W
A86: CaCO3 | B86: Lime Manufacturing | C86: North Dakota | D86: 0 | E86: 0 | F86: 0 | G86: W | H86: W
A87: CaCO3 | B87: Lime Manufacturing | C87: Ohio | D87: W | E87: 2030 | F87: 255 | G87: W | H87: W
A88: CaCO3 | B88: Lime Manufacturing | C88: Oklahoma | D88: W | E88: 349 | F88: 395 | G88: W | H88: W
A89: CaCO3 | B89: Lime Manufacturing | C89: Oregon | D89: 0 | E89: 0 | F89: 0 | G89: W | H89: W
A90: CaCO3 | B90: Lime Manufacturing | C90: Pennsylvania | D90: 3980 | E90: 3690 | F90: W | G90: W | H90: W
A91: CaCO3 | B91: Lime Manufacturing | C91: Rhode Island | D91: 0 | E91: 0 | F91: 0 | G91: W | H91: W
A92: CaCO3 | B92: Lime Manufacturing | C92: South Carolina | D92: 0 | E92: 0 | F92: 0 | G92: W | H92: W
A93: CaCO3 | B93: Lime Manufacturing | C93: South Dakota | D93: 1060 | E93: 933 | F93: 895 | G93: W | H93: W
A94: CaCO3 | B94: Lime Manufacturing | C94: Tennessee | D94: 252 | E94: 226 | F94: 0 | G94: W | H94: W
A95: CaCO3 | B95: Lime Manufacturing | C95: Texas | D95: 2460 | E95: 4550 | F95: 3960 | G95: W | H95: W
A96: CaCO3 | B96: Lime Manufacturing | C96: Utah | D96: W | E96: W | F96: W | G96: W | H96: W
A97: CaCO3 | B97: Lime Manufacturing | C97: Vermont | D97: 0 | E97: 0 | F97: 0 | G97: W | H97: W
A98: CaCO3 | B98: Lime Manufacturing | C98: Virginia | D98: 0 | E98: 394 | F98: W | G98: W | H98: W
A99: CaCO3 | B99: Lime Manufacturing | C99: Washington | D99: 6 | E99: 8 | F99: 8 | G99: W | H99: W
A100: CaCO3 | B100: Lime Manufacturing | C100: West Virginia | D100: 0 | E100: 0 | F100: 0 | G100: W | H100: W
...

Sheet X4. Pricing
A1: byproduct | B1: price_2021_usd_t | C1: price_2022_usd_t | D1: price_2023_usd_t | E1: price_2024_usd_t | F1: price_2025_usd_t
A2: B | B2: {='B1. B'!D72:H72} -> 394 | C2: 485 | D2: 606 | E2: 574 | F2: 540
A3: BaSO4 | B3: {='B2. BaSO4'!D62:H62} -> 167 | C3: 145 | D3: 218 | E3: 210 | F3: 210
A4: Br | B4: {='B3. Br'!D68:H68} -> 2585.52 | C4: 2984.688 | D4: 2649.024 | E4: 2449.44 | F4: 2721.6
A5: CaCO3 | B5: {='B4. CaCO3'!E152:I152} -> 163.2263 | C5: 161.70155 | D5: 152.16391 | E5: 140.95973 | F5: 144.42427
A6: CaF2 | B6: {='B5. CaF2'!D30:H30} -> 322 | C6: 387 | D6: 428 | E6: 464 | F6: 470
A7: Ca(OH)2 | B7: {='B6. Ca(OH)2'!D41:H41} -> 158 | C7: 179.1 | D7: 234.6 | E7: 274.2 | F7: 280
A8: CaSO4 | B8: {='B7. CaSO4'!D32:H32} -> 42 | C8: 50 | D8: 60 | E8: 60 | F8: 62
A9: HCl | B9: {='B8. HCl'!E65:I65} -> 324.2371 | C9: 261.72011 | D9: 213.57044 | E9: 212.28239 | F9: 211.36214
A10: HF | B10: {='B9. HF'!E71:I71} -> 1746.8321 | C10: 2366.6705 | D10: 2287.0204 | E10: 2302.8433 | F10: 2728.2643
A11: K2O | B11: {='B10. K2O'!D31:H31} -> 1120 | C11: 1790 | D11: 1250 | E11: 1150 | F11: 1200
A12: Li | B12: {='B11. Li'!D44:H44} -> 62283.917 | C12: 339101.33 | D12: 207613.06 | E12: 62816.259 | F12: 47910.706
A13: MgCl2 | B13: {='B12. MgCl2'!E255:I255} -> 713.93383 | C13: 619.08324 | D13: 413.04751 | E13: 249.90114 | F13: 229.03071
A14: Mg(OH)2 | B14: {='B13. Mg(OH)2'!E64:I64} -> 943.33625 | C14: 1141.2279 | D14: 1073.0938 | E14: 974.70585 | F14: 978.80726
A15: MgSO4 | B15: {='B14. MgSO4'!E71:I71} -> 672.56132 | C15: 663.64621 | D15: 656.35234 | E15: 702.16204 | F15: 761.22479
A16: NaCl | B16: {='B15. NaCl'!E34:I34} -> 199.25271 | C16: 222.06245 | D16: 111.52886 | E16: 119.05435 | F16: 127.37973
A17: Na2CO3 | B17: {='B16. Na2CO3'!D37:H37} -> 133.37 | C17: 178.52 | D17: 211.48 | E17: 169.35 | F17: 150
A18: NaOH | B18: {='B17. NaOH'!E66:I66} -> 188.53129 | C18: 359.5089 | D18: 286.13721 | E18: 205.5603 | F18: 216.79091
A19: NH3 | B19: {='B18. NH3'!D37:H37} -> 524.02175 | C19: 970.07487 | D19: 426.10765 | E19: 398.90929 | F19: 407.97541
A20: P2O5 | B20: {='B19. P2O5'!D35:H35} -> 296.42857 | C20: 353.57143 | D20: 360.71429 | E20: 342.85714 | F20: 357.14286
A21: SrSO4 | B21: {='B20. SrSO4'!D36:H36} -> 210 | C21: 143 | D21: 82 | E21: 807 | F21: 160

Sheet PIE Template
B2: Byproduct Name
B3: (quantities are representative of quantified form listed below, unless otherwise specified)
B5: Byproduct Information
B6: Chemical Formula of Quantified Form:
B7: USGS Mineral Commodity Summary Page:
B8: Demand Data Market Specificity: | C8: Byproduct
B9: Demand Data Resolution: | C9: Domestic
B13: Major End-Use Markets1
B14: Assigned End-Use Category | C14: End-Use | D14: Demand (kt) | E14: % of Demand
B17: (1) Source:
B21: Domestic Demand
B22: Calculation Schema: | C22: Trade Balance Estimate
B23: Description | C23: Units | D23: 2021 | E23: 2022 | F23: 2023 | G23: 2024 | H23: 2025
B24: Domestic Production1 | C24: kt
B25: Imports for Consumption2 | C25: kt
B26: Domestic Exports3 | C26: kt
B27: Consumption, apparent4 | C27: kt
B28: (1) See "Domestic Production" section below
B29: (2) See "Imports and Exports" section below
B30: (3) See "Imports and Exports" section below
B31: (4) Production + Imports – Exports
B33: Demand Calculations
B34: Domestic Production
B35: NOTES
B37: Domestic Production, XX
B38: Description | C38: Units | D38: 2021 | E38: 2022 | F38: 2023 | G38: 2024 | H38: 2025
B39: DESCRIPTION1
B40: (1) Source:
B42: Imports and Exports
B43: NOTES
B45: Imports for Consumption, XX
B46: Product Name | C46: Units | D46: HTS Code | E46: 2021 | F46: 2022 | G46: 2023 | H46: 2024 | I46: 2025
B47: DESCRIPTION1
B48: DESCRIPTION1
B49: (1) Source: USITC DataWeb, Imports for Consumption
B51: Domestic Exports, XX
B52: Product Name | C52: Units | D52: HTS Code | E52: 2021 | F52: 2022 | G52: 2023 | H52: 2024 | I52: 2025
B53: DESCRIPTION1
B54: DESCRIPTION1
B55: DESCRIPTION1
B56: (1) Source: USITC DataWeb, Domestic Exports
B60: Pricing
B61: Description | C61: Units | D61: 2021 | E61: 2022 | F61: 2023 | G61: 2024 | H61: 2025
B62: INSERT DESRIPTION1
B63: (1) Source:

Sheet Direct Template
B2: Byproduct Name
B3: (quantities are representative of quantified form listed below, unless otherwise specified)
B5: Byproduct Information
B6: Chemical Formula of Quantified Form:
B7: USGS Mineral Commodity Summary Page:
B8: Demand Data Market Specificity: | C8: Byproduct
B9: Demand Data Resolution: | C9: Domestic
B13: Major End-Use Markets1
B14: Assigned End-Use Category | C14: End-Use | D14: Demand (kt) | E14: % of Demand | G14: NOTES ON MARKETS
B18: (1) Source:
B22: Domestic Demand
B23: Calculation Schema: | C23: Primary Consumption Estimate
B24: Description | C24: Units | D24: 2021 | E24: 2022 | F24: 2023 | G24: 2024 | H24: 2025 | J24: NOTES ON DEMAND
B25: INSERT VALUE DESCRIPTION1
B26: (1) Source:
B30: Pricing
B31: Description | C31: Units | D31: 2021 | E31: 2022 | F31: 2023 | G31: 2024 | H31: 2025 | J31: NOTES ON PRICING
B32: INSERT VALUE DESCRIPTION1
B33: (1) Source:

Sheet Indirect Template
B2: Byproduct Name
B3: (quantities are representative of quantified form listed below, unless otherwise specified)
B5: Byproduct Information
B6: Chemical Formula of Quantified Form:
B7: USGS Mineral Commodity Summary Page:
B8: Demand Data Market Specificity: | C8: Byproduct
B9: Demand Data Resolution: | C9: Domestic
B13: Major End-Use Markets1
B14: Assigned End-Use Category | C14: End-Use | D14: Demand (kt) | E14: % of Demand | G14: NOTES ON MARKETS
B18: (1) Source:
B22: Domestic Demand
B23: Calculation Schema: | C23: Adjusted Consumption Estimate
B24: Description | C24: Units | D24: 2021 | E24: 2022 | F24: 2023 | G24: 2024 | H24: 2025 | J24: NOTES ON DEMAND
B25: INSERT VALUE DESCRIPTION1
B26: Scaling factor2
B27: INSERT VALUE DESCRIPTION1 | C27: kt
B28: (1) Source:
B29: (2) SOURCE AND DESCRIPTION OF SCALING FACTOR
B33: Pricing
B34: Description | C34: Units | D34: 2021 | E34: 2022 | F34: 2023 | G34: 2024 | H34: 2025 | J34: NOTES ON PRICING
B35: INSERT VALUE DESCRIPTION1
B36: (1) Source:
